Workbook
Name A: 'CODIGO-LITERAL'!$B$1:$B$5
Name ACTIVIDAD: 'CODIGO-LITERAL'!$B$6:$B$9
Name B: 'CODIGO-LITERAL'!$B$10:$B$15
Name CALIFICACION_OPERACION: 'CODIGO-LITERAL'!$B$16:$B$19
Name CAUSA_BAJA_BIEN: 'CODIGO-LITERAL'!$B$20:$B$26
Name CLAVE_OPERACION: 'CODIGO-LITERAL'!$B$27:$B$44
Name CLAVE_OPERACION_GASTO: 'CODIGO-LITERAL'!$B$45:$B$57
Name CONCEPTO_GASTO: 'CODIGO-LITERAL'!$B$58:$B$104
Name CONCEPTO_INGRESO: 'CODIGO-LITERAL'!$B$105:$B$113
Name MEDIO_UTILIZADO: 'CODIGO-LITERAL'!$B$114:$B$118
Name METODO_AMORTIZACION: 'CODIGO-LITERAL'!$B$204:$B$213
Name OPERACION_EXENTA: 'CODIGO-LITERAL'!$B$119:$B$124
Name SITUACION: 'CODIGO-LITERAL'!$B$125:$B$129
Name TIPO_BIEN: 'CODIGO-LITERAL'!$B$130:$B$149
Name TIPO_FACTURA: 'CODIGO-LITERAL'!$B$150:$B$161
Name TIPO_FACTURA_GASTO: 'CODIGO-LITERAL'!$B$191:$B$203
Name TIPO_IVA: 'CODIGO-LITERAL'!$B$172:$B$180
Name TIPO_NIF: 'CODIGO-LITERAL'!$B$162:$B$167
Name TIPO_RECARGO_EQUIVALENCIA: 'CODIGO-LITERAL'!$B$181:$B$186
Name TRIMESTRE: 'CODIGO-LITERAL'!$B$168:$B$171

Sheet INSTRUCCIONES
C4: Leyenda de colores
D7: Desplegable del que seleccionar el valor que corresponda
D8: Introducción de valor libre según el formato e instrucciones que se muestran en las ayudas de cada dato
D9: No es necesario introducir el dato
D10: Dato calculado, no es necesario modificarlo

Sheet Registrar expedidas_ingresos
A1: Autoliquidación | C1: Actividad | F1: Tipo de Factura | G1: Concepto de Ingreso | H1: Ingreso Computable | I1: Fecha Expedición | J1: Fecha Operación | K1: Identificación de la Factura | N1: NIF Destinatario | Q1: Nombre Destinatario | R1: Clave de Operación | S1: Calificación de la Operación | T1: Operación Exenta | U1: Total Factura | V1: Base Imponible | W1: Tipo de IVA | X1: Cuota IVA Repercutida | Y1: Tipo de Recargo Eq. | Z1: Cuota Recargo Eq. | AA1: Cobro (Operación Criterio de Caja de IVA y/o artículo 7.2.1º de Reglamento del IRPF) | AE1: Tipo Retención del IRPF | AF1: Importe Retenido del IRPF | AG1: Registro Acuerdo Facturación | AH1: Inmueble | AJ1: Referencia Externa
A2: Ejercicio | B2: Periodo | C2: Código | D2: Tipo | E2: Grupo o Epígrafe del IAE | K2: Serie | L2: Número | M2: Número-Final | N2: Tipo | O2: Código País | P2: Identificación | AA2: Fecha | AB2: Importe | AC2: Medio Utilizado | AD2: Identificación Medio Utilizado | AH2: Situación | AI2: Referencia Catastral
U4: =IF(AND(EXPEDIDAS_INGRESOS!S4="",EXPEDIDAS_INGRESOS!T4=""),"",IF(EXPEDIDAS_INGRESOS!S4="S1",SUM(V4,X4,Z4),V4)) | X4: =IF(OR(V4="",W4=""),"",V4*W4/100) | Z4: =IF(OR(V4="",Y4=""),"",V4*Y4/100)
U5: =IF(AND(EXPEDIDAS_INGRESOS!S5="",EXPEDIDAS_INGRESOS!T5=""),"",IF(EXPEDIDAS_INGRESOS!S5="S1",SUM(V5,X5,Z5),V5)) | Z5: =IF(OR(V5="",Y5=""),"",V5*Y5/100)
U6: =IF(AND(EXPEDIDAS_INGRESOS!S6="",EXPEDIDAS_INGRESOS!T6=""),"",IF(EXPEDIDAS_INGRESOS!S6="S1",SUM(V6,X6,Z6),V6)) | Z6: =IF(OR(V6="",Y6=""),"",V6*Y6/100)
U7: =IF(AND(EXPEDIDAS_INGRESOS!S7="",EXPEDIDAS_INGRESOS!T7=""),"",IF(EXPEDIDAS_INGRESOS!S7="S1",SUM(V7,X7,Z7),V7)) | Z7: =IF(OR(V7="",Y7=""),"",V7*Y7/100)
U8: =IF(AND(EXPEDIDAS_INGRESOS!S8="",EXPEDIDAS_INGRESOS!T8=""),"",IF(EXPEDIDAS_INGRESOS!S8="S1",SUM(V8,X8,Z8),V8)) | Z8: =IF(OR(V8="",Y8=""),"",V8*Y8/100)
U9: =IF(AND(EXPEDIDAS_INGRESOS!S9="",EXPEDIDAS_INGRESOS!T9=""),"",IF(EXPEDIDAS_INGRESOS!S9="S1",SUM(V9,X9,Z9),V9)) | Z9: =IF(OR(V9="",Y9=""),"",V9*Y9/100)
U10: =IF(AND(EXPEDIDAS_INGRESOS!S10="",EXPEDIDAS_INGRESOS!T10=""),"",IF(EXPEDIDAS_INGRESOS!S10="S1",SUM(V10,X10,Z10),V10)) | Z10: =IF(OR(V10="",Y10=""),"",V10*Y10/100)
U11: =IF(AND(EXPEDIDAS_INGRESOS!S11="",EXPEDIDAS_INGRESOS!T11=""),"",IF(EXPEDIDAS_INGRESOS!S11="S1",SUM(V11,X11,Z11),V11)) | Z11: =IF(OR(V11="",Y11=""),"",V11*Y11/100)
U12: =IF(AND(EXPEDIDAS_INGRESOS!S12="",EXPEDIDAS_INGRESOS!T12=""),"",IF(EXPEDIDAS_INGRESOS!S12="S1",SUM(V12,X12,Z12),V12)) | Z12: =IF(OR(V12="",Y12=""),"",V12*Y12/100)
U13: =IF(AND(EXPEDIDAS_INGRESOS!S13="",EXPEDIDAS_INGRESOS!T13=""),"",IF(EXPEDIDAS_INGRESOS!S13="S1",SUM(V13,X13,Z13),V13)) | Z13: =IF(OR(V13="",Y13=""),"",V13*Y13/100)
U14: =IF(AND(EXPEDIDAS_INGRESOS!S14="",EXPEDIDAS_INGRESOS!T14=""),"",IF(EXPEDIDAS_INGRESOS!S14="S1",SUM(V14,X14,Z14),V14)) | Z14: =IF(OR(V14="",Y14=""),"",V14*Y14/100)
U15: =IF(AND(EXPEDIDAS_INGRESOS!S15="",EXPEDIDAS_INGRESOS!T15=""),"",IF(EXPEDIDAS_INGRESOS!S15="S1",SUM(V15,X15,Z15),V15)) | Z15: =IF(OR(V15="",Y15=""),"",V15*Y15/100)
U16: =IF(AND(EXPEDIDAS_INGRESOS!S16="",EXPEDIDAS_INGRESOS!T16=""),"",IF(EXPEDIDAS_INGRESOS!S16="S1",SUM(V16,X16,Z16),V16)) | Z16: =IF(OR(V16="",Y16=""),"",V16*Y16/100)
... U103: =IF(AND(EXPEDIDAS_INGRESOS!S103="",EXPEDIDAS_INGRESOS!T103=""),"",IF(EXPEDIDAS_INGRESOS!S103="S1",SUM(V103,X103,Z103),V103)) | Z103: =IF(OR(V103="",Y103=""),"",V103*Y103/100)

Sheet Registrar recibidas_gastos
A1: Autoliquidación | C1: Actividad | F1: Tipo de Factura | G1: Concepto de Gasto | H1: Gasto Deducible | I1: Fecha Expedición | J1: Fecha Operación | K1: Identificación Factura del Expedidor | M1: Fecha Recepción | N1: Número Recepción | O1: Número Recepción Final | P1: NIF Expedidor | S1: Nombre Expedidor | T1: Clave de Operación | U1: Bien de Inversión | V1: Inversión del Sujeto Pasivo | W1: Deducible en Periodo Posterior | X1: Periodo Deducción | Z1: Total Factura | AA1: Base Imponible | AB1: Tipo de IVA | AC1: Cuota IVA Soportado | AD1: Cuota Deducible | AE1: Tipo de Recargo Eq. | AF1: Cuota Recargo Eq. | AG1: Pago (Operación Criterio de Caja de IVA y/o artículo 7.2.1º de Reglamento del IRPF) | AK1: Tipo Retención del IRPF | AL1: Importe Retenido del IRPF | AM1: Registro Acuerdo Facturación | AN1: Inmueble | AP1: Referencia Externa
A2: Ejercicio | B2: Periodo | C2: Código | D2: Tipo | E2: Grupo o Epígrafe del IAE | K2: (Serie-Número) | L2: Número-Final | P2: Tipo | Q2: Código País | R2: Identificación | X2: Ejercicio | Y2: Periodo | AG2: Fecha | AH2: Importe | AI2: Medio Utilizado | AJ2: Identificación Medio Utilizado | AN2: Situación | AO2: Referencia Catastral
N4: =IF(RECIBIDAS_GASTOS!F4="","",CONCATENATE(RECIBIDAS_GASTOS!F4,"-",COUNTIF(RECIBIDAS_GASTOS!F:F,RECIBIDAS_GASTOS!F4))) | O4: =IF(RECIBIDAS_GASTOS!F4="","",CONCATENATE(RECIBIDAS_GASTOS!F4,"-",COUNTIF(RECIBIDAS_GASTOS!F:F,RECIBIDAS_GASTOS!F4))) | Z4: =IF(AA4="","",IF(AND(F4="",T4=""),"",IF(OR(LEFT(T4,2)="03",LEFT(T4,2)="05",LEFT(T4,2)="09"),AA4,SUM(AA4,AC4,AF4)))) | AC4: =IF(OR(AA4="",AB4=""),"",AA4*AB4/100) | AF4: =IF(OR(AA4="",AE4=""),"",AA4*AE4/100)
N5: =IF(RECIBIDAS_GASTOS!F5="","",CONCATENATE(RECIBIDAS_GASTOS!F5,"-",COUNTIF(RECIBIDAS_GASTOS!F:F,RECIBIDAS_GASTOS!F5))) | O5: =IF(RECIBIDAS_GASTOS!F5="","",CONCATENATE(RECIBIDAS_GASTOS!F5,"-",COUNTIF(RECIBIDAS_GASTOS!F:F,RECIBIDAS_GASTOS!F5))) | Z5: =IF(AA5="","",IF(AND(F5="",T5=""),"",IF(OR(LEFT(T5,2)="03",LEFT(T5,2)="05",LEFT(T5,2)="09"),AA5,SUM(AA5,AC5,AF5)))) | AC5: =IF(OR(AA5="",AB5=""),"",AA5*AB5/100) | AF5: =IF(OR(AA5="",AE5=""),"",AA5*AE5/100)
N6: =IF(RECIBIDAS_GASTOS!F6="","",CONCATENATE(RECIBIDAS_GASTOS!F6,"-",COUNTIF(RECIBIDAS_GASTOS!F:F,RECIBIDAS_GASTOS!F6))) | O6: =IF(RECIBIDAS_GASTOS!F6="","",CONCATENATE(RECIBIDAS_GASTOS!F6,"-",COUNTIF(RECIBIDAS_GASTOS!F:F,RECIBIDAS_GASTOS!F6))) | Z6: =IF(AA6="","",IF(AND(F6="",T6=""),"",IF(OR(LEFT(T6,2)="03",LEFT(T6,2)="05",LEFT(T6,2)="09"),AA6,SUM(AA6,AC6,AF6)))) | AC6: =IF(OR(AA6="",AB6=""),"",AA6*AB6/100) | AF6: =IF(OR(AA6="",AE6=""),"",AA6*AE6/100)
N7: =IF(RECIBIDAS_GASTOS!F7="","",CONCATENATE(RECIBIDAS_GASTOS!F7,"-",COUNTIF(RECIBIDAS_GASTOS!F:F,RECIBIDAS_GASTOS!F7))) | O7: =IF(RECIBIDAS_GASTOS!F7="","",CONCATENATE(RECIBIDAS_GASTOS!F7,"-",COUNTIF(RECIBIDAS_GASTOS!F:F,RECIBIDAS_GASTOS!F7))) | Z7: =IF(AA7="","",IF(AND(F7="",T7=""),"",IF(OR(LEFT(T7,2)="03",LEFT(T7,2)="05",LEFT(T7,2)="09"),AA7,SUM(AA7,AC7,AF7)))) | AC7: =IF(OR(AA7="",AB7=""),"",AA7*AB7/100) | AF7: =IF(OR(AA7="",AE7=""),"",AA7*AE7/100)
N8: =IF(RECIBIDAS_GASTOS!F8="","",CONCATENATE(RECIBIDAS_GASTOS!F8,"-",COUNTIF(RECIBIDAS_GASTOS!F:F,RECIBIDAS_GASTOS!F8))) | O8: =IF(RECIBIDAS_GASTOS!F8="","",CONCATENATE(RECIBIDAS_GASTOS!F8,"-",COUNTIF(RECIBIDAS_GASTOS!F:F,RECIBIDAS_GASTOS!F8))) | Z8: =IF(AA8="","",IF(AND(F8="",T8=""),"",IF(OR(LEFT(T8,2)="03",LEFT(T8,2)="05",LEFT(T8,2)="09"),AA8,SUM(AA8,AC8,AF8)))) | AC8: =IF(OR(AA8="",AB8=""),"",AA8*AB8/100) | AF8: =IF(OR(AA8="",AE8=""),"",AA8*AE8/100)
N9: =IF(RECIBIDAS_GASTOS!F9="","",CONCATENATE(RECIBIDAS_GASTOS!F9,"-",COUNTIF(RECIBIDAS_GASTOS!F:F,RECIBIDAS_GASTOS!F9))) | O9: =IF(RECIBIDAS_GASTOS!F9="","",CONCATENATE(RECIBIDAS_GASTOS!F9,"-",COUNTIF(RECIBIDAS_GASTOS!F:F,RECIBIDAS_GASTOS!F9))) | Z9: =IF(AA9="","",IF(AND(F9="",T9=""),"",IF(OR(LEFT(T9,2)="03",LEFT(T9,2)="05",LEFT(T9,2)="09"),AA9,SUM(AA9,AC9,AF9)))) | AC9: =IF(OR(AA9="",AB9=""),"",AA9*AB9/100) | AF9: =IF(OR(AA9="",AE9=""),"",AA9*AE9/100)
N10: =IF(RECIBIDAS_GASTOS!F10="","",CONCATENATE(RECIBIDAS_GASTOS!F10,"-",COUNTIF(RECIBIDAS_GASTOS!F:F,RECIBIDAS_GASTOS!F10))) | O10: =IF(RECIBIDAS_GASTOS!F10="","",CONCATENATE(RECIBIDAS_GASTOS!F10,"-",COUNTIF(RECIBIDAS_GASTOS!F:F,RECIBIDAS_GASTOS!F10))) | Z10: =IF(AA10="","",IF(AND(F10="",T10=""),"",IF(OR(LEFT(T10,2)="03",LEFT(T10,2)="05",LEFT(T10,2)="09"),AA10,SUM(AA10,AC10,AF10)))) | AC10: =IF(OR(AA10="",AB10=""),"",AA10*AB10/100) | AF10: =IF(OR(AA10="",AE10=""),"",AA10*AE10/100)
N11: =IF(RECIBIDAS_GASTOS!F11="","",CONCATENATE(RECIBIDAS_GASTOS!F11,"-",COUNTIF(RECIBIDAS_GASTOS!F:F,RECIBIDAS_GASTOS!F11))) | O11: =IF(RECIBIDAS_GASTOS!F11="","",CONCATENATE(RECIBIDAS_GASTOS!F11,"-",COUNTIF(RECIBIDAS_GASTOS!F:F,RECIBIDAS_GASTOS!F11))) | Z11: =IF(AA11="","",IF(AND(F11="",T11=""),"",IF(OR(LEFT(T11,2)="03",LEFT(T11,2)="05",LEFT(T11,2)="09"),AA11,SUM(AA11,AC11,AF11)))) | AC11: =IF(OR(AA11="",AB11=""),"",AA11*AB11/100) | AF11: =IF(OR(AA11="",AE11=""),"",AA11*AE11/100)
N12: =IF(RECIBIDAS_GASTOS!F12="","",CONCATENATE(RECIBIDAS_GASTOS!F12,"-",COUNTIF(RECIBIDAS_GASTOS!F:F,RECIBIDAS_GASTOS!F12))) | O12: =IF(RECIBIDAS_GASTOS!F12="","",CONCATENATE(RECIBIDAS_GASTOS!F12,"-",COUNTIF(RECIBIDAS_GASTOS!F:F,RECIBIDAS_GASTOS!F12))) | Z12: =IF(AA12="","",IF(AND(F12="",T12=""),"",IF(OR(LEFT(T12,2)="03",LEFT(T12,2)="05",LEFT(T12,2)="09"),AA12,SUM(AA12,AC12,AF12)))) | AC12: =IF(OR(AA12="",AB12=""),"",AA12*AB12/100) | AF12: =IF(OR(AA12="",AE12=""),"",AA12*AE12/100)
N13: =IF(RECIBIDAS_GASTOS!F13="","",CONCATENATE(RECIBIDAS_GASTOS!F13,"-",COUNTIF(RECIBIDAS_GASTOS!F:F,RECIBIDAS_GASTOS!F13))) | O13: =IF(RECIBIDAS_GASTOS!F13="","",CONCATENATE(RECIBIDAS_GASTOS!F13,"-",COUNTIF(RECIBIDAS_GASTOS!F:F,RECIBIDAS_GASTOS!F13))) | Z13: =IF(AA13="","",IF(AND(F13="",T13=""),"",IF(OR(LEFT(T13,2)="03",LEFT(T13,2)="05",LEFT(T13,2)="09"),AA13,SUM(AA13,AC13,AF13)))) | AC13: =IF(OR(AA13="",AB13=""),"",AA13*AB13/100) | AF13: =IF(OR(AA13="",AE13=""),"",AA13*AE13/100)
N14: =IF(RECIBIDAS_GASTOS!F14="","",CONCATENATE(RECIBIDAS_GASTOS!F14,"-",COUNTIF(RECIBIDAS_GASTOS!F:F,RECIBIDAS_GASTOS!F14))) | O14: =IF(RECIBIDAS_GASTOS!F14="","",CONCATENATE(RECIBIDAS_GASTOS!F14,"-",COUNTIF(RECIBIDAS_GASTOS!F:F,RECIBIDAS_GASTOS!F14))) | Z14: =IF(AA14="","",IF(AND(F14="",T14=""),"",IF(OR(LEFT(T14,2)="03",LEFT(T14,2)="05",LEFT(T14,2)="09"),AA14,SUM(AA14,AC14,AF14)))) | AC14: =IF(OR(AA14="",AB14=""),"",AA14*AB14/100) | AF14: =IF(OR(AA14="",AE14=""),"",AA14*AE14/100)
N15: =IF(RECIBIDAS_GASTOS!F15="","",CONCATENATE(RECIBIDAS_GASTOS!F15,"-",COUNTIF(RECIBIDAS_GASTOS!F:F,RECIBIDAS_GASTOS!F15))) | O15: =IF(RECIBIDAS_GASTOS!F15="","",CONCATENATE(RECIBIDAS_GASTOS!F15,"-",COUNTIF(RECIBIDAS_GASTOS!F:F,RECIBIDAS_GASTOS!F15))) | Z15: =IF(AA15="","",IF(AND(F15="",T15=""),"",IF(OR(LEFT(T15,2)="03",LEFT(T15,2)="05",LEFT(T15,2)="09"),AA15,SUM(AA15,AC15,AF15)))) | AC15: =IF(OR(AA15="",AB15=""),"",AA15*AB15/100) | AF15: =IF(OR(AA15="",AE15=""),"",AA15*AE15/100)
... N103: =IF(RECIBIDAS_GASTOS!F103="","",CONCATENATE(RECIBIDAS_GASTOS!F103,"-",COUNTIF(RECIBIDAS_GASTOS!F:F,RECIBIDAS_GASTOS!F103))) | O103: =IF(RECIBIDAS_GASTOS!F103="","",CONCATENATE(RECIBIDAS_GASTOS!F103,"-",COUNTIF(RECIBIDAS_GASTOS!F:F,RECIBIDAS_GASTOS!F103))) | Z103: =IF(AA103="","",IF(AND(F103="",T103=""),"",IF(OR(LEFT(T103,2)="03",LEFT(T103,2)="05",LEFT(T103,2)="09"),AA103,SUM(AA103,AC103,AF103)))) | AC103: =IF(OR(AA103="",AB103=""),"",AA103*AB103/100) | AF103: =IF(OR(AA103="",AE103=""),"",AA103*AE103/100)

Sheet Registrar bienes de inversión
A1: Autoliquidación | C1: Actividad | F1: Tipo de Bien | G1: Descripción del Bien | I1: Fecha Inicio Utilización | J1: Valor Adquisición | K1: Valor Amortizable | L1: Método de Amortización | M1: Porcentaje de Amortización | N1: Amortización | R1: Fecha Expedición | S1: Identificación Factura del Expedidor | U1: Número Recepción | V1: Número Recepción Final | W1: NIF Expedidor | Z1: Nombre Expedidor | AA1: Año de Inicio Utilización | AE1: Regularización Anual | AH1: Baja del Bien | AJ1: Identificación de la Factura de Transmisión del Bien | AM1: Registro Acuerdo Facturación | AN1: Inmueble | AP1: Referencia Externa
A2: Ejercicio | B2: Periodo | C2: Código | D2: Tipo | E2: Grupo o Epígrafe del IAE | G2: Identificador | H2: Literal | N2: Acumulada al Inicio | O2: Cuota Resultante | P2: Acumulada al final | Q2: Pendiente | S2: (Serie-Número) | T2: Número-Final | W2: Tipo | X2: Código País | Y2: Identificación | AA2: Base Imponible | AB2: Tipo de IVA | AC2: Prorrata Definitiva | AD2: Cuota Deducible | AE2: Prorrata Definitiva | AF2: Cuota Deducible | AG2: Cuota a Regularizar | AH2: Fecha | AI2: Causa | AJ2: Serie | AK2: Número | AL2: Número-Final | AN2: Situación | AO2: Referencia Catastral

Sheet EXPEDIDAS_INGRESOS
A1: Autoliquidación | C1: Actividad | F1: Tipo de Factura | G1: Concepto de Ingreso | H1: Ingreso Computable | I1: Fecha Expedición | J1: Fecha Operación | K1: Identificación de la Factura | N1: NIF Destinatario | Q1: Nombre Destinatario | R1: Clave de Operación | S1: Calificación de la Operación | T1: Operación Exenta | U1: Total Factura | V1: Base Imponible | W1: Tipo de IVA | X1: Cuota IVA Repercutida | Y1: Tipo de Recargo Eq. | Z1: Cuota Recargo Eq. | AA1: Cobro (Operación Criterio de Caja de IVA y/o artículo 7.2.1º de Reglamento del IRPF) | AE1: Tipo Retención del IRPF | AF1: Importe Retenido del IRPF | AG1: Registro Acuerdo Facturación | AH1: Inmueble | AJ1: Refrencia Externa
A2: Ejercicio | B2: Periodo | C2: Código | D2: Tipo | E2: Grupo o Epígrafe del IAE | K2: Serie | L2: Número | M2: Número-Final | N2: Tipo | O2: Código País | P2: Identificación | AA2: Fecha | AB2: Importe | AC2: Medio Utilizado | AD2: Identificación Medio Utilizado | AH2: Situación | AI2: Referencia Catastral
A3: Decimal (4,0) | B3: Alfanumérico (2) | C3: Alfanumérico (1) | D3: Alfanumérico (2) | E3: Alfanumérico (4) | F3: Alfanumérico (2) | G3: Alfanumérico (3) | H3: Decimal(12,2) | I3: Fecha(dd/mm/yyyy) | J3: Fecha(dd/mm/yyyy) | K3: Alfanumérico (20) | L3: Alfanumérico (20) | M3: Alfanumérico (20) | N3: Alfanumérico (2) | O3: Alfanumérico (2) | P3: Alfanumérico (20) | Q3: Alfanumérico (40) | R3: Alfanumérico (2) | S3: Alfanumérico (2) | T3: Alfanumérico (2) | U3: Decimal(12,2) | V3: Decimal(12,2) | W3: Decimal(4,2) | X3: Decimal(12,2) | Y3: Decimal(4,2) | Z3: Decimal(12,2) | AA3: Fecha(dd/mm/yyyy) | AB3: Decimal(12,2) | AC3: Alfanumérico (2) | AD3: Alfanumérico (34) | AE3: Decimal(4,2) | AF3: Decimal(12,2) | AG3: Alfanumérico (15) | AH3: Alfanumérico (1) | AI3: Alfanumérico (20) | AJ3: Alfanumérico (40)
A4: =IF('Registrar expedidas_ingresos'!J4="",IF('Registrar expedidas_ingresos'!I4="","",YEAR('Registrar expedidas_ingresos'!I4)),YEAR('Registrar expedidas_ingresos'!J4)) | B4: =IF('Registrar expedidas_ingresos'!B4="","",'Registrar expedidas_ingresos'!B4) | C4: =IF('Registrar expedidas_ingresos'!C4="","",VLOOKUP(CONCATENATE("ACTIVIDAD",'Registrar expedidas_ingresos'!C4),'CODIGO-LITERAL'!C:D,2,FALSE)) | D4: =IF(OR(C4="C",C4="D"),"",IF(ISERROR(VLOOKUP(CONCATENATE(C4,'Registrar expedidas_ingresos'!D4),'CODIGO-LITERAL'!$C:$D,2,FALSE)),"",VLOOKUP(CONCATENATE(C4,'Registrar expedidas_ingresos'!D4),'CODIGO-LITERAL'!$C:$D,2,FALSE))) | E4: =IF('Registrar expedidas_ingresos'!E4="","",'Registrar expedidas_ingresos'!E4) | F4: =IF(ISERROR(VLOOKUP(CONCATENATE("TIPO FACTURA",'Registrar expedidas_ingresos'!F4),'CODIGO-LITERAL'!$C:$D,2,FALSE)),"",VLOOKUP(CONCATENATE("TIPO FACTURA",'Registrar expedidas_ingresos'!F4),'CODIGO-LITERAL'!$C:$D,2,FALSE)) | I4: =IF('Registrar expedidas_ingresos'!I4="","",'Registrar expedidas_ingresos'!I4) | J4: =IF('Registrar expedidas_ingresos'!J4="","",'Registrar expedidas_ingresos'!J4) | K4: =IF('Registrar expedidas_ingresos'!K4="","",'Registrar expedidas_ingresos'!K4) | L4: =IF('Registrar expedidas_ingresos'!L4="","",'Registrar expedidas_ingresos'!L4) | M4: =IF('Registrar expedidas_ingresos'!M4="","",'Registrar expedidas_ingresos'!M4) | N4: =IF(OR(F4="F2",LEFT('Registrar expedidas_ingresos'!N4,2)="01"),"",IF(ISERROR(VLOOKUP(CONCATENATE("TIPO NIF",'Registrar expedidas_ingresos'!N4),'CODIGO-LITERAL'!$C:$D,2,FALSE)),"",VLOOKUP(CONCATENATE("TIPO NIF",'Registrar expedidas_ingresos'!N4),'CODIGO-LITERAL'!$C:$D,2,FALSE))) | O4: =IF(OR('Registrar expedidas_ingresos'!O4="",N4="02",F4="F2"),"",'Registrar expedidas_ingresos'!O4) | P4: =IF('Registrar expedidas_ingresos'!P4="","",'Registrar expedidas_ingresos'!P4) | Q4: =IF(F4="F2","VENTAS A CONSUMIDOR FINAL",IF('Registrar expedidas_ingresos'!Q4="","",'Registrar expedidas_ingresos'!Q4)) | R4: =IF(F4="DV","02",IF(ISERROR(VLOOKUP(CONCATENATE("CLAVE OPERACION",'Registrar expedidas_ingresos'!R4),'CODIGO-LITERAL'!$C:$D,2,FALSE)),"",VLOOKUP(CONCATENATE("CLAVE OPERACION",'Registrar expedidas_ingresos'!R4),'CODIGO-LITERAL'!$C:$D,2,FALSE))) | S4: =IF(R4="03","S1", IF(R4="08","N2", IF(ISERROR(VLOOKUP(CONCATENATE("CALIFICACION OPERACION",'Registrar expedidas_ingresos'!S4),'CODIGO-LITERAL'!$C:$D,2,FALSE)),"",VLOOKUP(CONCATENATE("CALIFICACION OPERACION",'Registrar expedidas_ingresos'!S4),'CODIGO-LITERAL'!$C:$D,2,FALSE)))) | T4: =IF(R4="03","",IF(R4="08","",IF(ISERROR(VLOOKUP(CONCATENATE("OPERACION EXENTA",'Registrar expedidas_ingresos'!T4),'CODIGO-LITERAL'!$C:$D,2,FALSE)),"",VLOOKUP(CONCATENATE("OPERACION EXENTA",'Registrar expedidas_ingresos'!T4),'CODIGO-LITERAL'!$C:$D,2,FALSE)))) | U4: =IF(AND(S4="",T4=""),"",IF(S4="S1",ROUND(SUM(V4,X4,Z4),2),ROUND(V4,2))) | V4: =IF('Registrar expedidas_ingresos'!V4="","",ROUND('Registrar expedidas_ingresos'!V4,2)) | W4: =IF(S4="S2",0,IF('Registrar expedidas_ingresos'!W4="","",'Registrar expedidas_ingresos'!W4)) | X4: =IF(S4="S2",0,IF('Registrar expedidas_ingresos'!X4="","",ROUND('Registrar expedidas_ingresos'!X4,2))) | Y4: =IF('Registrar expedidas_ingresos'!Y4="","",'Registrar expedidas_ingresos'!Y4) | Z4: =IF('Registrar expedidas_ingresos'!Z4="","",ROUND('Registrar expedidas_ingresos'!Z4,2)) | AA4: =IF(R4<>"07","",IF('Registrar expedidas_ingresos'!AA4="","",'Registrar expedidas_ingresos'!AA4)) | AB4: =IF(R4<>"07","",IF('Registrar expedidas_ingresos'!AB4="","",'Registrar expedidas_ingresos'!AB4)) | AC4: =IF(R4<>"07","",IF(ISERROR(VLOOKUP(CONCATENATE("MEDIO UTILIZADO",'Registrar expedidas_ingresos'!AC4),'CODIGO-LITERAL'!$C:$D,2,FALSE)),"",VLOOKUP(CONCATENATE("MEDIO UTILIZADO",'Registrar expedidas_ingresos'!AC4),'CODIGO-LITERAL'!$C:$D,2,FALSE))) | AD4: =IF(R4<>"07","",IF('Registrar expedidas_ingresos'!AD4="","",'Registrar expedidas_ingresos'!AD4)) | AG4: =IF('Registrar expedidas_ingresos'!AG4="","",'Registrar expedidas_ingresos'!AG4) | AH4: =IF(ISERROR(VLOOKUP(CONCATENATE("SITUACION",'Registrar expedidas_ingresos'!AH4),'CODIGO-LITERAL'!$C:$D,2,FALSE)),"",VLOOKUP(CONCATENATE("SITUACION",'Registrar expedidas_ingresos'!AH4),'CODIGO-LITERAL'!$C:$D,2,FALSE)) | AI4: =IF('Registrar expedidas_ingresos'!AI4="","",'Registrar expedidas_ingresos'!AI4) | AJ4: =IF('Registrar expedidas_ingresos'!AJ4="","",'Registrar expedidas_ingresos'!AJ4)
A5: =IF('Registrar expedidas_ingresos'!J5="",IF('Registrar expedidas_ingresos'!I5="","",YEAR('Registrar expedidas_ingresos'!I5)),YEAR('Registrar expedidas_ingresos'!J5)) | B5: =IF('Registrar expedidas_ingresos'!B5="","",'Registrar expedidas_ingresos'!B5) | C5: =IF('Registrar expedidas_ingresos'!C5="","",VLOOKUP(CONCATENATE("ACTIVIDAD",'Registrar expedidas_ingresos'!C5),'CODIGO-LITERAL'!C:D,2,FALSE)) | D5: =IF(OR(C5="C",C5="D"),"",IF(ISERROR(VLOOKUP(CONCATENATE(C5,'Registrar expedidas_ingresos'!D5),'CODIGO-LITERAL'!$C:$D,2,FALSE)),"",VLOOKUP(CONCATENATE(C5,'Registrar expedidas_ingresos'!D5),'CODIGO-LITERAL'!$C:$D,2,FALSE))) | E5: =IF('Registrar expedidas_ingresos'!E5="","",'Registrar expedidas_ingresos'!E5) | F5: =IF(ISERROR(VLOOKUP(CONCATENATE("TIPO FACTURA",'Registrar expedidas_ingresos'!F5),'CODIGO-LITERAL'!$C:$D,2,FALSE)),"",VLOOKUP(CONCATENATE("TIPO FACTURA",'Registrar expedidas_ingresos'!F5),'CODIGO-LITERAL'!$C:$D,2,FALSE)) | I5: =IF('Registrar expedidas_ingresos'!I5="","",'Registrar expedidas_ingresos'!I5) | J5: =IF('Registrar expedidas_ingresos'!J5="","",'Registrar expedidas_ingresos'!J5) | K5: =IF('Registrar expedidas_ingresos'!K5="","",'Registrar expedidas_ingresos'!K5) | L5: =IF('Registrar expedidas_ingresos'!L5="","",'Registrar expedidas_ingresos'!L5) | M5: =IF('Registrar expedidas_ingresos'!M5="","",'Registrar expedidas_ingresos'!M5) | N5: =IF(OR(F5="F2",LEFT('Registrar expedidas_ingresos'!N5,2)="01"),"",IF(ISERROR(VLOOKUP(CONCATENATE("TIPO NIF",'Registrar expedidas_ingresos'!N5),'CODIGO-LITERAL'!$C:$D,2,FALSE)),"",VLOOKUP(CONCATENATE("TIPO NIF",'Registrar expedidas_ingresos'!N5),'CODIGO-LITERAL'!$C:$D,2,FALSE))) | O5: =IF(OR('Registrar expedidas_ingresos'!O5="",N5="02",F5="F2"),"",'Registrar expedidas_ingresos'!O5) | P5: =IF('Registrar expedidas_ingresos'!P5="","",'Registrar expedidas_ingresos'!P5) | Q5: =IF(F5="F2","VENTAS A CONSUMIDOR FINAL",IF('Registrar expedidas_ingresos'!Q5="","",'Registrar expedidas_ingresos'!Q5)) | R5: =IF(F5="DV","02",IF(ISERROR(VLOOKUP(CONCATENATE("CLAVE OPERACION",'Registrar expedidas_ingresos'!R5),'CODIGO-LITERAL'!$C:$D,2,FALSE)),"",VLOOKUP(CONCATENATE("CLAVE OPERACION",'Registrar expedidas_ingresos'!R5),'CODIGO-LITERAL'!$C:$D,2,FALSE))) | S5: =IF(R5="03","S1", IF(R5="08","N2", IF(ISERROR(VLOOKUP(CONCATENATE("CALIFICACION OPERACION",'Registrar expedidas_ingresos'!S5),'CODIGO-LITERAL'!$C:$D,2,FALSE)),"",VLOOKUP(CONCATENATE("CALIFICACION OPERACION",'Registrar expedidas_ingresos'!S5),'CODIGO-LITERAL'!$C:$D,2,FALSE)))) | T5: =IF(R5="03","",IF(R5="08","",IF(ISERROR(VLOOKUP(CONCATENATE("OPERACION EXENTA",'Registrar expedidas_ingresos'!T5),'CODIGO-LITERAL'!$C:$D,2,FALSE)),"",VLOOKUP(CONCATENATE("OPERACION EXENTA",'Registrar expedidas_ingresos'!T5),'CODIGO-LITERAL'!$C:$D,2,FALSE)))) | U5: =IF(AND(S5="",T5=""),"",IF(S5="S1",ROUND(SUM(V5,X5,Z5),2),ROUND(V5,2))) | V5: =IF('Registrar expedidas_ingresos'!V5="","",ROUND('Registrar expedidas_ingresos'!V5,2)) | W5: =IF(S5="S2",0,IF('Registrar expedidas_ingresos'!W5="","",'Registrar expedidas_ingresos'!W5)) | X5: =IF(S5="S2",0,IF('Registrar expedidas_ingresos'!X5="","",ROUND('Registrar expedidas_ingresos'!X5,2))) | Y5: =IF('Registrar expedidas_ingresos'!Y5="","",'Registrar expedidas_ingresos'!Y5) | Z5: =IF('Registrar expedidas_ingresos'!Z5="","",ROUND('Registrar expedidas_ingresos'!Z5,2)) | AA5: =IF(R5<>"07","",IF('Registrar expedidas_ingresos'!AA5="","",'Registrar expedidas_ingresos'!AA5)) | AB5: =IF(R5<>"07","",IF('Registrar expedidas_ingresos'!AB5="","",'Registrar expedidas_ingresos'!AB5)) | AC5: =IF(R5<>"07","",IF(ISERROR(VLOOKUP(CONCATENATE("MEDIO UTILIZADO",'Registrar expedidas_ingresos'!AC5),'CODIGO-LITERAL'!$C:$D,2,FALSE)),"",VLOOKUP(CONCATENATE("MEDIO UTILIZADO",'Registrar expedidas_ingresos'!AC5),'CODIGO-LITERAL'!$C:$D,2,FALSE))) | AD5: =IF(R5<>"07","",IF('Registrar expedidas_ingresos'!AD5="","",'Registrar expedidas_ingresos'!AD5)) | AG5: =IF('Registrar expedidas_ingresos'!AG5="","",'Registrar expedidas_ingresos'!AG5) | AH5: =IF(ISERROR(VLOOKUP(CONCATENATE("SITUACION",'Registrar expedidas_ingresos'!AH5),'CODIGO-LITERAL'!$C:$D,2,FALSE)),"",VLOOKUP(CONCATENATE("SITUACION",'Registrar expedidas_ingresos'!AH5),'CODIGO-LITERAL'!$C:$D,2,FALSE)) | AI5: =IF('Registrar expedidas_ingresos'!AI5="","",'Registrar expedidas_ingresos'!AI5) | AJ5: =IF('Registrar expedidas_ingresos'!AJ5="","",'Registrar expedidas_ingresos'!AJ5)
A6: =IF('Registrar expedidas_ingresos'!J6="",IF('Registrar expedidas_ingresos'!I6="","",YEAR('Registrar expedidas_ingresos'!I6)),YEAR('Registrar expedidas_ingresos'!J6)) | B6: =IF('Registrar expedidas_ingresos'!B6="","",'Registrar expedidas_ingresos'!B6) | C6: =IF('Registrar expedidas_ingresos'!C6="","",VLOOKUP(CONCATENATE("ACTIVIDAD",'Registrar expedidas_ingresos'!C6),'CODIGO-LITERAL'!C:D,2,FALSE)) | D6: =IF(OR(C6="C",C6="D"),"",IF(ISERROR(VLOOKUP(CONCATENATE(C6,'Registrar expedidas_ingresos'!D6),'CODIGO-LITERAL'!$C:$D,2,FALSE)),"",VLOOKUP(CONCATENATE(C6,'Registrar expedidas_ingresos'!D6),'CODIGO-LITERAL'!$C:$D,2,FALSE))) | E6: =IF('Registrar expedidas_ingresos'!E6="","",'Registrar expedidas_ingresos'!E6) | F6: =IF(ISERROR(VLOOKUP(CONCATENATE("TIPO FACTURA",'Registrar expedidas_ingresos'!F6),'CODIGO-LITERAL'!$C:$D,2,FALSE)),"",VLOOKUP(CONCATENATE("TIPO FACTURA",'Registrar expedidas_ingresos'!F6),'CODIGO-LITERAL'!$C:$D,2,FALSE)) | I6: =IF('Registrar expedidas_ingresos'!I6="","",'Registrar expedidas_ingresos'!I6) | J6: =IF('Registrar expedidas_ingresos'!J6="","",'Registrar expedidas_ingresos'!J6) | K6: =IF('Registrar expedidas_ingresos'!K6="","",'Registrar expedidas_ingresos'!K6) | L6: =IF('Registrar expedidas_ingresos'!L6="","",'Registrar expedidas_ingresos'!L6) | M6: =IF('Registrar expedidas_ingresos'!M6="","",'Registrar expedidas_ingresos'!M6) | N6: =IF(OR(F6="F2",LEFT('Registrar expedidas_ingresos'!N6,2)="01"),"",IF(ISERROR(VLOOKUP(CONCATENATE("TIPO NIF",'Registrar expedidas_ingresos'!N6),'CODIGO-LITERAL'!$C:$D,2,FALSE)),"",VLOOKUP(CONCATENATE("TIPO NIF",'Registrar expedidas_ingresos'!N6),'CODIGO-LITERAL'!$C:$D,2,FALSE))) | O6: =IF(OR('Registrar expedidas_ingresos'!O6="",N6="02",F6="F2"),"",'Registrar expedidas_ingresos'!O6) | P6: =IF('Registrar expedidas_ingresos'!P6="","",'Registrar expedidas_ingresos'!P6) | Q6: =IF(F6="F2","VENTAS A CONSUMIDOR FINAL",IF('Registrar expedidas_ingresos'!Q6="","",'Registrar expedidas_ingresos'!Q6)) | R6: =IF(F6="DV","02",IF(ISERROR(VLOOKUP(CONCATENATE("CLAVE OPERACION",'Registrar expedidas_ingresos'!R6),'CODIGO-LITERAL'!$C:$D,2,FALSE)),"",VLOOKUP(CONCATENATE("CLAVE OPERACION",'Registrar expedidas_ingresos'!R6),'CODIGO-LITERAL'!$C:$D,2,FALSE))) | S6: =IF(R6="03","S1", IF(R6="08","N2", IF(ISERROR(VLOOKUP(CONCATENATE("CALIFICACION OPERACION",'Registrar expedidas_ingresos'!S6),'CODIGO-LITERAL'!$C:$D,2,FALSE)),"",VLOOKUP(CONCATENATE("CALIFICACION OPERACION",'Registrar expedidas_ingresos'!S6),'CODIGO-LITERAL'!$C:$D,2,FALSE)))) | T6: =IF(R6="03","",IF(R6="08","",IF(ISERROR(VLOOKUP(CONCATENATE("OPERACION EXENTA",'Registrar expedidas_ingresos'!T6),'CODIGO-LITERAL'!$C:$D,2,FALSE)),"",VLOOKUP(CONCATENATE("OPERACION EXENTA",'Registrar expedidas_ingresos'!T6),'CODIGO-LITERAL'!$C:$D,2,FALSE)))) | U6: =IF(AND(S6="",T6=""),"",IF(S6="S1",ROUND(SUM(V6,X6,Z6),2),ROUND(V6,2))) | V6: =IF('Registrar expedidas_ingresos'!V6="","",ROUND('Registrar expedidas_ingresos'!V6,2)) | W6: =IF(S6="S2",0,IF('Registrar expedidas_ingresos'!W6="","",'Registrar expedidas_ingresos'!W6)) | X6: =IF(S6="S2",0,IF('Registrar expedidas_ingresos'!X6="","",ROUND('Registrar expedidas_ingresos'!X6,2))) | Y6: =IF('Registrar expedidas_ingresos'!Y6="","",'Registrar expedidas_ingresos'!Y6) | Z6: =IF('Registrar expedidas_ingresos'!Z6="","",ROUND('Registrar expedidas_ingresos'!Z6,2)) | AA6: =IF(R6<>"07","",IF('Registrar expedidas_ingresos'!AA6="","",'Registrar expedidas_ingresos'!AA6)) | AB6: =IF(R6<>"07","",IF('Registrar expedidas_ingresos'!AB6="","",'Registrar expedidas_ingresos'!AB6)) | AC6: =IF(R6<>"07","",IF(ISERROR(VLOOKUP(CONCATENATE("MEDIO UTILIZADO",'Registrar expedidas_ingresos'!AC6),'CODIGO-LITERAL'!$C:$D,2,FALSE)),"",VLOOKUP(CONCATENATE("MEDIO UTILIZADO",'Registrar expedidas_ingresos'!AC6),'CODIGO-LITERAL'!$C:$D,2,FALSE))) | AD6: =IF(R6<>"07","",IF('Registrar expedidas_ingresos'!AD6="","",'Registrar expedidas_ingresos'!AD6)) | AG6: =IF('Registrar expedidas_ingresos'!AG6="","",'Registrar expedidas_ingresos'!AG6) | AH6: =IF(ISERROR(VLOOKUP(CONCATENATE("SITUACION",'Registrar expedidas_ingresos'!AH6),'CODIGO-LITERAL'!$C:$D,2,FALSE)),"",VLOOKUP(CONCATENATE("SITUACION",'Registrar expedidas_ingresos'!AH6),'CODIGO-LITERAL'!$C:$D,2,FALSE)) | AI6: =IF('Registrar expedidas_ingresos'!AI6="","",'Registrar expedidas_ingresos'!AI6) | AJ6: =IF('Registrar expedidas_ingresos'!AJ6="","",'Registrar expedidas_ingresos'!AJ6)
A7: =IF('Registrar expedidas_ingresos'!J7="",IF('Registrar expedidas_ingresos'!I7="","",YEAR('Registrar expedidas_ingresos'!I7)),YEAR('Registrar expedidas_ingresos'!J7)) | B7: =IF('Registrar expedidas_ingresos'!B7="","",'Registrar expedidas_ingresos'!B7) | C7: =IF('Registrar expedidas_ingresos'!C7="","",VLOOKUP(CONCATENATE("ACTIVIDAD",'Registrar expedidas_ingresos'!C7),'CODIGO-LITERAL'!C:D,2,FALSE)) | D7: =IF(OR(C7="C",C7="D"),"",IF(ISERROR(VLOOKUP(CONCATENATE(C7,'Registrar expedidas_ingresos'!D7),'CODIGO-LITERAL'!$C:$D,2,FALSE)),"",VLOOKUP(CONCATENATE(C7,'Registrar expedidas_ingresos'!D7),'CODIGO-LITERAL'!$C:$D,2,FALSE))) | E7: =IF('Registrar expedidas_ingresos'!E7="","",'Registrar expedidas_ingresos'!E7) | F7: =IF(ISERROR(VLOOKUP(CONCATENATE("TIPO FACTURA",'Registrar expedidas_ingresos'!F7),'CODIGO-LITERAL'!$C:$D,2,FALSE)),"",VLOOKUP(CONCATENATE("TIPO FACTURA",'Registrar expedidas_ingresos'!F7),'CODIGO-LITERAL'!$C:$D,2,FALSE)) | I7: =IF('Registrar expedidas_ingresos'!I7="","",'Registrar expedidas_ingresos'!I7) | J7: =IF('Registrar expedidas_ingresos'!J7="","",'Registrar expedidas_ingresos'!J7) | K7: =IF('Registrar expedidas_ingresos'!K7="","",'Registrar expedidas_ingresos'!K7) | L7: =IF('Registrar expedidas_ingresos'!L7="","",'Registrar expedidas_ingresos'!L7) | M7: =IF('Registrar expedidas_ingresos'!M7="","",'Registrar expedidas_ingresos'!M7) | N7: =IF(OR(F7="F2",LEFT('Registrar expedidas_ingresos'!N7,2)="01"),"",IF(ISERROR(VLOOKUP(CONCATENATE("TIPO NIF",'Registrar expedidas_ingresos'!N7),'CODIGO-LITERAL'!$C:$D,2,FALSE)),"",VLOOKUP(CONCATENATE("TIPO NIF",'Registrar expedidas_ingresos'!N7),'CODIGO-LITERAL'!$C:$D,2,FALSE))) | O7: =IF(OR('Registrar expedidas_ingresos'!O7="",N7="02",F7="F2"),"",'Registrar expedidas_ingresos'!O7) | P7: =IF('Registrar expedidas_ingresos'!P7="","",'Registrar expedidas_ingresos'!P7) | Q7: =IF(F7="F2","VENTAS A CONSUMIDOR FINAL",IF('Registrar expedidas_ingresos'!Q7="","",'Registrar expedidas_ingresos'!Q7)) | R7: =IF(F7="DV","02",IF(ISERROR(VLOOKUP(CONCATENATE("CLAVE OPERACION",'Registrar expedidas_ingresos'!R7),'CODIGO-LITERAL'!$C:$D,2,FALSE)),"",VLOOKUP(CONCATENATE("CLAVE OPERACION",'Registrar expedidas_ingresos'!R7),'CODIGO-LITERAL'!$C:$D,2,FALSE))) | S7: =IF(R7="03","S1", IF(R7="08","N2", IF(ISERROR(VLOOKUP(CONCATENATE("CALIFICACION OPERACION",'Registrar expedidas_ingresos'!S7),'CODIGO-LITERAL'!$C:$D,2,FALSE)),"",VLOOKUP(CONCATENATE("CALIFICACION OPERACION",'Registrar expedidas_ingresos'!S7),'CODIGO-LITERAL'!$C:$D,2,FALSE)))) | T7: =IF(R7="03","",IF(R7="08","",IF(ISERROR(VLOOKUP(CONCATENATE("OPERACION EXENTA",'Registrar expedidas_ingresos'!T7),'CODIGO-LITERAL'!$C:$D,2,FALSE)),"",VLOOKUP(CONCATENATE("OPERACION EXENTA",'Registrar expedidas_ingresos'!T7),'CODIGO-LITERAL'!$C:$D,2,FALSE)))) | U7: =IF(AND(S7="",T7=""),"",IF(S7="S1",ROUND(SUM(V7,X7,Z7),2),ROUND(V7,2))) | V7: =IF('Registrar expedidas_ingresos'!V7="","",ROUND('Registrar expedidas_ingresos'!V7,2)) | W7: =IF(S7="S2",0,IF('Registrar expedidas_ingresos'!W7="","",'Registrar expedidas_ingresos'!W7)) | X7: =IF(S7="S2",0,IF('Registrar expedidas_ingresos'!X7="","",ROUND('Registrar expedidas_ingresos'!X7,2))) | Y7: =IF('Registrar expedidas_ingresos'!Y7="","",'Registrar expedidas_ingresos'!Y7) | Z7: =IF('Registrar expedidas_ingresos'!Z7="","",ROUND('Registrar expedidas_ingresos'!Z7,2)) | AA7: =IF(R7<>"07","",IF('Registrar expedidas_ingresos'!AA7="","",'Registrar expedidas_ingresos'!AA7)) | AB7: =IF(R7<>"07","",IF('Registrar expedidas_ingresos'!AB7="","",'Registrar expedidas_ingresos'!AB7)) | AC7: =IF(R7<>"07","",IF(ISERROR(VLOOKUP(CONCATENATE("MEDIO UTILIZADO",'Registrar expedidas_ingresos'!AC7),'CODIGO-LITERAL'!$C:$D,2,FALSE)),"",VLOOKUP(CONCATENATE("MEDIO UTILIZADO",'Registrar expedidas_ingresos'!AC7),'CODIGO-LITERAL'!$C:$D,2,FALSE))) | AD7: =IF(R7<>"07","",IF('Registrar expedidas_ingresos'!AD7="","",'Registrar expedidas_ingresos'!AD7)) | AG7: =IF('Registrar expedidas_ingresos'!AG7="","",'Registrar expedidas_ingresos'!AG7) | AH7: =IF(ISERROR(VLOOKUP(CONCATENATE("SITUACION",'Registrar expedidas_ingresos'!AH7),'CODIGO-LITERAL'!$C:$D,2,FALSE)),"",VLOOKUP(CONCATENATE("SITUACION",'Registrar expedidas_ingresos'!AH7),'CODIGO-LITERAL'!$C:$D,2,FALSE)) | AI7: =IF('Registrar expedidas_ingresos'!AI7="","",'Registrar expedidas_ingresos'!AI7) | AJ7: =IF('Registrar expedidas_ingresos'!AJ7="","",'Registrar expedidas_ingresos'!AJ7)
A8: =IF('Registrar expedidas_ingresos'!J8="",IF('Registrar expedidas_ingresos'!I8="","",YEAR('Registrar expedidas_ingresos'!I8)),YEAR('Registrar expedidas_ingresos'!J8)) | B8: =IF('Registrar expedidas_ingresos'!B8="","",'Registrar expedidas_ingresos'!B8) | C8: =IF('Registrar expedidas_ingresos'!C8="","",VLOOKUP(CONCATENATE("ACTIVIDAD",'Registrar expedidas_ingresos'!C8),'CODIGO-LITERAL'!C:D,2,FALSE)) | D8: =IF(OR(C8="C",C8="D"),"",IF(ISERROR(VLOOKUP(CONCATENATE(C8,'Registrar expedidas_ingresos'!D8),'CODIGO-LITERAL'!$C:$D,2,FALSE)),"",VLOOKUP(CONCATENATE(C8,'Registrar expedidas_ingresos'!D8),'CODIGO-LITERAL'!$C:$D,2,FALSE))) | E8: =IF('Registrar expedidas_ingresos'!E8="","",'Registrar expedidas_ingresos'!E8) | F8: =IF(ISERROR(VLOOKUP(CONCATENATE("TIPO FACTURA",'Registrar expedidas_ingresos'!F8),'CODIGO-LITERAL'!$C:$D,2,FALSE)),"",VLOOKUP(CONCATENATE("TIPO FACTURA",'Registrar expedidas_ingresos'!F8),'CODIGO-LITERAL'!$C:$D,2,FALSE)) | I8: =IF('Registrar expedidas_ingresos'!I8="","",'Registrar expedidas_ingresos'!I8) | J8: =IF('Registrar expedidas_ingresos'!J8="","",'Registrar expedidas_ingresos'!J8) | K8: =IF('Registrar expedidas_ingresos'!K8="","",'Registrar expedidas_ingresos'!K8) | L8: =IF('Registrar expedidas_ingresos'!L8="","",'Registrar expedidas_ingresos'!L8) | M8: =IF('Registrar expedidas_ingresos'!M8="","",'Registrar expedidas_ingresos'!M8) | N8: =IF(OR(F8="F2",LEFT('Registrar expedidas_ingresos'!N8,2)="01"),"",IF(ISERROR(VLOOKUP(CONCATENATE("TIPO NIF",'Registrar expedidas_ingresos'!N8),'CODIGO-LITERAL'!$C:$D,2,FALSE)),"",VLOOKUP(CONCATENATE("TIPO NIF",'Registrar expedidas_ingresos'!N8),'CODIGO-LITERAL'!$C:$D,2,FALSE))) | O8: =IF(OR('Registrar expedidas_ingresos'!O8="",N8="02",F8="F2"),"",'Registrar expedidas_ingresos'!O8) | P8: =IF('Registrar expedidas_ingresos'!P8="","",'Registrar expedidas_ingresos'!P8) | Q8: =IF(F8="F2","VENTAS A CONSUMIDOR FINAL",IF('Registrar expedidas_ingresos'!Q8="","",'Registrar expedidas_ingresos'!Q8)) | R8: =IF(F8="DV","02",IF(ISERROR(VLOOKUP(CONCATENATE("CLAVE OPERACION",'Registrar expedidas_ingresos'!R8),'CODIGO-LITERAL'!$C:$D,2,FALSE)),"",VLOOKUP(CONCATENATE("CLAVE OPERACION",'Registrar expedidas_ingresos'!R8),'CODIGO-LITERAL'!$C:$D,2,FALSE))) | S8: =IF(R8="03","S1", IF(R8="08","N2", IF(ISERROR(VLOOKUP(CONCATENATE("CALIFICACION OPERACION",'Registrar expedidas_ingresos'!S8),'CODIGO-LITERAL'!$C:$D,2,FALSE)),"",VLOOKUP(CONCATENATE("CALIFICACION OPERACION",'Registrar expedidas_ingresos'!S8),'CODIGO-LITERAL'!$C:$D,2,FALSE)))) | T8: =IF(R8="03","",IF(R8="08","",IF(ISERROR(VLOOKUP(CONCATENATE("OPERACION EXENTA",'Registrar expedidas_ingresos'!T8),'CODIGO-LITERAL'!$C:$D,2,FALSE)),"",VLOOKUP(CONCATENATE("OPERACION EXENTA",'Registrar expedidas_ingresos'!T8),'CODIGO-LITERAL'!$C:$D,2,FALSE)))) | U8: =IF(AND(S8="",T8=""),"",IF(S8="S1",ROUND(SUM(V8,X8,Z8),2),ROUND(V8,2))) | V8: =IF('Registrar expedidas_ingresos'!V8="","",ROUND('Registrar expedidas_ingresos'!V8,2)) | W8: =IF(S8="S2",0,IF('Registrar expedidas_ingresos'!W8="","",'Registrar expedidas_ingresos'!W8)) | X8: =IF(S8="S2",0,IF('Registrar expedidas_ingresos'!X8="","",ROUND('Registrar expedidas_ingresos'!X8,2))) | Y8: =IF('Registrar expedidas_ingresos'!Y8="","",'Registrar expedidas_ingresos'!Y8) | Z8: =IF('Registrar expedidas_ingresos'!Z8="","",ROUND('Registrar expedidas_ingresos'!Z8,2)) | AA8: =IF(R8<>"07","",IF('Registrar expedidas_ingresos'!AA8="","",'Registrar expedidas_ingresos'!AA8)) | AB8: =IF(R8<>"07","",IF('Registrar expedidas_ingresos'!AB8="","",'Registrar expedidas_ingresos'!AB8)) | AC8: =IF(R8<>"07","",IF(ISERROR(VLOOKUP(CONCATENATE("MEDIO UTILIZADO",'Registrar expedidas_ingresos'!AC8),'CODIGO-LITERAL'!$C:$D,2,FALSE)),"",VLOOKUP(CONCATENATE("MEDIO UTILIZADO",'Registrar expedidas_ingresos'!AC8),'CODIGO-LITERAL'!$C:$D,2,FALSE))) | AD8: =IF(R8<>"07","",IF('Registrar expedidas_ingresos'!AD8="","",'Registrar expedidas_ingresos'!AD8)) | AG8: =IF('Registrar expedidas_ingresos'!AG8="","",'Registrar expedidas_ingresos'!AG8) | AH8: =IF(ISERROR(VLOOKUP(CONCATENATE("SITUACION",'Registrar expedidas_ingresos'!AH8),'CODIGO-LITERAL'!$C:$D,2,FALSE)),"",VLOOKUP(CONCATENATE("SITUACION",'Registrar expedidas_ingresos'!AH8),'CODIGO-LITERAL'!$C:$D,2,FALSE)) | AI8: =IF('Registrar expedidas_ingresos'!AI8="","",'Registrar expedidas_ingresos'!AI8) | AJ8: =IF('Registrar expedidas_ingresos'!AJ8="","",'Registrar expedidas_ingresos'!AJ8)
A9: =IF('Registrar expedidas_ingresos'!J9="",IF('Registrar expedidas_ingresos'!I9="","",YEAR('Registrar expedidas_ingresos'!I9)),YEAR('Registrar expedidas_ingresos'!J9)) | B9: =IF('Registrar expedidas_ingresos'!B9="","",'Registrar expedidas_ingresos'!B9) | C9: =IF('Registrar expedidas_ingresos'!C9="","",VLOOKUP(CONCATENATE("ACTIVIDAD",'Registrar expedidas_ingresos'!C9),'CODIGO-LITERAL'!C:D,2,FALSE)) | D9: =IF(OR(C9="C",C9="D"),"",IF(ISERROR(VLOOKUP(CONCATENATE(C9,'Registrar expedidas_ingresos'!D9),'CODIGO-LITERAL'!$C:$D,2,FALSE)),"",VLOOKUP(CONCATENATE(C9,'Registrar expedidas_ingresos'!D9),'CODIGO-LITERAL'!$C:$D,2,FALSE))) | E9: =IF('Registrar expedidas_ingresos'!E9="","",'Registrar expedidas_ingresos'!E9) | F9: =IF(ISERROR(VLOOKUP(CONCATENATE("TIPO FACTURA",'Registrar expedidas_ingresos'!F9),'CODIGO-LITERAL'!$C:$D,2,FALSE)),"",VLOOKUP(CONCATENATE("TIPO FACTURA",'Registrar expedidas_ingresos'!F9),'CODIGO-LITERAL'!$C:$D,2,FALSE)) | I9: =IF('Registrar expedidas_ingresos'!I9="","",'Registrar expedidas_ingresos'!I9) | J9: =IF('Registrar expedidas_ingresos'!J9="","",'Registrar expedidas_ingresos'!J9) | K9: =IF('Registrar expedidas_ingresos'!K9="","",'Registrar expedidas_ingresos'!K9) | L9: =IF('Registrar expedidas_ingresos'!L9="","",'Registrar expedidas_ingresos'!L9) | M9: =IF('Registrar expedidas_ingresos'!M9="","",'Registrar expedidas_ingresos'!M9) | N9: =IF(OR(F9="F2",LEFT('Registrar expedidas_ingresos'!N9,2)="01"),"",IF(ISERROR(VLOOKUP(CONCATENATE("TIPO NIF",'Registrar expedidas_ingresos'!N9),'CODIGO-LITERAL'!$C:$D,2,FALSE)),"",VLOOKUP(CONCATENATE("TIPO NIF",'Registrar expedidas_ingresos'!N9),'CODIGO-LITERAL'!$C:$D,2,FALSE))) | O9: =IF(OR('Registrar expedidas_ingresos'!O9="",N9="02",F9="F2"),"",'Registrar expedidas_ingresos'!O9) | P9: =IF('Registrar expedidas_ingresos'!P9="","",'Registrar expedidas_ingresos'!P9) | Q9: =IF(F9="F2","VENTAS A CONSUMIDOR FINAL",IF('Registrar expedidas_ingresos'!Q9="","",'Registrar expedidas_ingresos'!Q9)) | R9: =IF(F9="DV","02",IF(ISERROR(VLOOKUP(CONCATENATE("CLAVE OPERACION",'Registrar expedidas_ingresos'!R9),'CODIGO-LITERAL'!$C:$D,2,FALSE)),"",VLOOKUP(CONCATENATE("CLAVE OPERACION",'Registrar expedidas_ingresos'!R9),'CODIGO-LITERAL'!$C:$D,2,FALSE))) | S9: =IF(R9="03","S1", IF(R9="08","N2", IF(ISERROR(VLOOKUP(CONCATENATE("CALIFICACION OPERACION",'Registrar expedidas_ingresos'!S9),'CODIGO-LITERAL'!$C:$D,2,FALSE)),"",VLOOKUP(CONCATENATE("CALIFICACION OPERACION",'Registrar expedidas_ingresos'!S9),'CODIGO-LITERAL'!$C:$D,2,FALSE)))) | T9: =IF(R9="03","",IF(R9="08","",IF(ISERROR(VLOOKUP(CONCATENATE("OPERACION EXENTA",'Registrar expedidas_ingresos'!T9),'CODIGO-LITERAL'!$C:$D,2,FALSE)),"",VLOOKUP(CONCATENATE("OPERACION EXENTA",'Registrar expedidas_ingresos'!T9),'CODIGO-LITERAL'!$C:$D,2,FALSE)))) | U9: =IF(AND(S9="",T9=""),"",IF(S9="S1",ROUND(SUM(V9,X9,Z9),2),ROUND(V9,2))) | V9: =IF('Registrar expedidas_ingresos'!V9="","",ROUND('Registrar expedidas_ingresos'!V9,2)) | W9: =IF(S9="S2",0,IF('Registrar expedidas_ingresos'!W9="","",'Registrar expedidas_ingresos'!W9)) | X9: =IF(S9="S2",0,IF('Registrar expedidas_ingresos'!X9="","",ROUND('Registrar expedidas_ingresos'!X9,2))) | Y9: =IF('Registrar expedidas_ingresos'!Y9="","",'Registrar expedidas_ingresos'!Y9) | Z9: =IF('Registrar expedidas_ingresos'!Z9="","",ROUND('Registrar expedidas_ingresos'!Z9,2)) | AA9: =IF(R9<>"07","",IF('Registrar expedidas_ingresos'!AA9="","",'Registrar expedidas_ingresos'!AA9)) | AB9: =IF(R9<>"07","",IF('Registrar expedidas_ingresos'!AB9="","",'Registrar expedidas_ingresos'!AB9)) | AC9: =IF(R9<>"07","",IF(ISERROR(VLOOKUP(CONCATENATE("MEDIO UTILIZADO",'Registrar expedidas_ingresos'!AC9),'CODIGO-LITERAL'!$C:$D,2,FALSE)),"",VLOOKUP(CONCATENATE("MEDIO UTILIZADO",'Registrar expedidas_ingresos'!AC9),'CODIGO-LITERAL'!$C:$D,2,FALSE))) | AD9: =IF(R9<>"07","",IF('Registrar expedidas_ingresos'!AD9="","",'Registrar expedidas_ingresos'!AD9)) | AG9: =IF('Registrar expedidas_ingresos'!AG9="","",'Registrar expedidas_ingresos'!AG9) | AH9: =IF(ISERROR(VLOOKUP(CONCATENATE("SITUACION",'Registrar expedidas_ingresos'!AH9),'CODIGO-LITERAL'!$C:$D,2,FALSE)),"",VLOOKUP(CONCATENATE("SITUACION",'Registrar expedidas_ingresos'!AH9),'CODIGO-LITERAL'!$C:$D,2,FALSE)) | AI9: =IF('Registrar expedidas_ingresos'!AI9="","",'Registrar expedidas_ingresos'!AI9) | AJ9: =IF('Registrar expedidas_ingresos'!AJ9="","",'Registrar expedidas_ingresos'!AJ9)
A10: =IF('Registrar expedidas_ingresos'!J10="",IF('Registrar expedidas_ingresos'!I10="","",YEAR('Registrar expedidas_ingresos'!I10)),YEAR('Registrar expedidas_ingresos'!J10)) | B10: =IF('Registrar expedidas_ingresos'!B10="","",'Registrar expedidas_ingresos'!B10) | C10: =IF('Registrar expedidas_ingresos'!C10="","",VLOOKUP(CONCATENATE("ACTIVIDAD",'Registrar expedidas_ingresos'!C10),'CODIGO-LITERAL'!C:D,2,FALSE)) | D10: =IF(OR(C10="C",C10="D"),"",IF(ISERROR(VLOOKUP(CONCATENATE(C10,'Registrar expedidas_ingresos'!D10),'CODIGO-LITERAL'!$C:$D,2,FALSE)),"",VLOOKUP(CONCATENATE(C10,'Registrar expedidas_ingresos'!D10),'CODIGO-LITERAL'!$C:$D,2,FALSE))) | E10: =IF('Registrar expedidas_ingresos'!E10="","",'Registrar expedidas_ingresos'!E10) | F10: =IF(ISERROR(VLOOKUP(CONCATENATE("TIPO FACTURA",'Registrar expedidas_ingresos'!F10),'CODIGO-LITERAL'!$C:$D,2,FALSE)),"",VLOOKUP(CONCATENATE("TIPO FACTURA",'Registrar expedidas_ingresos'!F10),'CODIGO-LITERAL'!$C:$D,2,FALSE)) | I10: =IF('Registrar expedidas_ingresos'!I10="","",'Registrar expedidas_ingresos'!I10) | J10: =IF('Registrar expedidas_ingresos'!J10="","",'Registrar expedidas_ingresos'!J10) | K10: =IF('Registrar expedidas_ingresos'!K10="","",'Registrar expedidas_ingresos'!K10) | L10: =IF('Registrar expedidas_ingresos'!L10="","",'Registrar expedidas_ingresos'!L10) | M10: =IF('Registrar expedidas_ingresos'!M10="","",'Registrar expedidas_ingresos'!M10) | N10: =IF(OR(F10="F2",LEFT('Registrar expedidas_ingresos'!N10,2)="01"),"",IF(ISERROR(VLOOKUP(CONCATENATE("TIPO NIF",'Registrar expedidas_ingresos'!N10),'CODIGO-LITERAL'!$C:$D,2,FALSE)),"",VLOOKUP(CONCATENATE("TIPO NIF",'Registrar expedidas_ingresos'!N10),'CODIGO-LITERAL'!$C:$D,2,FALSE))) | O10: =IF(OR('Registrar expedidas_ingresos'!O10="",N10="02",F10="F2"),"",'Registrar expedidas_ingresos'!O10) | P10: =IF('Registrar expedidas_ingresos'!P10="","",'Registrar expedidas_ingresos'!P10) | Q10: =IF(F10="F2","VENTAS A CONSUMIDOR FINAL",IF('Registrar expedidas_ingresos'!Q10="","",'Registrar expedidas_ingresos'!Q10)) | R10: =IF(F10="DV","02",IF(ISERROR(VLOOKUP(CONCATENATE("CLAVE OPERACION",'Registrar expedidas_ingresos'!R10),'CODIGO-LITERAL'!$C:$D,2,FALSE)),"",VLOOKUP(CONCATENATE("CLAVE OPERACION",'Registrar expedidas_ingresos'!R10),'CODIGO-LITERAL'!$C:$D,2,FALSE))) | S10: =IF(R10="03","S1", IF(R10="08","N2", IF(ISERROR(VLOOKUP(CONCATENATE("CALIFICACION OPERACION",'Registrar expedidas_ingresos'!S10),'CODIGO-LITERAL'!$C:$D,2,FALSE)),"",VLOOKUP(CONCATENATE("CALIFICACION OPERACION",'Registrar expedidas_ingresos'!S10),'CODIGO-LITERAL'!$C:$D,2,FALSE)))) | T10: =IF(R10="03","",IF(R10="08","",IF(ISERROR(VLOOKUP(CONCATENATE("OPERACION EXENTA",'Registrar expedidas_ingresos'!T10),'CODIGO-LITERAL'!$C:$D,2,FALSE)),"",VLOOKUP(CONCATENATE("OPERACION EXENTA",'Registrar expedidas_ingresos'!T10),'CODIGO-LITERAL'!$C:$D,2,FALSE)))) | U10: =IF(AND(S10="",T10=""),"",IF(S10="S1",ROUND(SUM(V10,X10,Z10),2),ROUND(V10,2))) | V10: =IF('Registrar expedidas_ingresos'!V10="","",ROUND('Registrar expedidas_ingresos'!V10,2)) | W10: =IF(S10="S2",0,IF('Registrar expedidas_ingresos'!W10="","",'Registrar expedidas_ingresos'!W10)) | X10: =IF(S10="S2",0,IF('Registrar expedidas_ingresos'!X10="","",ROUND('Registrar expedidas_ingresos'!X10,2))) | Y10: =IF('Registrar expedidas_ingresos'!Y10="","",'Registrar expedidas_ingresos'!Y10) | Z10: =IF('Registrar expedidas_ingresos'!Z10="","",ROUND('Registrar expedidas_ingresos'!Z10,2)) | AA10: =IF(R10<>"07","",IF('Registrar expedidas_ingresos'!AA10="","",'Registrar expedidas_ingresos'!AA10)) | AB10: =IF(R10<>"07","",IF('Registrar expedidas_ingresos'!AB10="","",'Registrar expedidas_ingresos'!AB10)) | AC10: =IF(R10<>"07","",IF(ISERROR(VLOOKUP(CONCATENATE("MEDIO UTILIZADO",'Registrar expedidas_ingresos'!AC10),'CODIGO-LITERAL'!$C:$D,2,FALSE)),"",VLOOKUP(CONCATENATE("MEDIO UTILIZADO",'Registrar expedidas_ingresos'!AC10),'CODIGO-LITERAL'!$C:$D,2,FALSE))) | AD10: =IF(R10<>"07","",IF('Registrar expedidas_ingresos'!AD10="","",'Registrar expedidas_ingresos'!AD10)) | AG10: =IF('Registrar expedidas_ingresos'!AG10="","",'Registrar expedidas_ingresos'!AG10) | AH10: =IF(ISERROR(VLOOKUP(CONCATENATE("SITUACION",'Registrar expedidas_ingresos'!AH10),'CODIGO-LITERAL'!$C:$D,2,FALSE)),"",VLOOKUP(CONCATENATE("SITUACION",'Registrar expedidas_ingresos'!AH10),'CODIGO-LITERAL'!$C:$D,2,FALSE)) | AI10: =IF('Registrar expedidas_ingresos'!AI10="","",'Registrar expedidas_ingresos'!AI10) | AJ10: =IF('Registrar expedidas_ingresos'!AJ10="","",'Registrar expedidas_ingresos'!AJ10)
A11: =IF('Registrar expedidas_ingresos'!J11="",IF('Registrar expedidas_ingresos'!I11="","",YEAR('Registrar expedidas_ingresos'!I11)),YEAR('Registrar expedidas_ingresos'!J11)) | B11: =IF('Registrar expedidas_ingresos'!B11="","",'Registrar expedidas_ingresos'!B11) | C11: =IF('Registrar expedidas_ingresos'!C11="","",VLOOKUP(CONCATENATE("ACTIVIDAD",'Registrar expedidas_ingresos'!C11),'CODIGO-LITERAL'!C:D,2,FALSE)) | D11: =IF(OR(C11="C",C11="D"),"",IF(ISERROR(VLOOKUP(CONCATENATE(C11,'Registrar expedidas_ingresos'!D11),'CODIGO-LITERAL'!$C:$D,2,FALSE)),"",VLOOKUP(CONCATENATE(C11,'Registrar expedidas_ingresos'!D11),'CODIGO-LITERAL'!$C:$D,2,FALSE))) | E11: =IF('Registrar expedidas_ingresos'!E11="","",'Registrar expedidas_ingresos'!E11) | F11: =IF(ISERROR(VLOOKUP(CONCATENATE("TIPO FACTURA",'Registrar expedidas_ingresos'!F11),'CODIGO-LITERAL'!$C:$D,2,FALSE)),"",VLOOKUP(CONCATENATE("TIPO FACTURA",'Registrar expedidas_ingresos'!F11),'CODIGO-LITERAL'!$C:$D,2,FALSE)) | I11: =IF('Registrar expedidas_ingresos'!I11="","",'Registrar expedidas_ingresos'!I11) | J11: =IF('Registrar expedidas_ingresos'!J11="","",'Registrar expedidas_ingresos'!J11) | K11: =IF('Registrar expedidas_ingresos'!K11="","",'Registrar expedidas_ingresos'!K11) | L11: =IF('Registrar expedidas_ingresos'!L11="","",'Registrar expedidas_ingresos'!L11) | M11: =IF('Registrar expedidas_ingresos'!M11="","",'Registrar expedidas_ingresos'!M11) | N11: =IF(OR(F11="F2",LEFT('Registrar expedidas_ingresos'!N11,2)="01"),"",IF(ISERROR(VLOOKUP(CONCATENATE("TIPO NIF",'Registrar expedidas_ingresos'!N11),'CODIGO-LITERAL'!$C:$D,2,FALSE)),"",VLOOKUP(CONCATENATE("TIPO NIF",'Registrar expedidas_ingresos'!N11),'CODIGO-LITERAL'!$C:$D,2,FALSE))) | O11: =IF(OR('Registrar expedidas_ingresos'!O11="",N11="02",F11="F2"),"",'Registrar expedidas_ingresos'!O11) | P11: =IF('Registrar expedidas_ingresos'!P11="","",'Registrar expedidas_ingresos'!P11) | Q11: =IF(F11="F2","VENTAS A CONSUMIDOR FINAL",IF('Registrar expedidas_ingresos'!Q11="","",'Registrar expedidas_ingresos'!Q11)) | R11: =IF(F11="DV","02",IF(ISERROR(VLOOKUP(CONCATENATE("CLAVE OPERACION",'Registrar expedidas_ingresos'!R11),'CODIGO-LITERAL'!$C:$D,2,FALSE)),"",VLOOKUP(CONCATENATE("CLAVE OPERACION",'Registrar expedidas_ingresos'!R11),'CODIGO-LITERAL'!$C:$D,2,FALSE))) | S11: =IF(R11="03","S1", IF(R11="08","N2", IF(ISERROR(VLOOKUP(CONCATENATE("CALIFICACION OPERACION",'Registrar expedidas_ingresos'!S11),'CODIGO-LITERAL'!$C:$D,2,FALSE)),"",VLOOKUP(CONCATENATE("CALIFICACION OPERACION",'Registrar expedidas_ingresos'!S11),'CODIGO-LITERAL'!$C:$D,2,FALSE)))) | T11: =IF(R11="03","",IF(R11="08","",IF(ISERROR(VLOOKUP(CONCATENATE("OPERACION EXENTA",'Registrar expedidas_ingresos'!T11),'CODIGO-LITERAL'!$C:$D,2,FALSE)),"",VLOOKUP(CONCATENATE("OPERACION EXENTA",'Registrar expedidas_ingresos'!T11),'CODIGO-LITERAL'!$C:$D,2,FALSE)))) | U11: =IF(AND(S11="",T11=""),"",IF(S11="S1",ROUND(SUM(V11,X11,Z11),2),ROUND(V11,2))) | V11: =IF('Registrar expedidas_ingresos'!V11="","",ROUND('Registrar expedidas_ingresos'!V11,2)) | W11: =IF(S11="S2",0,IF('Registrar expedidas_ingresos'!W11="","",'Registrar expedidas_ingresos'!W11)) | X11: =IF(S11="S2",0,IF('Registrar expedidas_ingresos'!X11="","",ROUND('Registrar expedidas_ingresos'!X11,2))) | Y11: =IF('Registrar expedidas_ingresos'!Y11="","",'Registrar expedidas_ingresos'!Y11) | Z11: =IF('Registrar expedidas_ingresos'!Z11="","",ROUND('Registrar expedidas_ingresos'!Z11,2)) | AA11: =IF(R11<>"07","",IF('Registrar expedidas_ingresos'!AA11="","",'Registrar expedidas_ingresos'!AA11)) | AB11: =IF(R11<>"07","",IF('Registrar expedidas_ingresos'!AB11="","",'Registrar expedidas_ingresos'!AB11)) | AC11: =IF(R11<>"07","",IF(ISERROR(VLOOKUP(CONCATENATE("MEDIO UTILIZADO",'Registrar expedidas_ingresos'!AC11),'CODIGO-LITERAL'!$C:$D,2,FALSE)),"",VLOOKUP(CONCATENATE("MEDIO UTILIZADO",'Registrar expedidas_ingresos'!AC11),'CODIGO-LITERAL'!$C:$D,2,FALSE))) | AD11: =IF(R11<>"07","",IF('Registrar expedidas_ingresos'!AD11="","",'Registrar expedidas_ingresos'!AD11)) | AG11: =IF('Registrar expedidas_ingresos'!AG11="","",'Registrar expedidas_ingresos'!AG11) | AH11: =IF(ISERROR(VLOOKUP(CONCATENATE("SITUACION",'Registrar expedidas_ingresos'!AH11),'CODIGO-LITERAL'!$C:$D,2,FALSE)),"",VLOOKUP(CONCATENATE("SITUACION",'Registrar expedidas_ingresos'!AH11),'CODIGO-LITERAL'!$C:$D,2,FALSE)) | AI11: =IF('Registrar expedidas_ingresos'!AI11="","",'Registrar expedidas_ingresos'!AI11) | AJ11: =IF('Registrar expedidas_ingresos'!AJ11="","",'Registrar expedidas_ingresos'!AJ11)
A12: =IF('Registrar expedidas_ingresos'!J12="",IF('Registrar expedidas_ingresos'!I12="","",YEAR('Registrar expedidas_ingresos'!I12)),YEAR('Registrar expedidas_ingresos'!J12)) | B12: =IF('Registrar expedidas_ingresos'!B12="","",'Registrar expedidas_ingresos'!B12) | C12: =IF('Registrar expedidas_ingresos'!C12="","",VLOOKUP(CONCATENATE("ACTIVIDAD",'Registrar expedidas_ingresos'!C12),'CODIGO-LITERAL'!C:D,2,FALSE)) | D12: =IF(OR(C12="C",C12="D"),"",IF(ISERROR(VLOOKUP(CONCATENATE(C12,'Registrar expedidas_ingresos'!D12),'CODIGO-LITERAL'!$C:$D,2,FALSE)),"",VLOOKUP(CONCATENATE(C12,'Registrar expedidas_ingresos'!D12),'CODIGO-LITERAL'!$C:$D,2,FALSE))) | E12: =IF('Registrar expedidas_ingresos'!E12="","",'Registrar expedidas_ingresos'!E12) | F12: =IF(ISERROR(VLOOKUP(CONCATENATE("TIPO FACTURA",'Registrar expedidas_ingresos'!F12),'CODIGO-LITERAL'!$C:$D,2,FALSE)),"",VLOOKUP(CONCATENATE("TIPO FACTURA",'Registrar expedidas_ingresos'!F12),'CODIGO-LITERAL'!$C:$D,2,FALSE)) | I12: =IF('Registrar expedidas_ingresos'!I12="","",'Registrar expedidas_ingresos'!I12) | J12: =IF('Registrar expedidas_ingresos'!J12="","",'Registrar expedidas_ingresos'!J12) | K12: =IF('Registrar expedidas_ingresos'!K12="","",'Registrar expedidas_ingresos'!K12) | L12: =IF('Registrar expedidas_ingresos'!L12="","",'Registrar expedidas_ingresos'!L12) | M12: =IF('Registrar expedidas_ingresos'!M12="","",'Registrar expedidas_ingresos'!M12) | N12: =IF(OR(F12="F2",LEFT('Registrar expedidas_ingresos'!N12,2)="01"),"",IF(ISERROR(VLOOKUP(CONCATENATE("TIPO NIF",'Registrar expedidas_ingresos'!N12),'CODIGO-LITERAL'!$C:$D,2,FALSE)),"",VLOOKUP(CONCATENATE("TIPO NIF",'Registrar expedidas_ingresos'!N12),'CODIGO-LITERAL'!$C:$D,2,FALSE))) | O12: =IF(OR('Registrar expedidas_ingresos'!O12="",N12="02",F12="F2"),"",'Registrar expedidas_ingresos'!O12) | P12: =IF('Registrar expedidas_ingresos'!P12="","",'Registrar expedidas_ingresos'!P12) | Q12: =IF(F12="F2","VENTAS A CONSUMIDOR FINAL",IF('Registrar expedidas_ingresos'!Q12="","",'Registrar expedidas_ingresos'!Q12)) | R12: =IF(F12="DV","02",IF(ISERROR(VLOOKUP(CONCATENATE("CLAVE OPERACION",'Registrar expedidas_ingresos'!R12),'CODIGO-LITERAL'!$C:$D,2,FALSE)),"",VLOOKUP(CONCATENATE("CLAVE OPERACION",'Registrar expedidas_ingresos'!R12),'CODIGO-LITERAL'!$C:$D,2,FALSE))) | S12: =IF(R12="03","S1", IF(R12="08","N2", IF(ISERROR(VLOOKUP(CONCATENATE("CALIFICACION OPERACION",'Registrar expedidas_ingresos'!S12),'CODIGO-LITERAL'!$C:$D,2,FALSE)),"",VLOOKUP(CONCATENATE("CALIFICACION OPERACION",'Registrar expedidas_ingresos'!S12),'CODIGO-LITERAL'!$C:$D,2,FALSE)))) | T12: =IF(R12="03","",IF(R12="08","",IF(ISERROR(VLOOKUP(CONCATENATE("OPERACION EXENTA",'Registrar expedidas_ingresos'!T12),'CODIGO-LITERAL'!$C:$D,2,FALSE)),"",VLOOKUP(CONCATENATE("OPERACION EXENTA",'Registrar expedidas_ingresos'!T12),'CODIGO-LITERAL'!$C:$D,2,FALSE)))) | U12: =IF(AND(S12="",T12=""),"",IF(S12="S1",ROUND(SUM(V12,X12,Z12),2),ROUND(V12,2))) | V12: =IF('Registrar expedidas_ingresos'!V12="","",ROUND('Registrar expedidas_ingresos'!V12,2)) | W12: =IF(S12="S2",0,IF('Registrar expedidas_ingresos'!W12="","",'Registrar expedidas_ingresos'!W12)) | X12: =IF(S12="S2",0,IF('Registrar expedidas_ingresos'!X12="","",ROUND('Registrar expedidas_ingresos'!X12,2))) | Y12: =IF('Registrar expedidas_ingresos'!Y12="","",'Registrar expedidas_ingresos'!Y12) | Z12: =IF('Registrar expedidas_ingresos'!Z12="","",ROUND('Registrar expedidas_ingresos'!Z12,2)) | AA12: =IF(R12<>"07","",IF('Registrar expedidas_ingresos'!AA12="","",'Registrar expedidas_ingresos'!AA12)) | AB12: =IF(R12<>"07","",IF('Registrar expedidas_ingresos'!AB12="","",'Registrar expedidas_ingresos'!AB12)) | AC12: =IF(R12<>"07","",IF(ISERROR(VLOOKUP(CONCATENATE("MEDIO UTILIZADO",'Registrar expedidas_ingresos'!AC12),'CODIGO-LITERAL'!$C:$D,2,FALSE)),"",VLOOKUP(CONCATENATE("MEDIO UTILIZADO",'Registrar expedidas_ingresos'!AC12),'CODIGO-LITERAL'!$C:$D,2,FALSE))) | AD12: =IF(R12<>"07","",IF('Registrar expedidas_ingresos'!AD12="","",'Registrar expedidas_ingresos'!AD12)) | AG12: =IF('Registrar expedidas_ingresos'!AG12="","",'Registrar expedidas_ingresos'!AG12) | AH12: =IF(ISERROR(VLOOKUP(CONCATENATE("SITUACION",'Registrar expedidas_ingresos'!AH12),'CODIGO-LITERAL'!$C:$D,2,FALSE)),"",VLOOKUP(CONCATENATE("SITUACION",'Registrar expedidas_ingresos'!AH12),'CODIGO-LITERAL'!$C:$D,2,FALSE)) | AI12: =IF('Registrar expedidas_ingresos'!AI12="","",'Registrar expedidas_ingresos'!AI12) | AJ12: =IF('Registrar expedidas_ingresos'!AJ12="","",'Registrar expedidas_ingresos'!AJ12)
A13: =IF('Registrar expedidas_ingresos'!J13="",IF('Registrar expedidas_ingresos'!I13="","",YEAR('Registrar expedidas_ingresos'!I13)),YEAR('Registrar expedidas_ingresos'!J13)) | B13: =IF('Registrar expedidas_ingresos'!B13="","",'Registrar expedidas_ingresos'!B13) | C13: =IF('Registrar expedidas_ingresos'!C13="","",VLOOKUP(CONCATENATE("ACTIVIDAD",'Registrar expedidas_ingresos'!C13),'CODIGO-LITERAL'!C:D,2,FALSE)) | D13: =IF(OR(C13="C",C13="D"),"",IF(ISERROR(VLOOKUP(CONCATENATE(C13,'Registrar expedidas_ingresos'!D13),'CODIGO-LITERAL'!$C:$D,2,FALSE)),"",VLOOKUP(CONCATENATE(C13,'Registrar expedidas_ingresos'!D13),'CODIGO-LITERAL'!$C:$D,2,FALSE))) | E13: =IF('Registrar expedidas_ingresos'!E13="","",'Registrar expedidas_ingresos'!E13) | F13: =IF(ISERROR(VLOOKUP(CONCATENATE("TIPO FACTURA",'Registrar expedidas_ingresos'!F13),'CODIGO-LITERAL'!$C:$D,2,FALSE)),"",VLOOKUP(CONCATENATE("TIPO FACTURA",'Registrar expedidas_ingresos'!F13),'CODIGO-LITERAL'!$C:$D,2,FALSE)) | I13: =IF('Registrar expedidas_ingresos'!I13="","",'Registrar expedidas_ingresos'!I13) | J13: =IF('Registrar expedidas_ingresos'!J13="","",'Registrar expedidas_ingresos'!J13) | K13: =IF('Registrar expedidas_ingresos'!K13="","",'Registrar expedidas_ingresos'!K13) | L13: =IF('Registrar expedidas_ingresos'!L13="","",'Registrar expedidas_ingresos'!L13) | M13: =IF('Registrar expedidas_ingresos'!M13="","",'Registrar expedidas_ingresos'!M13) | N13: =IF(OR(F13="F2",LEFT('Registrar expedidas_ingresos'!N13,2)="01"),"",IF(ISERROR(VLOOKUP(CONCATENATE("TIPO NIF",'Registrar expedidas_ingresos'!N13),'CODIGO-LITERAL'!$C:$D,2,FALSE)),"",VLOOKUP(CONCATENATE("TIPO NIF",'Registrar expedidas_ingresos'!N13),'CODIGO-LITERAL'!$C:$D,2,FALSE))) | O13: =IF(OR('Registrar expedidas_ingresos'!O13="",N13="02",F13="F2"),"",'Registrar expedidas_ingresos'!O13) | P13: =IF('Registrar expedidas_ingresos'!P13="","",'Registrar expedidas_ingresos'!P13) | Q13: =IF(F13="F2","VENTAS A CONSUMIDOR FINAL",IF('Registrar expedidas_ingresos'!Q13="","",'Registrar expedidas_ingresos'!Q13)) | R13: =IF(F13="DV","02",IF(ISERROR(VLOOKUP(CONCATENATE("CLAVE OPERACION",'Registrar expedidas_ingresos'!R13),'CODIGO-LITERAL'!$C:$D,2,FALSE)),"",VLOOKUP(CONCATENATE("CLAVE OPERACION",'Registrar expedidas_ingresos'!R13),'CODIGO-LITERAL'!$C:$D,2,FALSE))) | S13: =IF(R13="03","S1", IF(R13="08","N2", IF(ISERROR(VLOOKUP(CONCATENATE("CALIFICACION OPERACION",'Registrar expedidas_ingresos'!S13),'CODIGO-LITERAL'!$C:$D,2,FALSE)),"",VLOOKUP(CONCATENATE("CALIFICACION OPERACION",'Registrar expedidas_ingresos'!S13),'CODIGO-LITERAL'!$C:$D,2,FALSE)))) | T13: =IF(R13="03","",IF(R13="08","",IF(ISERROR(VLOOKUP(CONCATENATE("OPERACION EXENTA",'Registrar expedidas_ingresos'!T13),'CODIGO-LITERAL'!$C:$D,2,FALSE)),"",VLOOKUP(CONCATENATE("OPERACION EXENTA",'Registrar expedidas_ingresos'!T13),'CODIGO-LITERAL'!$C:$D,2,FALSE)))) | U13: =IF(AND(S13="",T13=""),"",IF(S13="S1",ROUND(SUM(V13,X13,Z13),2),ROUND(V13,2))) | V13: =IF('Registrar expedidas_ingresos'!V13="","",ROUND('Registrar expedidas_ingresos'!V13,2)) | W13: =IF(S13="S2",0,IF('Registrar expedidas_ingresos'!W13="","",'Registrar expedidas_ingresos'!W13)) | X13: =IF(S13="S2",0,IF('Registrar expedidas_ingresos'!X13="","",ROUND('Registrar expedidas_ingresos'!X13,2))) | Y13: =IF('Registrar expedidas_ingresos'!Y13="","",'Registrar expedidas_ingresos'!Y13) | Z13: =IF('Registrar expedidas_ingresos'!Z13="","",ROUND('Registrar expedidas_ingresos'!Z13,2)) | AA13: =IF(R13<>"07","",IF('Registrar expedidas_ingresos'!AA13="","",'Registrar expedidas_ingresos'!AA13)) | AB13: =IF(R13<>"07","",IF('Registrar expedidas_ingresos'!AB13="","",'Registrar expedidas_ingresos'!AB13)) | AC13: =IF(R13<>"07","",IF(ISERROR(VLOOKUP(CONCATENATE("MEDIO UTILIZADO",'Registrar expedidas_ingresos'!AC13),'CODIGO-LITERAL'!$C:$D,2,FALSE)),"",VLOOKUP(CONCATENATE("MEDIO UTILIZADO",'Registrar expedidas_ingresos'!AC13),'CODIGO-LITERAL'!$C:$D,2,FALSE))) | AD13: =IF(R13<>"07","",IF('Registrar expedidas_ingresos'!AD13="","",'Registrar expedidas_ingresos'!AD13)) | AG13: =IF('Registrar expedidas_ingresos'!AG13="","",'Registrar expedidas_ingresos'!AG13) | AH13: =IF(ISERROR(VLOOKUP(CONCATENATE("SITUACION",'Registrar expedidas_ingresos'!AH13),'CODIGO-LITERAL'!$C:$D,2,FALSE)),"",VLOOKUP(CONCATENATE("SITUACION",'Registrar expedidas_ingresos'!AH13),'CODIGO-LITERAL'!$C:$D,2,FALSE)) | AI13: =IF('Registrar expedidas_ingresos'!AI13="","",'Registrar expedidas_ingresos'!AI13) | AJ13: =IF('Registrar expedidas_ingresos'!AJ13="","",'Registrar expedidas_ingresos'!AJ13)
A14: =IF('Registrar expedidas_ingresos'!J14="",IF('Registrar expedidas_ingresos'!I14="","",YEAR('Registrar expedidas_ingresos'!I14)),YEAR('Registrar expedidas_ingresos'!J14)) | B14: =IF('Registrar expedidas_ingresos'!B14="","",'Registrar expedidas_ingresos'!B14) | C14: =IF('Registrar expedidas_ingresos'!C14="","",VLOOKUP(CONCATENATE("ACTIVIDAD",'Registrar expedidas_ingresos'!C14),'CODIGO-LITERAL'!C:D,2,FALSE)) | D14: =IF(OR(C14="C",C14="D"),"",IF(ISERROR(VLOOKUP(CONCATENATE(C14,'Registrar expedidas_ingresos'!D14),'CODIGO-LITERAL'!$C:$D,2,FALSE)),"",VLOOKUP(CONCATENATE(C14,'Registrar expedidas_ingresos'!D14),'CODIGO-LITERAL'!$C:$D,2,FALSE))) | E14: =IF('Registrar expedidas_ingresos'!E14="","",'Registrar expedidas_ingresos'!E14) | F14: =IF(ISERROR(VLOOKUP(CONCATENATE("TIPO FACTURA",'Registrar expedidas_ingresos'!F14),'CODIGO-LITERAL'!$C:$D,2,FALSE)),"",VLOOKUP(CONCATENATE("TIPO FACTURA",'Registrar expedidas_ingresos'!F14),'CODIGO-LITERAL'!$C:$D,2,FALSE)) | I14: =IF('Registrar expedidas_ingresos'!I14="","",'Registrar expedidas_ingresos'!I14) | J14: =IF('Registrar expedidas_ingresos'!J14="","",'Registrar expedidas_ingresos'!J14) | K14: =IF('Registrar expedidas_ingresos'!K14="","",'Registrar expedidas_ingresos'!K14) | L14: =IF('Registrar expedidas_ingresos'!L14="","",'Registrar expedidas_ingresos'!L14) | M14: =IF('Registrar expedidas_ingresos'!M14="","",'Registrar expedidas_ingresos'!M14) | N14: =IF(OR(F14="F2",LEFT('Registrar expedidas_ingresos'!N14,2)="01"),"",IF(ISERROR(VLOOKUP(CONCATENATE("TIPO NIF",'Registrar expedidas_ingresos'!N14),'CODIGO-LITERAL'!$C:$D,2,FALSE)),"",VLOOKUP(CONCATENATE("TIPO NIF",'Registrar expedidas_ingresos'!N14),'CODIGO-LITERAL'!$C:$D,2,FALSE))) | O14: =IF(OR('Registrar expedidas_ingresos'!O14="",N14="02",F14="F2"),"",'Registrar expedidas_ingresos'!O14) | P14: =IF('Registrar expedidas_ingresos'!P14="","",'Registrar expedidas_ingresos'!P14) | Q14: =IF(F14="F2","VENTAS A CONSUMIDOR FINAL",IF('Registrar expedidas_ingresos'!Q14="","",'Registrar expedidas_ingresos'!Q14)) | R14: =IF(F14="DV","02",IF(ISERROR(VLOOKUP(CONCATENATE("CLAVE OPERACION",'Registrar expedidas_ingresos'!R14),'CODIGO-LITERAL'!$C:$D,2,FALSE)),"",VLOOKUP(CONCATENATE("CLAVE OPERACION",'Registrar expedidas_ingresos'!R14),'CODIGO-LITERAL'!$C:$D,2,FALSE))) | S14: =IF(R14="03","S1", IF(R14="08","N2", IF(ISERROR(VLOOKUP(CONCATENATE("CALIFICACION OPERACION",'Registrar expedidas_ingresos'!S14),'CODIGO-LITERAL'!$C:$D,2,FALSE)),"",VLOOKUP(CONCATENATE("CALIFICACION OPERACION",'Registrar expedidas_ingresos'!S14),'CODIGO-LITERAL'!$C:$D,2,FALSE)))) | T14: =IF(R14="03","",IF(R14="08","",IF(ISERROR(VLOOKUP(CONCATENATE("OPERACION EXENTA",'Registrar expedidas_ingresos'!T14),'CODIGO-LITERAL'!$C:$D,2,FALSE)),"",VLOOKUP(CONCATENATE("OPERACION EXENTA",'Registrar expedidas_ingresos'!T14),'CODIGO-LITERAL'!$C:$D,2,FALSE)))) | U14: =IF(AND(S14="",T14=""),"",IF(S14="S1",ROUND(SUM(V14,X14,Z14),2),ROUND(V14,2))) | V14: =IF('Registrar expedidas_ingresos'!V14="","",ROUND('Registrar expedidas_ingresos'!V14,2)) | W14: =IF(S14="S2",0,IF('Registrar expedidas_ingresos'!W14="","",'Registrar expedidas_ingresos'!W14)) | X14: =IF(S14="S2",0,IF('Registrar expedidas_ingresos'!X14="","",ROUND('Registrar expedidas_ingresos'!X14,2))) | Y14: =IF('Registrar expedidas_ingresos'!Y14="","",'Registrar expedidas_ingresos'!Y14) | Z14: =IF('Registrar expedidas_ingresos'!Z14="","",ROUND('Registrar expedidas_ingresos'!Z14,2)) | AA14: =IF(R14<>"07","",IF('Registrar expedidas_ingresos'!AA14="","",'Registrar expedidas_ingresos'!AA14)) | AB14: =IF(R14<>"07","",IF('Registrar expedidas_ingresos'!AB14="","",'Registrar expedidas_ingresos'!AB14)) | AC14: =IF(R14<>"07","",IF(ISERROR(VLOOKUP(CONCATENATE("MEDIO UTILIZADO",'Registrar expedidas_ingresos'!AC14),'CODIGO-LITERAL'!$C:$D,2,FALSE)),"",VLOOKUP(CONCATENATE("MEDIO UTILIZADO",'Registrar expedidas_ingresos'!AC14),'CODIGO-LITERAL'!$C:$D,2,FALSE))) | AD14: =IF(R14<>"07","",IF('Registrar expedidas_ingresos'!AD14="","",'Registrar expedidas_ingresos'!AD14)) | AG14: =IF('Registrar expedidas_ingresos'!AG14="","",'Registrar expedidas_ingresos'!AG14) | AH14: =IF(ISERROR(VLOOKUP(CONCATENATE("SITUACION",'Registrar expedidas_ingresos'!AH14),'CODIGO-LITERAL'!$C:$D,2,FALSE)),"",VLOOKUP(CONCATENATE("SITUACION",'Registrar expedidas_ingresos'!AH14),'CODIGO-LITERAL'!$C:$D,2,FALSE)) | AI14: =IF('Registrar expedidas_ingresos'!AI14="","",'Registrar expedidas_ingresos'!AI14) | AJ14: =IF('Registrar expedidas_ingresos'!AJ14="","",'Registrar expedidas_ingresos'!AJ14)
A15: =IF('Registrar expedidas_ingresos'!J15="",IF('Registrar expedidas_ingresos'!I15="","",YEAR('Registrar expedidas_ingresos'!I15)),YEAR('Registrar expedidas_ingresos'!J15)) | B15: =IF('Registrar expedidas_ingresos'!B15="","",'Registrar expedidas_ingresos'!B15) | C15: =IF('Registrar expedidas_ingresos'!C15="","",VLOOKUP(CONCATENATE("ACTIVIDAD",'Registrar expedidas_ingresos'!C15),'CODIGO-LITERAL'!C:D,2,FALSE)) | D15: =IF(OR(C15="C",C15="D"),"",IF(ISERROR(VLOOKUP(CONCATENATE(C15,'Registrar expedidas_ingresos'!D15),'CODIGO-LITERAL'!$C:$D,2,FALSE)),"",VLOOKUP(CONCATENATE(C15,'Registrar expedidas_ingresos'!D15),'CODIGO-LITERAL'!$C:$D,2,FALSE))) | E15: =IF('Registrar expedidas_ingresos'!E15="","",'Registrar expedidas_ingresos'!E15) | F15: =IF(ISERROR(VLOOKUP(CONCATENATE("TIPO FACTURA",'Registrar expedidas_ingresos'!F15),'CODIGO-LITERAL'!$C:$D,2,FALSE)),"",VLOOKUP(CONCATENATE("TIPO FACTURA",'Registrar expedidas_ingresos'!F15),'CODIGO-LITERAL'!$C:$D,2,FALSE)) | I15: =IF('Registrar expedidas_ingresos'!I15="","",'Registrar expedidas_ingresos'!I15) | J15: =IF('Registrar expedidas_ingresos'!J15="","",'Registrar expedidas_ingresos'!J15) | K15: =IF('Registrar expedidas_ingresos'!K15="","",'Registrar expedidas_ingresos'!K15) | L15: =IF('Registrar expedidas_ingresos'!L15="","",'Registrar expedidas_ingresos'!L15) | M15: =IF('Registrar expedidas_ingresos'!M15="","",'Registrar expedidas_ingresos'!M15) | N15: =IF(OR(F15="F2",LEFT('Registrar expedidas_ingresos'!N15,2)="01"),"",IF(ISERROR(VLOOKUP(CONCATENATE("TIPO NIF",'Registrar expedidas_ingresos'!N15),'CODIGO-LITERAL'!$C:$D,2,FALSE)),"",VLOOKUP(CONCATENATE("TIPO NIF",'Registrar expedidas_ingresos'!N15),'CODIGO-LITERAL'!$C:$D,2,FALSE))) | O15: =IF(OR('Registrar expedidas_ingresos'!O15="",N15="02",F15="F2"),"",'Registrar expedidas_ingresos'!O15) | P15: =IF('Registrar expedidas_ingresos'!P15="","",'Registrar expedidas_ingresos'!P15) | Q15: =IF(F15="F2","VENTAS A CONSUMIDOR FINAL",IF('Registrar expedidas_ingresos'!Q15="","",'Registrar expedidas_ingresos'!Q15)) | R15: =IF(F15="DV","02",IF(ISERROR(VLOOKUP(CONCATENATE("CLAVE OPERACION",'Registrar expedidas_ingresos'!R15),'CODIGO-LITERAL'!$C:$D,2,FALSE)),"",VLOOKUP(CONCATENATE("CLAVE OPERACION",'Registrar expedidas_ingresos'!R15),'CODIGO-LITERAL'!$C:$D,2,FALSE))) | S15: =IF(R15="03","S1", IF(R15="08","N2", IF(ISERROR(VLOOKUP(CONCATENATE("CALIFICACION OPERACION",'Registrar expedidas_ingresos'!S15),'CODIGO-LITERAL'!$C:$D,2,FALSE)),"",VLOOKUP(CONCATENATE("CALIFICACION OPERACION",'Registrar expedidas_ingresos'!S15),'CODIGO-LITERAL'!$C:$D,2,FALSE)))) | T15: =IF(R15="03","",IF(R15="08","",IF(ISERROR(VLOOKUP(CONCATENATE("OPERACION EXENTA",'Registrar expedidas_ingresos'!T15),'CODIGO-LITERAL'!$C:$D,2,FALSE)),"",VLOOKUP(CONCATENATE("OPERACION EXENTA",'Registrar expedidas_ingresos'!T15),'CODIGO-LITERAL'!$C:$D,2,FALSE)))) | U15: =IF(AND(S15="",T15=""),"",IF(S15="S1",ROUND(SUM(V15,X15,Z15),2),ROUND(V15,2))) | V15: =IF('Registrar expedidas_ingresos'!V15="","",ROUND('Registrar expedidas_ingresos'!V15,2)) | W15: =IF(S15="S2",0,IF('Registrar expedidas_ingresos'!W15="","",'Registrar expedidas_ingresos'!W15)) | X15: =IF(S15="S2",0,IF('Registrar expedidas_ingresos'!X15="","",ROUND('Registrar expedidas_ingresos'!X15,2))) | Y15: =IF('Registrar expedidas_ingresos'!Y15="","",'Registrar expedidas_ingresos'!Y15) | Z15: =IF('Registrar expedidas_ingresos'!Z15="","",ROUND('Registrar expedidas_ingresos'!Z15,2)) | AA15: =IF(R15<>"07","",IF('Registrar expedidas_ingresos'!AA15="","",'Registrar expedidas_ingresos'!AA15)) | AB15: =IF(R15<>"07","",IF('Registrar expedidas_ingresos'!AB15="","",'Registrar expedidas_ingresos'!AB15)) | AC15: =IF(R15<>"07","",IF(ISERROR(VLOOKUP(CONCATENATE("MEDIO UTILIZADO",'Registrar expedidas_ingresos'!AC15),'CODIGO-LITERAL'!$C:$D,2,FALSE)),"",VLOOKUP(CONCATENATE("MEDIO UTILIZADO",'Registrar expedidas_ingresos'!AC15),'CODIGO-LITERAL'!$C:$D,2,FALSE))) | AD15: =IF(R15<>"07","",IF('Registrar expedidas_ingresos'!AD15="","",'Registrar expedidas_ingresos'!AD15)) | AG15: =IF('Registrar expedidas_ingresos'!AG15="","",'Registrar expedidas_ingresos'!AG15) | AH15: =IF(ISERROR(VLOOKUP(CONCATENATE("SITUACION",'Registrar expedidas_ingresos'!AH15),'CODIGO-LITERAL'!$C:$D,2,FALSE)),"",VLOOKUP(CONCATENATE("SITUACION",'Registrar expedidas_ingresos'!AH15),'CODIGO-LITERAL'!$C:$D,2,FALSE)) | AI15: =IF('Registrar expedidas_ingresos'!AI15="","",'Registrar expedidas_ingresos'!AI15) | AJ15: =IF('Registrar expedidas_ingresos'!AJ15="","",'Registrar expedidas_ingresos'!AJ15)
... A103: =IF('Registrar expedidas_ingresos'!J103="",IF('Registrar expedidas_ingresos'!I103="","",YEAR('Registrar expedidas_ingresos'!I103)),YEAR('Registrar expedidas_ingresos'!J103)) | B103: =IF('Registrar expedidas_ingresos'!B103="","",'Registrar expedidas_ingresos'!B103) | C103: =IF('Registrar expedidas_ingresos'!C103="","",VLOOKUP(CONCATENATE("ACTIVIDAD",'Registrar expedidas_ingresos'!C103),'CODIGO-LITERAL'!C:D,2,FALSE)) | D103: =IF(OR(C103="C",C103="D"),"",IF(ISERROR(VLOOKUP(CONCATENATE(C103,'Registrar expedidas_ingresos'!D103),'CODIGO-LITERAL'!$C:$D,2,FALSE)),"",VLOOKUP(CONCATENATE(C103,'Registrar expedidas_ingresos'!D103),'CODIGO-LITERAL'!$C:$D,2,FALSE))) | E103: =IF('Registrar expedidas_ingresos'!E103="","",'Registrar expedidas_ingresos'!E103) | F103: =IF(ISERROR(VLOOKUP(CONCATENATE("TIPO FACTURA",'Registrar expedidas_ingresos'!F103),'CODIGO-LITERAL'!$C:$D,2,FALSE)),"",VLOOKUP(CONCATENATE("TIPO FACTURA",'Registrar expedidas_ingresos'!F103),'CODIGO-LITERAL'!$C:$D,2,FALSE)) | I103: =IF('Registrar expedidas_ingresos'!I103="","",'Registrar expedidas_ingresos'!I103) | J103: =IF('Registrar expedidas_ingresos'!J103="","",'Registrar expedidas_ingresos'!J103) | K103: =IF('Registrar expedidas_ingresos'!K103="","",'Registrar expedidas_ingresos'!K103) | L103: =IF('Registrar expedidas_ingresos'!L103="","",'Registrar expedidas_ingresos'!L103) | M103: =IF('Registrar expedidas_ingresos'!M103="","",'Registrar expedidas_ingresos'!M103) | N103: =IF(OR(F103="F2",LEFT('Registrar expedidas_ingresos'!N103,2)="01"),"",IF(ISERROR(VLOOKUP(CONCATENATE("TIPO NIF",'Registrar expedidas_ingresos'!N103),'CODIGO-LITERAL'!$C:$D,2,FALSE)),"",VLOOKUP(CONCATENATE("TIPO NIF",'Registrar expedidas_ingresos'!N103),'CODIGO-LITERAL'!$C:$D,2,FALSE))) | O103: =IF(OR('Registrar expedidas_ingresos'!O103="",N103="02",F103="F2"),"",'Registrar expedidas_ingresos'!O103) | P103: =IF('Registrar expedidas_ingresos'!P103="","",'Registrar expedidas_ingresos'!P103) | Q103: =IF(F103="F2","VENTAS A CONSUMIDOR FINAL",IF('Registrar expedidas_ingresos'!Q103="","",'Registrar expedidas_ingresos'!Q103)) | R103: =IF(F103="DV","02",IF(ISERROR(VLOOKUP(CONCATENATE("CLAVE OPERACION",'Registrar expedidas_ingresos'!R103),'CODIGO-LITERAL'!$C:$D,2,FALSE)),"",VLOOKUP(CONCATENATE("CLAVE OPERACION",'Registrar expedidas_ingresos'!R103),'CODIGO-LITERAL'!$C:$D,2,FALSE))) | S103: =IF(R103="03","S1", IF(R103="08","N2", IF(ISERROR(VLOOKUP(CONCATENATE("CALIFICACION OPERACION",'Registrar expedidas_ingresos'!S103),'CODIGO-LITERAL'!$C:$D,2,FALSE)),"",VLOOKUP(CONCATENATE("CALIFICACION OPERACION",'Registrar expedidas_ingresos'!S103),'CODIGO-LITERAL'!$C:$D,2,FALSE)))) | T103: =IF(R103="03","",IF(R103="08","",IF(ISERROR(VLOOKUP(CONCATENATE("OPERACION EXENTA",'Registrar expedidas_ingresos'!T103),'CODIGO-LITERAL'!$C:$D,2,FALSE)),"",VLOOKUP(CONCATENATE("OPERACION EXENTA",'Registrar expedidas_ingresos'!T103),'CODIGO-LITERAL'!$C:$D,2,FALSE)))) | U103: =IF(AND(S103="",T103=""),"",IF(S103="S1",ROUND(SUM(V103,X103,Z103),2),ROUND(V103,2))) | V103: =IF('Registrar expedidas_ingresos'!V103="","",ROUND('Registrar expedidas_ingresos'!V103,2)) | W103: =IF(S103="S2",0,IF('Registrar expedidas_ingresos'!W103="","",'Registrar expedidas_ingresos'!W103)) | X103: =IF(S103="S2",0,IF('Registrar expedidas_ingresos'!X103="","",ROUND('Registrar expedidas_ingresos'!X103,2))) | Y103: =IF('Registrar expedidas_ingresos'!Y103="","",'Registrar expedidas_ingresos'!Y103) | Z103: =IF('Registrar expedidas_ingresos'!Z103="","",ROUND('Registrar expedidas_ingresos'!Z103,2)) | AA103: =IF(R103<>"07","",IF('Registrar expedidas_ingresos'!AA103="","",'Registrar expedidas_ingresos'!AA103)) | AB103: =IF(R103<>"07","",IF('Registrar expedidas_ingresos'!AB103="","",'Registrar expedidas_ingresos'!AB103)) | AC103: =IF(R103<>"07","",IF(ISERROR(VLOOKUP(CONCATENATE("MEDIO UTILIZADO",'Registrar expedidas_ingresos'!AC103),'CODIGO-LITERAL'!$C:$D,2,FALSE)),"",VLOOKUP(CONCATENATE("MEDIO UTILIZADO",'Registrar expedidas_ingresos'!AC103),'CODIGO-LITERAL'!$C:$D,2,FALSE))) | AD103: =IF(R103<>"07","",IF('Registrar expedidas_ingresos'!AD103="","",'Registrar expedidas_ingresos'!AD103)) | AG103: =IF('Registrar expedidas_ingresos'!AG103="","",'Registrar expedidas_ingresos'!AG103) | AH103: =IF(ISERROR(VLOOKUP(CONCATENATE("SITUACION",'Registrar expedidas_ingresos'!AH103),'CODIGO-LITERAL'!$C:$D,2,FALSE)),"",VLOOKUP(CONCATENATE("SITUACION",'Registrar expedidas_ingresos'!AH103),'CODIGO-LITERAL'!$C:$D,2,FALSE)) | AI103: =IF('Registrar expedidas_ingresos'!AI103="","",'Registrar expedidas_ingresos'!AI103) | AJ103: =IF('Registrar expedidas_ingresos'!AJ103="","",'Registrar expedidas_ingresos'!AJ103)

Sheet RECIBIDAS_GASTOS
A1: Autoliquidación | C1: Actividad | F1: Tipo de Factura | G1: Concepto de Gasto | H1: Gasto Deducible | I1: Fecha Expedición | J1: Fecha Operación | K1: Identificación Factura del Expedidor | M1: Fecha Recepción | N1: Número Recepción | O1: Número Recepción Final | P1: NIF Expedidor | S1: Nombre Expedidor | T1: Clave de Operación | U1: Bien de Inversión | V1: Inversión del Sujeto Pasivo | W1: Deducible en Periodo Posterior | X1: Periodo Deducción | Z1: Total Factura | AA1: Base Imponible | AB1: Tipo de IVA | AC1: Cuota IVA Soportado | AD1: Cuota Deducible | AE1: Tipo de Recargo Eq. | AF1: Cuota Recargo Eq. | AG1: Pago (Operación Criterio de Caja de IVA y/o artículo 7.2.1º de Reglamento del IRPF) | AK1: Tipo Retención del IRPF | AL1: Importe Retenido del IRPF | AM1: Registro Acuerdo Facturación | AN1: Inmueble | AP1: RefErencia Externa
A2: Ejercicio | B2: Periodo | C2: Código | D2: Tipo | E2: Grupo o Epígrafe del IAE | K2: (Serie-Número) | L2: Número-Final | P2: Tipo | Q2: Código País | R2: Identificación | X2: Ejercicio | Y2: Periodo | AG2: Fecha | AH2: Importe | AI2: Medio Utilizado | AJ2: Identificación Medio Utilizado | AN2: Situación | AO2: Referencia Catastral
A3: Decimal (4,0) | B3: Alfanumérico (2) | C3: Alfanumérico (1) | D3: Alfanumérico (2) | E3: Alfanumérico (4) | F3: Alfanumérico (2) | G3: Alfanumérico (3) | H3: Decimal(12,2) | I3: Fecha(dd/mm/yyyy) | J3: Fecha(dd/mm/yyyy) | K3: Alfanumérico (40) | L3: Alfanumérico (20) | M3: Fecha(dd/mm/yyyy) | N3: Alfanumérico (20) | O3: Alfanumérico (20) | P3: Alfanumérico (2) | Q3: Alfanumérico (2) | R3: Alfanumérico (20) | S3: Alfanumérico (40) | T3: Alfanumérico (2) | U3: Alfanumérico (1) | V3: Alfanumérico (1) | W3: Alfanumérico (1) | X3: Decimal (4,0) | Y3: Alfanumérico (2) | Z3: Decimal(12,2) | AA3: Decimal(12,2) | AB3: Decimal(4,2) | AC3: Decimal(12,2) | AD3: Decimal(12,2) | AE3: Decimal(4,2) | AF3: Decimal(12,2) | AG3: Fecha(dd/mm/yyyy) | AH3: Decimal(12,2) | AI3: Alfanumérico (2) | AJ3: Alfanumérico (34) | AK3: Decimal(4,2) | AL3: Decimal(12,2) | AM3: Alfanumérico (15) | AN3: Alfanumérico (1) | AO3: Alfanumérico (20) | AP3: Alfanumérico (40)
A4: =IF('Registrar recibidas_gastos'!A4="","",'Registrar recibidas_gastos'!A4) | B4: =IF('Registrar recibidas_gastos'!B4="","",'Registrar recibidas_gastos'!B4) | C4: =IF('Registrar recibidas_gastos'!C4="","",VLOOKUP(CONCATENATE("ACTIVIDAD",'Registrar recibidas_gastos'!C4),'CODIGO-LITERAL'!$C:$D,2,FALSE)) | D4: =IF(OR(C4="C",C4="D"),"",IF(ISERROR(VLOOKUP(CONCATENATE(C4,'Registrar recibidas_gastos'!D4),'CODIGO-LITERAL'!$C:$D,2,FALSE)),"",VLOOKUP(CONCATENATE(C4,'Registrar recibidas_gastos'!D4),'CODIGO-LITERAL'!$C:$D,2,FALSE))) | E4: =IF('Registrar recibidas_gastos'!E4="","",'Registrar recibidas_gastos'!E4) | F4: =IF('Registrar recibidas_gastos'!F4="","",VLOOKUP(CONCATENATE("TIPO FACTURA GASTO",'Registrar recibidas_gastos'!F4),'CODIGO-LITERAL'!$C:$D,2,FALSE)) | I4: =IF('Registrar recibidas_gastos'!I4="","",'Registrar recibidas_gastos'!I4) | J4: =IF('Registrar recibidas_gastos'!J4="","",'Registrar recibidas_gastos'!J4) | K4: =IF('Registrar recibidas_gastos'!K4="","",'Registrar recibidas_gastos'!K4) | L4: =IF('Registrar recibidas_gastos'!L4="","",'Registrar recibidas_gastos'!L4) | M4: =IF('Registrar recibidas_gastos'!M4="","",'Registrar recibidas_gastos'!M4) | N4: =IF('Registrar recibidas_gastos'!N4="","",'Registrar recibidas_gastos'!N4) | O4: =IF('Registrar recibidas_gastos'!O4="","",'Registrar recibidas_gastos'!O4) | P4: =IF(OR(LEFT('Registrar recibidas_gastos'!P4,2)="01",'Registrar recibidas_gastos'!P4=""),"",VLOOKUP(CONCATENATE("TIPO NIF",'Registrar recibidas_gastos'!P4),'CODIGO-LITERAL'!$C:$D,2,FALSE)) | Q4: =IF('Registrar recibidas_gastos'!Q4="","",'Registrar recibidas_gastos'!Q4) | R4: =IF('Registrar recibidas_gastos'!R4="","",'Registrar recibidas_gastos'!R4) | S4: =IF('Registrar recibidas_gastos'!S4="","",'Registrar recibidas_gastos'!S4) | T4: =IF('Registrar recibidas_gastos'!T4="","",VLOOKUP(CONCATENATE("CLAVE OPERACION GASTO",'Registrar recibidas_gastos'!T4),'CODIGO-LITERAL'!$C:$D,2,FALSE)) | U4: =IF(T4="","",IF(OR(T4="02",T4="08"),"N",IF('Registrar recibidas_gastos'!U4="","N",'Registrar recibidas_gastos'!U4))) | V4: =IF(T4="","",IF(OR(T4="07",T4="08",T4="09",F4="F5",F4="LC"),"N",IF('Registrar recibidas_gastos'!V4="","N",'Registrar recibidas_gastos'!V4))) | W4: =IF(AND(X4="",Y4=""),"",IF(AND(RECIBIDAS_GASTOS!$X4<>"",RECIBIDAS_GASTOS!$Y4<>""),"S",IF('Registrar recibidas_gastos'!W4="","N",'Registrar recibidas_gastos'!W4))) | X4: =IF('Registrar recibidas_gastos'!X4="","",'Registrar recibidas_gastos'!X4) | Y4: =IF('Registrar recibidas_gastos'!Y4="","",'Registrar recibidas_gastos'!Y4) | Z4: =IF('Registrar recibidas_gastos'!Z4="","",IF(AND(F4="",T4=""),"",IF(OR(T4="03",T4="05",T4="09"),AA4,SUM(AA4,AC4,AF4)))) | AA4: =IF('Registrar recibidas_gastos'!AA4="","",ROUND('Registrar recibidas_gastos'!AA4,2)) | AB4: =IF('Registrar recibidas_gastos'!AB4="","",'Registrar recibidas_gastos'!AB4) | AC4: =IF(OR(T4="03",T4="05"),0,IF('Registrar recibidas_gastos'!AC4="","",ROUND(AA4*AB4/100,2))) | AD4: =IF('Registrar recibidas_gastos'!AD4="","",ROUND('Registrar recibidas_gastos'!AD4,2)) | AE4: =IF('Registrar recibidas_gastos'!AE4="","",'Registrar recibidas_gastos'!AE4) | AF4: =IF('Registrar recibidas_gastos'!AF4="","",ROUND(AA4*AE4/100,2)) | AG4: =IF('Registrar recibidas_gastos'!AG4="","",'Registrar recibidas_gastos'!AG4) | AH4: =IF('Registrar recibidas_gastos'!AH4="","",'Registrar recibidas_gastos'!AH4) | AI4: =IF('Registrar recibidas_gastos'!AI4="","",VLOOKUP(CONCATENATE("MEDIO UTILIZADO",'Registrar recibidas_gastos'!AI4),'CODIGO-LITERAL'!$C:$D,2,FALSE)) | AJ4: =IF('Registrar recibidas_gastos'!AJ4="","",'Registrar recibidas_gastos'!AJ4) | AM4: =IF('Registrar recibidas_gastos'!AM4="","",'Registrar recibidas_gastos'!AM4) | AN4: =IF('Registrar recibidas_gastos'!AN4="","",VLOOKUP(CONCATENATE("SITUACION",'Registrar recibidas_gastos'!AN4),'CODIGO-LITERAL'!$C:$D,2,FALSE)) | AO4: =IF('Registrar recibidas_gastos'!AO4="","",'Registrar recibidas_gastos'!AO4) | AP4: =IF('Registrar recibidas_gastos'!AP4="","",'Registrar recibidas_gastos'!AP4)
A5: =IF('Registrar recibidas_gastos'!A5="","",'Registrar recibidas_gastos'!A5) | B5: =IF('Registrar recibidas_gastos'!B5="","",'Registrar recibidas_gastos'!B5) | C5: =IF('Registrar recibidas_gastos'!C5="","",VLOOKUP(CONCATENATE("ACTIVIDAD",'Registrar recibidas_gastos'!C5),'CODIGO-LITERAL'!$C:$D,2,FALSE)) | D5: =IF(OR(C5="C",C5="D"),"",IF(ISERROR(VLOOKUP(CONCATENATE(C5,'Registrar recibidas_gastos'!D5),'CODIGO-LITERAL'!$C:$D,2,FALSE)),"",VLOOKUP(CONCATENATE(C5,'Registrar recibidas_gastos'!D5),'CODIGO-LITERAL'!$C:$D,2,FALSE))) | E5: =IF('Registrar recibidas_gastos'!E5="","",'Registrar recibidas_gastos'!E5) | F5: =IF('Registrar recibidas_gastos'!F5="","",VLOOKUP(CONCATENATE("TIPO FACTURA GASTO",'Registrar recibidas_gastos'!F5),'CODIGO-LITERAL'!$C:$D,2,FALSE)) | I5: =IF('Registrar recibidas_gastos'!I5="","",'Registrar recibidas_gastos'!I5) | J5: =IF('Registrar recibidas_gastos'!J5="","",'Registrar recibidas_gastos'!J5) | K5: =IF('Registrar recibidas_gastos'!K5="","",'Registrar recibidas_gastos'!K5) | L5: =IF('Registrar recibidas_gastos'!L5="","",'Registrar recibidas_gastos'!L5) | M5: =IF('Registrar recibidas_gastos'!M5="","",'Registrar recibidas_gastos'!M5) | N5: =IF('Registrar recibidas_gastos'!N5="","",'Registrar recibidas_gastos'!N5) | O5: =IF('Registrar recibidas_gastos'!O5="","",'Registrar recibidas_gastos'!O5) | P5: =IF(OR(LEFT('Registrar recibidas_gastos'!P5,2)="01",'Registrar recibidas_gastos'!P5=""),"",VLOOKUP(CONCATENATE("TIPO NIF",'Registrar recibidas_gastos'!P5),'CODIGO-LITERAL'!$C:$D,2,FALSE)) | Q5: =IF('Registrar recibidas_gastos'!Q5="","",'Registrar recibidas_gastos'!Q5) | R5: =IF('Registrar recibidas_gastos'!R5="","",'Registrar recibidas_gastos'!R5) | S5: =IF('Registrar recibidas_gastos'!S5="","",'Registrar recibidas_gastos'!S5) | T5: =IF('Registrar recibidas_gastos'!T5="","",VLOOKUP(CONCATENATE("CLAVE OPERACION GASTO",'Registrar recibidas_gastos'!T5),'CODIGO-LITERAL'!$C:$D,2,FALSE)) | U5: =IF(T5="","",IF(OR(T5="02",T5="08"),"N",IF('Registrar recibidas_gastos'!U5="","N",'Registrar recibidas_gastos'!U5))) | V5: =IF(T5="","",IF(OR(T5="07",T5="08",T5="09",F5="F5",F5="LC"),"N",IF('Registrar recibidas_gastos'!V5="","N",'Registrar recibidas_gastos'!V5))) | W5: =IF(AND(X5="",Y5=""),"",IF(AND(RECIBIDAS_GASTOS!$X5<>"",RECIBIDAS_GASTOS!$Y5<>""),"S",IF('Registrar recibidas_gastos'!W5="","N",'Registrar recibidas_gastos'!W5))) | X5: =IF('Registrar recibidas_gastos'!X5="","",'Registrar recibidas_gastos'!X5) | Y5: =IF('Registrar recibidas_gastos'!Y5="","",'Registrar recibidas_gastos'!Y5) | Z5: =IF('Registrar recibidas_gastos'!Z5="","",IF(AND(F5="",T5=""),"",IF(OR(T5="03",T5="05",T5="09"),AA5,SUM(AA5,AC5,AF5)))) | AA5: =IF('Registrar recibidas_gastos'!AA5="","",ROUND('Registrar recibidas_gastos'!AA5,2)) | AB5: =IF('Registrar recibidas_gastos'!AB5="","",'Registrar recibidas_gastos'!AB5) | AC5: =IF(OR(T5="03",T5="05"),0,IF('Registrar recibidas_gastos'!AC5="","",ROUND(AA5*AB5/100,2))) | AD5: =IF('Registrar recibidas_gastos'!AD5="","",ROUND('Registrar recibidas_gastos'!AD5,2)) | AE5: =IF('Registrar recibidas_gastos'!AE5="","",'Registrar recibidas_gastos'!AE5) | AF5: =IF('Registrar recibidas_gastos'!AF5="","",ROUND(AA5*AE5/100,2)) | AG5: =IF('Registrar recibidas_gastos'!AG5="","",'Registrar recibidas_gastos'!AG5) | AH5: =IF('Registrar recibidas_gastos'!AH5="","",'Registrar recibidas_gastos'!AH5) | AI5: =IF('Registrar recibidas_gastos'!AI5="","",VLOOKUP(CONCATENATE("MEDIO UTILIZADO",'Registrar recibidas_gastos'!AI5),'CODIGO-LITERAL'!$C:$D,2,FALSE)) | AJ5: =IF('Registrar recibidas_gastos'!AJ5="","",'Registrar recibidas_gastos'!AJ5) | AM5: =IF('Registrar recibidas_gastos'!AM5="","",'Registrar recibidas_gastos'!AM5) | AN5: =IF('Registrar recibidas_gastos'!AN5="","",VLOOKUP(CONCATENATE("SITUACION",'Registrar recibidas_gastos'!AN5),'CODIGO-LITERAL'!$C:$D,2,FALSE)) | AO5: =IF('Registrar recibidas_gastos'!AO5="","",'Registrar recibidas_gastos'!AO5) | AP5: =IF('Registrar recibidas_gastos'!AP5="","",'Registrar recibidas_gastos'!AP5)
A6: =IF('Registrar recibidas_gastos'!A6="","",'Registrar recibidas_gastos'!A6) | B6: =IF('Registrar recibidas_gastos'!B6="","",'Registrar recibidas_gastos'!B6) | C6: =IF('Registrar recibidas_gastos'!C6="","",VLOOKUP(CONCATENATE("ACTIVIDAD",'Registrar recibidas_gastos'!C6),'CODIGO-LITERAL'!$C:$D,2,FALSE)) | D6: =IF(OR(C6="C",C6="D"),"",IF(ISERROR(VLOOKUP(CONCATENATE(C6,'Registrar recibidas_gastos'!D6),'CODIGO-LITERAL'!$C:$D,2,FALSE)),"",VLOOKUP(CONCATENATE(C6,'Registrar recibidas_gastos'!D6),'CODIGO-LITERAL'!$C:$D,2,FALSE))) | E6: =IF('Registrar recibidas_gastos'!E6="","",'Registrar recibidas_gastos'!E6) | F6: =IF('Registrar recibidas_gastos'!F6="","",VLOOKUP(CONCATENATE("TIPO FACTURA GASTO",'Registrar recibidas_gastos'!F6),'CODIGO-LITERAL'!$C:$D,2,FALSE)) | I6: =IF('Registrar recibidas_gastos'!I6="","",'Registrar recibidas_gastos'!I6) | J6: =IF('Registrar recibidas_gastos'!J6="","",'Registrar recibidas_gastos'!J6) | K6: =IF('Registrar recibidas_gastos'!K6="","",'Registrar recibidas_gastos'!K6) | L6: =IF('Registrar recibidas_gastos'!L6="","",'Registrar recibidas_gastos'!L6) | M6: =IF('Registrar recibidas_gastos'!M6="","",'Registrar recibidas_gastos'!M6) | N6: =IF('Registrar recibidas_gastos'!N6="","",'Registrar recibidas_gastos'!N6) | O6: =IF('Registrar recibidas_gastos'!O6="","",'Registrar recibidas_gastos'!O6) | P6: =IF(OR(LEFT('Registrar recibidas_gastos'!P6,2)="01",'Registrar recibidas_gastos'!P6=""),"",VLOOKUP(CONCATENATE("TIPO NIF",'Registrar recibidas_gastos'!P6),'CODIGO-LITERAL'!$C:$D,2,FALSE)) | Q6: =IF('Registrar recibidas_gastos'!Q6="","",'Registrar recibidas_gastos'!Q6) | R6: =IF('Registrar recibidas_gastos'!R6="","",'Registrar recibidas_gastos'!R6) | S6: =IF('Registrar recibidas_gastos'!S6="","",'Registrar recibidas_gastos'!S6) | T6: =IF('Registrar recibidas_gastos'!T6="","",VLOOKUP(CONCATENATE("CLAVE OPERACION GASTO",'Registrar recibidas_gastos'!T6),'CODIGO-LITERAL'!$C:$D,2,FALSE)) | U6: =IF(T6="","",IF(OR(T6="02",T6="08"),"N",IF('Registrar recibidas_gastos'!U6="","N",'Registrar recibidas_gastos'!U6))) | V6: =IF(T6="","",IF(OR(T6="07",T6="08",T6="09",F6="F5",F6="LC"),"N",IF('Registrar recibidas_gastos'!V6="","N",'Registrar recibidas_gastos'!V6))) | W6: =IF(AND(X6="",Y6=""),"",IF(AND(RECIBIDAS_GASTOS!$X6<>"",RECIBIDAS_GASTOS!$Y6<>""),"S",IF('Registrar recibidas_gastos'!W6="","N",'Registrar recibidas_gastos'!W6))) | X6: =IF('Registrar recibidas_gastos'!X6="","",'Registrar recibidas_gastos'!X6) | Y6: =IF('Registrar recibidas_gastos'!Y6="","",'Registrar recibidas_gastos'!Y6) | Z6: =IF('Registrar recibidas_gastos'!Z6="","",IF(AND(F6="",T6=""),"",IF(OR(T6="03",T6="05",T6="09"),AA6,SUM(AA6,AC6,AF6)))) | AA6: =IF('Registrar recibidas_gastos'!AA6="","",ROUND('Registrar recibidas_gastos'!AA6,2)) | AB6: =IF('Registrar recibidas_gastos'!AB6="","",'Registrar recibidas_gastos'!AB6) | AC6: =IF(OR(T6="03",T6="05"),0,IF('Registrar recibidas_gastos'!AC6="","",ROUND(AA6*AB6/100,2))) | AD6: =IF('Registrar recibidas_gastos'!AD6="","",ROUND('Registrar recibidas_gastos'!AD6,2)) | AE6: =IF('Registrar recibidas_gastos'!AE6="","",'Registrar recibidas_gastos'!AE6) | AF6: =IF('Registrar recibidas_gastos'!AF6="","",ROUND(AA6*AE6/100,2)) | AG6: =IF('Registrar recibidas_gastos'!AG6="","",'Registrar recibidas_gastos'!AG6) | AH6: =IF('Registrar recibidas_gastos'!AH6="","",'Registrar recibidas_gastos'!AH6) | AI6: =IF('Registrar recibidas_gastos'!AI6="","",VLOOKUP(CONCATENATE("MEDIO UTILIZADO",'Registrar recibidas_gastos'!AI6),'CODIGO-LITERAL'!$C:$D,2,FALSE)) | AJ6: =IF('Registrar recibidas_gastos'!AJ6="","",'Registrar recibidas_gastos'!AJ6) | AM6: =IF('Registrar recibidas_gastos'!AM6="","",'Registrar recibidas_gastos'!AM6) | AN6: =IF('Registrar recibidas_gastos'!AN6="","",VLOOKUP(CONCATENATE("SITUACION",'Registrar recibidas_gastos'!AN6),'CODIGO-LITERAL'!$C:$D,2,FALSE)) | AO6: =IF('Registrar recibidas_gastos'!AO6="","",'Registrar recibidas_gastos'!AO6) | AP6: =IF('Registrar recibidas_gastos'!AP6="","",'Registrar recibidas_gastos'!AP6)
A7: =IF('Registrar recibidas_gastos'!A7="","",'Registrar recibidas_gastos'!A7) | B7: =IF('Registrar recibidas_gastos'!B7="","",'Registrar recibidas_gastos'!B7) | C7: =IF('Registrar recibidas_gastos'!C7="","",VLOOKUP(CONCATENATE("ACTIVIDAD",'Registrar recibidas_gastos'!C7),'CODIGO-LITERAL'!$C:$D,2,FALSE)) | D7: =IF(OR(C7="C",C7="D"),"",IF(ISERROR(VLOOKUP(CONCATENATE(C7,'Registrar recibidas_gastos'!D7),'CODIGO-LITERAL'!$C:$D,2,FALSE)),"",VLOOKUP(CONCATENATE(C7,'Registrar recibidas_gastos'!D7),'CODIGO-LITERAL'!$C:$D,2,FALSE))) | E7: =IF('Registrar recibidas_gastos'!E7="","",'Registrar recibidas_gastos'!E7) | F7: =IF('Registrar recibidas_gastos'!F7="","",VLOOKUP(CONCATENATE("TIPO FACTURA GASTO",'Registrar recibidas_gastos'!F7),'CODIGO-LITERAL'!$C:$D,2,FALSE)) | I7: =IF('Registrar recibidas_gastos'!I7="","",'Registrar recibidas_gastos'!I7) | J7: =IF('Registrar recibidas_gastos'!J7="","",'Registrar recibidas_gastos'!J7) | K7: =IF('Registrar recibidas_gastos'!K7="","",'Registrar recibidas_gastos'!K7) | L7: =IF('Registrar recibidas_gastos'!L7="","",'Registrar recibidas_gastos'!L7) | M7: =IF('Registrar recibidas_gastos'!M7="","",'Registrar recibidas_gastos'!M7) | N7: =IF('Registrar recibidas_gastos'!N7="","",'Registrar recibidas_gastos'!N7) | O7: =IF('Registrar recibidas_gastos'!O7="","",'Registrar recibidas_gastos'!O7) | P7: =IF(OR(LEFT('Registrar recibidas_gastos'!P7,2)="01",'Registrar recibidas_gastos'!P7=""),"",VLOOKUP(CONCATENATE("TIPO NIF",'Registrar recibidas_gastos'!P7),'CODIGO-LITERAL'!$C:$D,2,FALSE)) | Q7: =IF('Registrar recibidas_gastos'!Q7="","",'Registrar recibidas_gastos'!Q7) | R7: =IF('Registrar recibidas_gastos'!R7="","",'Registrar recibidas_gastos'!R7) | S7: =IF('Registrar recibidas_gastos'!S7="","",'Registrar recibidas_gastos'!S7) | T7: =IF('Registrar recibidas_gastos'!T7="","",VLOOKUP(CONCATENATE("CLAVE OPERACION GASTO",'Registrar recibidas_gastos'!T7),'CODIGO-LITERAL'!$C:$D,2,FALSE)) | U7: =IF(T7="","",IF(OR(T7="02",T7="08"),"N",IF('Registrar recibidas_gastos'!U7="","N",'Registrar recibidas_gastos'!U7))) | V7: =IF(T7="","",IF(OR(T7="07",T7="08",T7="09",F7="F5",F7="LC"),"N",IF('Registrar recibidas_gastos'!V7="","N",'Registrar recibidas_gastos'!V7))) | W7: =IF(AND(X7="",Y7=""),"",IF(AND(RECIBIDAS_GASTOS!$X7<>"",RECIBIDAS_GASTOS!$Y7<>""),"S",IF('Registrar recibidas_gastos'!W7="","N",'Registrar recibidas_gastos'!W7))) | X7: =IF('Registrar recibidas_gastos'!X7="","",'Registrar recibidas_gastos'!X7) | Y7: =IF('Registrar recibidas_gastos'!Y7="","",'Registrar recibidas_gastos'!Y7) | Z7: =IF('Registrar recibidas_gastos'!Z7="","",IF(AND(F7="",T7=""),"",IF(OR(T7="03",T7="05",T7="09"),AA7,SUM(AA7,AC7,AF7)))) | AA7: =IF('Registrar recibidas_gastos'!AA7="","",ROUND('Registrar recibidas_gastos'!AA7,2)) | AB7: =IF('Registrar recibidas_gastos'!AB7="","",'Registrar recibidas_gastos'!AB7) | AC7: =IF(OR(T7="03",T7="05"),0,IF('Registrar recibidas_gastos'!AC7="","",ROUND(AA7*AB7/100,2))) | AD7: =IF('Registrar recibidas_gastos'!AD7="","",ROUND('Registrar recibidas_gastos'!AD7,2)) | AE7: =IF('Registrar recibidas_gastos'!AE7="","",'Registrar recibidas_gastos'!AE7) | AF7: =IF('Registrar recibidas_gastos'!AF7="","",ROUND(AA7*AE7/100,2)) | AG7: =IF('Registrar recibidas_gastos'!AG7="","",'Registrar recibidas_gastos'!AG7) | AH7: =IF('Registrar recibidas_gastos'!AH7="","",'Registrar recibidas_gastos'!AH7) | AI7: =IF('Registrar recibidas_gastos'!AI7="","",VLOOKUP(CONCATENATE("MEDIO UTILIZADO",'Registrar recibidas_gastos'!AI7),'CODIGO-LITERAL'!$C:$D,2,FALSE)) | AJ7: =IF('Registrar recibidas_gastos'!AJ7="","",'Registrar recibidas_gastos'!AJ7) | AM7: =IF('Registrar recibidas_gastos'!AM7="","",'Registrar recibidas_gastos'!AM7) | AN7: =IF('Registrar recibidas_gastos'!AN7="","",VLOOKUP(CONCATENATE("SITUACION",'Registrar recibidas_gastos'!AN7),'CODIGO-LITERAL'!$C:$D,2,FALSE)) | AO7: =IF('Registrar recibidas_gastos'!AO7="","",'Registrar recibidas_gastos'!AO7) | AP7: =IF('Registrar recibidas_gastos'!AP7="","",'Registrar recibidas_gastos'!AP7)
A8: =IF('Registrar recibidas_gastos'!A8="","",'Registrar recibidas_gastos'!A8) | B8: =IF('Registrar recibidas_gastos'!B8="","",'Registrar recibidas_gastos'!B8) | C8: =IF('Registrar recibidas_gastos'!C8="","",VLOOKUP(CONCATENATE("ACTIVIDAD",'Registrar recibidas_gastos'!C8),'CODIGO-LITERAL'!$C:$D,2,FALSE)) | D8: =IF(OR(C8="C",C8="D"),"",IF(ISERROR(VLOOKUP(CONCATENATE(C8,'Registrar recibidas_gastos'!D8),'CODIGO-LITERAL'!$C:$D,2,FALSE)),"",VLOOKUP(CONCATENATE(C8,'Registrar recibidas_gastos'!D8),'CODIGO-LITERAL'!$C:$D,2,FALSE))) | E8: =IF('Registrar recibidas_gastos'!E8="","",'Registrar recibidas_gastos'!E8) | F8: =IF('Registrar recibidas_gastos'!F8="","",VLOOKUP(CONCATENATE("TIPO FACTURA GASTO",'Registrar recibidas_gastos'!F8),'CODIGO-LITERAL'!$C:$D,2,FALSE)) | I8: =IF('Registrar recibidas_gastos'!I8="","",'Registrar recibidas_gastos'!I8) | J8: =IF('Registrar recibidas_gastos'!J8="","",'Registrar recibidas_gastos'!J8) | K8: =IF('Registrar recibidas_gastos'!K8="","",'Registrar recibidas_gastos'!K8) | L8: =IF('Registrar recibidas_gastos'!L8="","",'Registrar recibidas_gastos'!L8) | M8: =IF('Registrar recibidas_gastos'!M8="","",'Registrar recibidas_gastos'!M8) | N8: =IF('Registrar recibidas_gastos'!N8="","",'Registrar recibidas_gastos'!N8) | O8: =IF('Registrar recibidas_gastos'!O8="","",'Registrar recibidas_gastos'!O8) | P8: =IF(OR(LEFT('Registrar recibidas_gastos'!P8,2)="01",'Registrar recibidas_gastos'!P8=""),"",VLOOKUP(CONCATENATE("TIPO NIF",'Registrar recibidas_gastos'!P8),'CODIGO-LITERAL'!$C:$D,2,FALSE)) | Q8: =IF('Registrar recibidas_gastos'!Q8="","",'Registrar recibidas_gastos'!Q8) | R8: =IF('Registrar recibidas_gastos'!R8="","",'Registrar recibidas_gastos'!R8) | S8: =IF('Registrar recibidas_gastos'!S8="","",'Registrar recibidas_gastos'!S8) | T8: =IF('Registrar recibidas_gastos'!T8="","",VLOOKUP(CONCATENATE("CLAVE OPERACION GASTO",'Registrar recibidas_gastos'!T8),'CODIGO-LITERAL'!$C:$D,2,FALSE)) | U8: =IF(T8="","",IF(OR(T8="02",T8="08"),"N",IF('Registrar recibidas_gastos'!U8="","N",'Registrar recibidas_gastos'!U8))) | V8: =IF(T8="","",IF(OR(T8="07",T8="08",T8="09",F8="F5",F8="LC"),"N",IF('Registrar recibidas_gastos'!V8="","N",'Registrar recibidas_gastos'!V8))) | W8: =IF(AND(X8="",Y8=""),"",IF(AND(RECIBIDAS_GASTOS!$X8<>"",RECIBIDAS_GASTOS!$Y8<>""),"S",IF('Registrar recibidas_gastos'!W8="","N",'Registrar recibidas_gastos'!W8))) | X8: =IF('Registrar recibidas_gastos'!X8="","",'Registrar recibidas_gastos'!X8) | Y8: =IF('Registrar recibidas_gastos'!Y8="","",'Registrar recibidas_gastos'!Y8) | Z8: =IF('Registrar recibidas_gastos'!Z8="","",IF(AND(F8="",T8=""),"",IF(OR(T8="03",T8="05",T8="09"),AA8,SUM(AA8,AC8,AF8)))) | AA8: =IF('Registrar recibidas_gastos'!AA8="","",ROUND('Registrar recibidas_gastos'!AA8,2)) | AB8: =IF('Registrar recibidas_gastos'!AB8="","",'Registrar recibidas_gastos'!AB8) | AC8: =IF(OR(T8="03",T8="05"),0,IF('Registrar recibidas_gastos'!AC8="","",ROUND(AA8*AB8/100,2))) | AD8: =IF('Registrar recibidas_gastos'!AD8="","",ROUND('Registrar recibidas_gastos'!AD8,2)) | AE8: =IF('Registrar recibidas_gastos'!AE8="","",'Registrar recibidas_gastos'!AE8) | AF8: =IF('Registrar recibidas_gastos'!AF8="","",ROUND(AA8*AE8/100,2)) | AG8: =IF('Registrar recibidas_gastos'!AG8="","",'Registrar recibidas_gastos'!AG8) | AH8: =IF('Registrar recibidas_gastos'!AH8="","",'Registrar recibidas_gastos'!AH8) | AI8: =IF('Registrar recibidas_gastos'!AI8="","",VLOOKUP(CONCATENATE("MEDIO UTILIZADO",'Registrar recibidas_gastos'!AI8),'CODIGO-LITERAL'!$C:$D,2,FALSE)) | AJ8: =IF('Registrar recibidas_gastos'!AJ8="","",'Registrar recibidas_gastos'!AJ8) | AM8: =IF('Registrar recibidas_gastos'!AM8="","",'Registrar recibidas_gastos'!AM8) | AN8: =IF('Registrar recibidas_gastos'!AN8="","",VLOOKUP(CONCATENATE("SITUACION",'Registrar recibidas_gastos'!AN8),'CODIGO-LITERAL'!$C:$D,2,FALSE)) | AO8: =IF('Registrar recibidas_gastos'!AO8="","",'Registrar recibidas_gastos'!AO8) | AP8: =IF('Registrar recibidas_gastos'!AP8="","",'Registrar recibidas_gastos'!AP8)
A9: =IF('Registrar recibidas_gastos'!A9="","",'Registrar recibidas_gastos'!A9) | B9: =IF('Registrar recibidas_gastos'!B9="","",'Registrar recibidas_gastos'!B9) | C9: =IF('Registrar recibidas_gastos'!C9="","",VLOOKUP(CONCATENATE("ACTIVIDAD",'Registrar recibidas_gastos'!C9),'CODIGO-LITERAL'!$C:$D,2,FALSE)) | D9: =IF(OR(C9="C",C9="D"),"",IF(ISERROR(VLOOKUP(CONCATENATE(C9,'Registrar recibidas_gastos'!D9),'CODIGO-LITERAL'!$C:$D,2,FALSE)),"",VLOOKUP(CONCATENATE(C9,'Registrar recibidas_gastos'!D9),'CODIGO-LITERAL'!$C:$D,2,FALSE))) | E9: =IF('Registrar recibidas_gastos'!E9="","",'Registrar recibidas_gastos'!E9) | F9: =IF('Registrar recibidas_gastos'!F9="","",VLOOKUP(CONCATENATE("TIPO FACTURA GASTO",'Registrar recibidas_gastos'!F9),'CODIGO-LITERAL'!$C:$D,2,FALSE)) | I9: =IF('Registrar recibidas_gastos'!I9="","",'Registrar recibidas_gastos'!I9) | J9: =IF('Registrar recibidas_gastos'!J9="","",'Registrar recibidas_gastos'!J9) | K9: =IF('Registrar recibidas_gastos'!K9="","",'Registrar recibidas_gastos'!K9) | L9: =IF('Registrar recibidas_gastos'!L9="","",'Registrar recibidas_gastos'!L9) | M9: =IF('Registrar recibidas_gastos'!M9="","",'Registrar recibidas_gastos'!M9) | N9: =IF('Registrar recibidas_gastos'!N9="","",'Registrar recibidas_gastos'!N9) | O9: =IF('Registrar recibidas_gastos'!O9="","",'Registrar recibidas_gastos'!O9) | P9: =IF(OR(LEFT('Registrar recibidas_gastos'!P9,2)="01",'Registrar recibidas_gastos'!P9=""),"",VLOOKUP(CONCATENATE("TIPO NIF",'Registrar recibidas_gastos'!P9),'CODIGO-LITERAL'!$C:$D,2,FALSE)) | Q9: =IF('Registrar recibidas_gastos'!Q9="","",'Registrar recibidas_gastos'!Q9) | R9: =IF('Registrar recibidas_gastos'!R9="","",'Registrar recibidas_gastos'!R9) | S9: =IF('Registrar recibidas_gastos'!S9="","",'Registrar recibidas_gastos'!S9) | T9: =IF('Registrar recibidas_gastos'!T9="","",VLOOKUP(CONCATENATE("CLAVE OPERACION GASTO",'Registrar recibidas_gastos'!T9),'CODIGO-LITERAL'!$C:$D,2,FALSE)) | U9: =IF(T9="","",IF(OR(T9="02",T9="08"),"N",IF('Registrar recibidas_gastos'!U9="","N",'Registrar recibidas_gastos'!U9))) | V9: =IF(T9="","",IF(OR(T9="07",T9="08",T9="09",F9="F5",F9="LC"),"N",IF('Registrar recibidas_gastos'!V9="","N",'Registrar recibidas_gastos'!V9))) | W9: =IF(AND(X9="",Y9=""),"",IF(AND(RECIBIDAS_GASTOS!$X9<>"",RECIBIDAS_GASTOS!$Y9<>""),"S",IF('Registrar recibidas_gastos'!W9="","N",'Registrar recibidas_gastos'!W9))) | X9: =IF('Registrar recibidas_gastos'!X9="","",'Registrar recibidas_gastos'!X9) | Y9: =IF('Registrar recibidas_gastos'!Y9="","",'Registrar recibidas_gastos'!Y9) | Z9: =IF('Registrar recibidas_gastos'!Z9="","",IF(AND(F9="",T9=""),"",IF(OR(T9="03",T9="05",T9="09"),AA9,SUM(AA9,AC9,AF9)))) | AA9: =IF('Registrar recibidas_gastos'!AA9="","",ROUND('Registrar recibidas_gastos'!AA9,2)) | AB9: =IF('Registrar recibidas_gastos'!AB9="","",'Registrar recibidas_gastos'!AB9) | AC9: =IF(OR(T9="03",T9="05"),0,IF('Registrar recibidas_gastos'!AC9="","",ROUND(AA9*AB9/100,2))) | AD9: =IF('Registrar recibidas_gastos'!AD9="","",ROUND('Registrar recibidas_gastos'!AD9,2)) | AE9: =IF('Registrar recibidas_gastos'!AE9="","",'Registrar recibidas_gastos'!AE9) | AF9: =IF('Registrar recibidas_gastos'!AF9="","",ROUND(AA9*AE9/100,2)) | AG9: =IF('Registrar recibidas_gastos'!AG9="","",'Registrar recibidas_gastos'!AG9) | AH9: =IF('Registrar recibidas_gastos'!AH9="","",'Registrar recibidas_gastos'!AH9) | AI9: =IF('Registrar recibidas_gastos'!AI9="","",VLOOKUP(CONCATENATE("MEDIO UTILIZADO",'Registrar recibidas_gastos'!AI9),'CODIGO-LITERAL'!$C:$D,2,FALSE)) | AJ9: =IF('Registrar recibidas_gastos'!AJ9="","",'Registrar recibidas_gastos'!AJ9) | AM9: =IF('Registrar recibidas_gastos'!AM9="","",'Registrar recibidas_gastos'!AM9) | AN9: =IF('Registrar recibidas_gastos'!AN9="","",VLOOKUP(CONCATENATE("SITUACION",'Registrar recibidas_gastos'!AN9),'CODIGO-LITERAL'!$C:$D,2,FALSE)) | AO9: =IF('Registrar recibidas_gastos'!AO9="","",'Registrar recibidas_gastos'!AO9) | AP9: =IF('Registrar recibidas_gastos'!AP9="","",'Registrar recibidas_gastos'!AP9)
A10: =IF('Registrar recibidas_gastos'!A10="","",'Registrar recibidas_gastos'!A10) | B10: =IF('Registrar recibidas_gastos'!B10="","",'Registrar recibidas_gastos'!B10) | C10: =IF('Registrar recibidas_gastos'!C10="","",VLOOKUP(CONCATENATE("ACTIVIDAD",'Registrar recibidas_gastos'!C10),'CODIGO-LITERAL'!$C:$D,2,FALSE)) | D10: =IF(OR(C10="C",C10="D"),"",IF(ISERROR(VLOOKUP(CONCATENATE(C10,'Registrar recibidas_gastos'!D10),'CODIGO-LITERAL'!$C:$D,2,FALSE)),"",VLOOKUP(CONCATENATE(C10,'Registrar recibidas_gastos'!D10),'CODIGO-LITERAL'!$C:$D,2,FALSE))) | E10: =IF('Registrar recibidas_gastos'!E10="","",'Registrar recibidas_gastos'!E10) | F10: =IF('Registrar recibidas_gastos'!F10="","",VLOOKUP(CONCATENATE("TIPO FACTURA GASTO",'Registrar recibidas_gastos'!F10),'CODIGO-LITERAL'!$C:$D,2,FALSE)) | I10: =IF('Registrar recibidas_gastos'!I10="","",'Registrar recibidas_gastos'!I10) | J10: =IF('Registrar recibidas_gastos'!J10="","",'Registrar recibidas_gastos'!J10) | K10: =IF('Registrar recibidas_gastos'!K10="","",'Registrar recibidas_gastos'!K10) | L10: =IF('Registrar recibidas_gastos'!L10="","",'Registrar recibidas_gastos'!L10) | M10: =IF('Registrar recibidas_gastos'!M10="","",'Registrar recibidas_gastos'!M10) | N10: =IF('Registrar recibidas_gastos'!N10="","",'Registrar recibidas_gastos'!N10) | O10: =IF('Registrar recibidas_gastos'!O10="","",'Registrar recibidas_gastos'!O10) | P10: =IF(OR(LEFT('Registrar recibidas_gastos'!P10,2)="01",'Registrar recibidas_gastos'!P10=""),"",VLOOKUP(CONCATENATE("TIPO NIF",'Registrar recibidas_gastos'!P10),'CODIGO-LITERAL'!$C:$D,2,FALSE)) | Q10: =IF('Registrar recibidas_gastos'!Q10="","",'Registrar recibidas_gastos'!Q10) | R10: =IF('Registrar recibidas_gastos'!R10="","",'Registrar recibidas_gastos'!R10) | S10: =IF('Registrar recibidas_gastos'!S10="","",'Registrar recibidas_gastos'!S10) | T10: =IF('Registrar recibidas_gastos'!T10="","",VLOOKUP(CONCATENATE("CLAVE OPERACION GASTO",'Registrar recibidas_gastos'!T10),'CODIGO-LITERAL'!$C:$D,2,FALSE)) | U10: =IF(T10="","",IF(OR(T10="02",T10="08"),"N",IF('Registrar recibidas_gastos'!U10="","N",'Registrar recibidas_gastos'!U10))) | V10: =IF(T10="","",IF(OR(T10="07",T10="08",T10="09",F10="F5",F10="LC"),"N",IF('Registrar recibidas_gastos'!V10="","N",'Registrar recibidas_gastos'!V10))) | W10: =IF(AND(X10="",Y10=""),"",IF(AND(RECIBIDAS_GASTOS!$X10<>"",RECIBIDAS_GASTOS!$Y10<>""),"S",IF('Registrar recibidas_gastos'!W10="","N",'Registrar recibidas_gastos'!W10))) | X10: =IF('Registrar recibidas_gastos'!X10="","",'Registrar recibidas_gastos'!X10) | Y10: =IF('Registrar recibidas_gastos'!Y10="","",'Registrar recibidas_gastos'!Y10) | Z10: =IF('Registrar recibidas_gastos'!Z10="","",IF(AND(F10="",T10=""),"",IF(OR(T10="03",T10="05",T10="09"),AA10,SUM(AA10,AC10,AF10)))) | AA10: =IF('Registrar recibidas_gastos'!AA10="","",ROUND('Registrar recibidas_gastos'!AA10,2)) | AB10: =IF('Registrar recibidas_gastos'!AB10="","",'Registrar recibidas_gastos'!AB10) | AC10: =IF(OR(T10="03",T10="05"),0,IF('Registrar recibidas_gastos'!AC10="","",ROUND(AA10*AB10/100,2))) | AD10: =IF('Registrar recibidas_gastos'!AD10="","",ROUND('Registrar recibidas_gastos'!AD10,2)) | AE10: =IF('Registrar recibidas_gastos'!AE10="","",'Registrar recibidas_gastos'!AE10) | AF10: =IF('Registrar recibidas_gastos'!AF10="","",ROUND(AA10*AE10/100,2)) | AG10: =IF('Registrar recibidas_gastos'!AG10="","",'Registrar recibidas_gastos'!AG10) | AH10: =IF('Registrar recibidas_gastos'!AH10="","",'Registrar recibidas_gastos'!AH10) | AI10: =IF('Registrar recibidas_gastos'!AI10="","",VLOOKUP(CONCATENATE("MEDIO UTILIZADO",'Registrar recibidas_gastos'!AI10),'CODIGO-LITERAL'!$C:$D,2,FALSE)) | AJ10: =IF('Registrar recibidas_gastos'!AJ10="","",'Registrar recibidas_gastos'!AJ10) | AM10: =IF('Registrar recibidas_gastos'!AM10="","",'Registrar recibidas_gastos'!AM10) | AN10: =IF('Registrar recibidas_gastos'!AN10="","",VLOOKUP(CONCATENATE("SITUACION",'Registrar recibidas_gastos'!AN10),'CODIGO-LITERAL'!$C:$D,2,FALSE)) | AO10: =IF('Registrar recibidas_gastos'!AO10="","",'Registrar recibidas_gastos'!AO10) | AP10: =IF('Registrar recibidas_gastos'!AP10="","",'Registrar recibidas_gastos'!AP10)
A11: =IF('Registrar recibidas_gastos'!A11="","",'Registrar recibidas_gastos'!A11) | B11: =IF('Registrar recibidas_gastos'!B11="","",'Registrar recibidas_gastos'!B11) | C11: =IF('Registrar recibidas_gastos'!C11="","",VLOOKUP(CONCATENATE("ACTIVIDAD",'Registrar recibidas_gastos'!C11),'CODIGO-LITERAL'!$C:$D,2,FALSE)) | D11: =IF(OR(C11="C",C11="D"),"",IF(ISERROR(VLOOKUP(CONCATENATE(C11,'Registrar recibidas_gastos'!D11),'CODIGO-LITERAL'!$C:$D,2,FALSE)),"",VLOOKUP(CONCATENATE(C11,'Registrar recibidas_gastos'!D11),'CODIGO-LITERAL'!$C:$D,2,FALSE))) | E11: =IF('Registrar recibidas_gastos'!E11="","",'Registrar recibidas_gastos'!E11) | F11: =IF('Registrar recibidas_gastos'!F11="","",VLOOKUP(CONCATENATE("TIPO FACTURA GASTO",'Registrar recibidas_gastos'!F11),'CODIGO-LITERAL'!$C:$D,2,FALSE)) | I11: =IF('Registrar recibidas_gastos'!I11="","",'Registrar recibidas_gastos'!I11) | J11: =IF('Registrar recibidas_gastos'!J11="","",'Registrar recibidas_gastos'!J11) | K11: =IF('Registrar recibidas_gastos'!K11="","",'Registrar recibidas_gastos'!K11) | L11: =IF('Registrar recibidas_gastos'!L11="","",'Registrar recibidas_gastos'!L11) | M11: =IF('Registrar recibidas_gastos'!M11="","",'Registrar recibidas_gastos'!M11) | N11: =IF('Registrar recibidas_gastos'!N11="","",'Registrar recibidas_gastos'!N11) | O11: =IF('Registrar recibidas_gastos'!O11="","",'Registrar recibidas_gastos'!O11) | P11: =IF(OR(LEFT('Registrar recibidas_gastos'!P11,2)="01",'Registrar recibidas_gastos'!P11=""),"",VLOOKUP(CONCATENATE("TIPO NIF",'Registrar recibidas_gastos'!P11),'CODIGO-LITERAL'!$C:$D,2,FALSE)) | Q11: =IF('Registrar recibidas_gastos'!Q11="","",'Registrar recibidas_gastos'!Q11) | R11: =IF('Registrar recibidas_gastos'!R11="","",'Registrar recibidas_gastos'!R11) | S11: =IF('Registrar recibidas_gastos'!S11="","",'Registrar recibidas_gastos'!S11) | T11: =IF('Registrar recibidas_gastos'!T11="","",VLOOKUP(CONCATENATE("CLAVE OPERACION GASTO",'Registrar recibidas_gastos'!T11),'CODIGO-LITERAL'!$C:$D,2,FALSE)) | U11: =IF(T11="","",IF(OR(T11="02",T11="08"),"N",IF('Registrar recibidas_gastos'!U11="","N",'Registrar recibidas_gastos'!U11))) | V11: =IF(T11="","",IF(OR(T11="07",T11="08",T11="09",F11="F5",F11="LC"),"N",IF('Registrar recibidas_gastos'!V11="","N",'Registrar recibidas_gastos'!V11))) | W11: =IF(AND(X11="",Y11=""),"",IF(AND(RECIBIDAS_GASTOS!$X11<>"",RECIBIDAS_GASTOS!$Y11<>""),"S",IF('Registrar recibidas_gastos'!W11="","N",'Registrar recibidas_gastos'!W11))) | X11: =IF('Registrar recibidas_gastos'!X11="","",'Registrar recibidas_gastos'!X11) | Y11: =IF('Registrar recibidas_gastos'!Y11="","",'Registrar recibidas_gastos'!Y11) | Z11: =IF('Registrar recibidas_gastos'!Z11="","",IF(AND(F11="",T11=""),"",IF(OR(T11="03",T11="05",T11="09"),AA11,SUM(AA11,AC11,AF11)))) | AA11: =IF('Registrar recibidas_gastos'!AA11="","",ROUND('Registrar recibidas_gastos'!AA11,2)) | AB11: =IF('Registrar recibidas_gastos'!AB11="","",'Registrar recibidas_gastos'!AB11) | AC11: =IF(OR(T11="03",T11="05"),0,IF('Registrar recibidas_gastos'!AC11="","",ROUND(AA11*AB11/100,2))) | AD11: =IF('Registrar recibidas_gastos'!AD11="","",ROUND('Registrar recibidas_gastos'!AD11,2)) | AE11: =IF('Registrar recibidas_gastos'!AE11="","",'Registrar recibidas_gastos'!AE11) | AF11: =IF('Registrar recibidas_gastos'!AF11="","",ROUND(AA11*AE11/100,2)) | AG11: =IF('Registrar recibidas_gastos'!AG11="","",'Registrar recibidas_gastos'!AG11) | AH11: =IF('Registrar recibidas_gastos'!AH11="","",'Registrar recibidas_gastos'!AH11) | AI11: =IF('Registrar recibidas_gastos'!AI11="","",VLOOKUP(CONCATENATE("MEDIO UTILIZADO",'Registrar recibidas_gastos'!AI11),'CODIGO-LITERAL'!$C:$D,2,FALSE)) | AJ11: =IF('Registrar recibidas_gastos'!AJ11="","",'Registrar recibidas_gastos'!AJ11) | AM11: =IF('Registrar recibidas_gastos'!AM11="","",'Registrar recibidas_gastos'!AM11) | AN11: =IF('Registrar recibidas_gastos'!AN11="","",VLOOKUP(CONCATENATE("SITUACION",'Registrar recibidas_gastos'!AN11),'CODIGO-LITERAL'!$C:$D,2,FALSE)) | AO11: =IF('Registrar recibidas_gastos'!AO11="","",'Registrar recibidas_gastos'!AO11) | AP11: =IF('Registrar recibidas_gastos'!AP11="","",'Registrar recibidas_gastos'!AP11)
A12: =IF('Registrar recibidas_gastos'!A12="","",'Registrar recibidas_gastos'!A12) | B12: =IF('Registrar recibidas_gastos'!B12="","",'Registrar recibidas_gastos'!B12) | C12: =IF('Registrar recibidas_gastos'!C12="","",VLOOKUP(CONCATENATE("ACTIVIDAD",'Registrar recibidas_gastos'!C12),'CODIGO-LITERAL'!$C:$D,2,FALSE)) | D12: =IF(OR(C12="C",C12="D"),"",IF(ISERROR(VLOOKUP(CONCATENATE(C12,'Registrar recibidas_gastos'!D12),'CODIGO-LITERAL'!$C:$D,2,FALSE)),"",VLOOKUP(CONCATENATE(C12,'Registrar recibidas_gastos'!D12),'CODIGO-LITERAL'!$C:$D,2,FALSE))) | E12: =IF('Registrar recibidas_gastos'!E12="","",'Registrar recibidas_gastos'!E12) | F12: =IF('Registrar recibidas_gastos'!F12="","",VLOOKUP(CONCATENATE("TIPO FACTURA GASTO",'Registrar recibidas_gastos'!F12),'CODIGO-LITERAL'!$C:$D,2,FALSE)) | I12: =IF('Registrar recibidas_gastos'!I12="","",'Registrar recibidas_gastos'!I12) | J12: =IF('Registrar recibidas_gastos'!J12="","",'Registrar recibidas_gastos'!J12) | K12: =IF('Registrar recibidas_gastos'!K12="","",'Registrar recibidas_gastos'!K12) | L12: =IF('Registrar recibidas_gastos'!L12="","",'Registrar recibidas_gastos'!L12) | M12: =IF('Registrar recibidas_gastos'!M12="","",'Registrar recibidas_gastos'!M12) | N12: =IF('Registrar recibidas_gastos'!N12="","",'Registrar recibidas_gastos'!N12) | O12: =IF('Registrar recibidas_gastos'!O12="","",'Registrar recibidas_gastos'!O12) | P12: =IF(OR(LEFT('Registrar recibidas_gastos'!P12,2)="01",'Registrar recibidas_gastos'!P12=""),"",VLOOKUP(CONCATENATE("TIPO NIF",'Registrar recibidas_gastos'!P12),'CODIGO-LITERAL'!$C:$D,2,FALSE)) | Q12: =IF('Registrar recibidas_gastos'!Q12="","",'Registrar recibidas_gastos'!Q12) | R12: =IF('Registrar recibidas_gastos'!R12="","",'Registrar recibidas_gastos'!R12) | S12: =IF('Registrar recibidas_gastos'!S12="","",'Registrar recibidas_gastos'!S12) | T12: =IF('Registrar recibidas_gastos'!T12="","",VLOOKUP(CONCATENATE("CLAVE OPERACION GASTO",'Registrar recibidas_gastos'!T12),'CODIGO-LITERAL'!$C:$D,2,FALSE)) | U12: =IF(T12="","",IF(OR(T12="02",T12="08"),"N",IF('Registrar recibidas_gastos'!U12="","N",'Registrar recibidas_gastos'!U12))) | V12: =IF(T12="","",IF(OR(T12="07",T12="08",T12="09",F12="F5",F12="LC"),"N",IF('Registrar recibidas_gastos'!V12="","N",'Registrar recibidas_gastos'!V12))) | W12: =IF(AND(X12="",Y12=""),"",IF(AND(RECIBIDAS_GASTOS!$X12<>"",RECIBIDAS_GASTOS!$Y12<>""),"S",IF('Registrar recibidas_gastos'!W12="","N",'Registrar recibidas_gastos'!W12))) | X12: =IF('Registrar recibidas_gastos'!X12="","",'Registrar recibidas_gastos'!X12) | Y12: =IF('Registrar recibidas_gastos'!Y12="","",'Registrar recibidas_gastos'!Y12) | Z12: =IF('Registrar recibidas_gastos'!Z12="","",IF(AND(F12="",T12=""),"",IF(OR(T12="03",T12="05",T12="09"),AA12,SUM(AA12,AC12,AF12)))) | AA12: =IF('Registrar recibidas_gastos'!AA12="","",ROUND('Registrar recibidas_gastos'!AA12,2)) | AB12: =IF('Registrar recibidas_gastos'!AB12="","",'Registrar recibidas_gastos'!AB12) | AC12: =IF(OR(T12="03",T12="05"),0,IF('Registrar recibidas_gastos'!AC12="","",ROUND(AA12*AB12/100,2))) | AD12: =IF('Registrar recibidas_gastos'!AD12="","",ROUND('Registrar recibidas_gastos'!AD12,2)) | AE12: =IF('Registrar recibidas_gastos'!AE12="","",'Registrar recibidas_gastos'!AE12) | AF12: =IF('Registrar recibidas_gastos'!AF12="","",ROUND(AA12*AE12/100,2)) | AG12: =IF('Registrar recibidas_gastos'!AG12="","",'Registrar recibidas_gastos'!AG12) | AH12: =IF('Registrar recibidas_gastos'!AH12="","",'Registrar recibidas_gastos'!AH12) | AI12: =IF('Registrar recibidas_gastos'!AI12="","",VLOOKUP(CONCATENATE("MEDIO UTILIZADO",'Registrar recibidas_gastos'!AI12),'CODIGO-LITERAL'!$C:$D,2,FALSE)) | AJ12: =IF('Registrar recibidas_gastos'!AJ12="","",'Registrar recibidas_gastos'!AJ12) | AM12: =IF('Registrar recibidas_gastos'!AM12="","",'Registrar recibidas_gastos'!AM12) | AN12: =IF('Registrar recibidas_gastos'!AN12="","",VLOOKUP(CONCATENATE("SITUACION",'Registrar recibidas_gastos'!AN12),'CODIGO-LITERAL'!$C:$D,2,FALSE)) | AO12: =IF('Registrar recibidas_gastos'!AO12="","",'Registrar recibidas_gastos'!AO12) | AP12: =IF('Registrar recibidas_gastos'!AP12="","",'Registrar recibidas_gastos'!AP12)
A13: =IF('Registrar recibidas_gastos'!A13="","",'Registrar recibidas_gastos'!A13) | B13: =IF('Registrar recibidas_gastos'!B13="","",'Registrar recibidas_gastos'!B13) | C13: =IF('Registrar recibidas_gastos'!C13="","",VLOOKUP(CONCATENATE("ACTIVIDAD",'Registrar recibidas_gastos'!C13),'CODIGO-LITERAL'!$C:$D,2,FALSE)) | D13: =IF(OR(C13="C",C13="D"),"",IF(ISERROR(VLOOKUP(CONCATENATE(C13,'Registrar recibidas_gastos'!D13),'CODIGO-LITERAL'!$C:$D,2,FALSE)),"",VLOOKUP(CONCATENATE(C13,'Registrar recibidas_gastos'!D13),'CODIGO-LITERAL'!$C:$D,2,FALSE))) | E13: =IF('Registrar recibidas_gastos'!E13="","",'Registrar recibidas_gastos'!E13) | F13: =IF('Registrar recibidas_gastos'!F13="","",VLOOKUP(CONCATENATE("TIPO FACTURA GASTO",'Registrar recibidas_gastos'!F13),'CODIGO-LITERAL'!$C:$D,2,FALSE)) | I13: =IF('Registrar recibidas_gastos'!I13="","",'Registrar recibidas_gastos'!I13) | J13: =IF('Registrar recibidas_gastos'!J13="","",'Registrar recibidas_gastos'!J13) | K13: =IF('Registrar recibidas_gastos'!K13="","",'Registrar recibidas_gastos'!K13) | L13: =IF('Registrar recibidas_gastos'!L13="","",'Registrar recibidas_gastos'!L13) | M13: =IF('Registrar recibidas_gastos'!M13="","",'Registrar recibidas_gastos'!M13) | N13: =IF('Registrar recibidas_gastos'!N13="","",'Registrar recibidas_gastos'!N13) | O13: =IF('Registrar recibidas_gastos'!O13="","",'Registrar recibidas_gastos'!O13) | P13: =IF(OR(LEFT('Registrar recibidas_gastos'!P13,2)="01",'Registrar recibidas_gastos'!P13=""),"",VLOOKUP(CONCATENATE("TIPO NIF",'Registrar recibidas_gastos'!P13),'CODIGO-LITERAL'!$C:$D,2,FALSE)) | Q13: =IF('Registrar recibidas_gastos'!Q13="","",'Registrar recibidas_gastos'!Q13) | R13: =IF('Registrar recibidas_gastos'!R13="","",'Registrar recibidas_gastos'!R13) | S13: =IF('Registrar recibidas_gastos'!S13="","",'Registrar recibidas_gastos'!S13) | T13: =IF('Registrar recibidas_gastos'!T13="","",VLOOKUP(CONCATENATE("CLAVE OPERACION GASTO",'Registrar recibidas_gastos'!T13),'CODIGO-LITERAL'!$C:$D,2,FALSE)) | U13: =IF(T13="","",IF(OR(T13="02",T13="08"),"N",IF('Registrar recibidas_gastos'!U13="","N",'Registrar recibidas_gastos'!U13))) | V13: =IF(T13="","",IF(OR(T13="07",T13="08",T13="09",F13="F5",F13="LC"),"N",IF('Registrar recibidas_gastos'!V13="","N",'Registrar recibidas_gastos'!V13))) | W13: =IF(AND(X13="",Y13=""),"",IF(AND(RECIBIDAS_GASTOS!$X13<>"",RECIBIDAS_GASTOS!$Y13<>""),"S",IF('Registrar recibidas_gastos'!W13="","N",'Registrar recibidas_gastos'!W13))) | X13: =IF('Registrar recibidas_gastos'!X13="","",'Registrar recibidas_gastos'!X13) | Y13: =IF('Registrar recibidas_gastos'!Y13="","",'Registrar recibidas_gastos'!Y13) | Z13: =IF('Registrar recibidas_gastos'!Z13="","",IF(AND(F13="",T13=""),"",IF(OR(T13="03",T13="05",T13="09"),AA13,SUM(AA13,AC13,AF13)))) | AA13: =IF('Registrar recibidas_gastos'!AA13="","",ROUND('Registrar recibidas_gastos'!AA13,2)) | AB13: =IF('Registrar recibidas_gastos'!AB13="","",'Registrar recibidas_gastos'!AB13) | AC13: =IF(OR(T13="03",T13="05"),0,IF('Registrar recibidas_gastos'!AC13="","",ROUND(AA13*AB13/100,2))) | AD13: =IF('Registrar recibidas_gastos'!AD13="","",ROUND('Registrar recibidas_gastos'!AD13,2)) | AE13: =IF('Registrar recibidas_gastos'!AE13="","",'Registrar recibidas_gastos'!AE13) | AF13: =IF('Registrar recibidas_gastos'!AF13="","",ROUND(AA13*AE13/100,2)) | AG13: =IF('Registrar recibidas_gastos'!AG13="","",'Registrar recibidas_gastos'!AG13) | AH13: =IF('Registrar recibidas_gastos'!AH13="","",'Registrar recibidas_gastos'!AH13) | AI13: =IF('Registrar recibidas_gastos'!AI13="","",VLOOKUP(CONCATENATE("MEDIO UTILIZADO",'Registrar recibidas_gastos'!AI13),'CODIGO-LITERAL'!$C:$D,2,FALSE)) | AJ13: =IF('Registrar recibidas_gastos'!AJ13="","",'Registrar recibidas_gastos'!AJ13) | AM13: =IF('Registrar recibidas_gastos'!AM13="","",'Registrar recibidas_gastos'!AM13) | AN13: =IF('Registrar recibidas_gastos'!AN13="","",VLOOKUP(CONCATENATE("SITUACION",'Registrar recibidas_gastos'!AN13),'CODIGO-LITERAL'!$C:$D,2,FALSE)) | AO13: =IF('Registrar recibidas_gastos'!AO13="","",'Registrar recibidas_gastos'!AO13) | AP13: =IF('Registrar recibidas_gastos'!AP13="","",'Registrar recibidas_gastos'!AP13)
A14: =IF('Registrar recibidas_gastos'!A14="","",'Registrar recibidas_gastos'!A14) | B14: =IF('Registrar recibidas_gastos'!B14="","",'Registrar recibidas_gastos'!B14) | C14: =IF('Registrar recibidas_gastos'!C14="","",VLOOKUP(CONCATENATE("ACTIVIDAD",'Registrar recibidas_gastos'!C14),'CODIGO-LITERAL'!$C:$D,2,FALSE)) | D14: =IF(OR(C14="C",C14="D"),"",IF(ISERROR(VLOOKUP(CONCATENATE(C14,'Registrar recibidas_gastos'!D14),'CODIGO-LITERAL'!$C:$D,2,FALSE)),"",VLOOKUP(CONCATENATE(C14,'Registrar recibidas_gastos'!D14),'CODIGO-LITERAL'!$C:$D,2,FALSE))) | E14: =IF('Registrar recibidas_gastos'!E14="","",'Registrar recibidas_gastos'!E14) | F14: =IF('Registrar recibidas_gastos'!F14="","",VLOOKUP(CONCATENATE("TIPO FACTURA GASTO",'Registrar recibidas_gastos'!F14),'CODIGO-LITERAL'!$C:$D,2,FALSE)) | I14: =IF('Registrar recibidas_gastos'!I14="","",'Registrar recibidas_gastos'!I14) | J14: =IF('Registrar recibidas_gastos'!J14="","",'Registrar recibidas_gastos'!J14) | K14: =IF('Registrar recibidas_gastos'!K14="","",'Registrar recibidas_gastos'!K14) | L14: =IF('Registrar recibidas_gastos'!L14="","",'Registrar recibidas_gastos'!L14) | M14: =IF('Registrar recibidas_gastos'!M14="","",'Registrar recibidas_gastos'!M14) | N14: =IF('Registrar recibidas_gastos'!N14="","",'Registrar recibidas_gastos'!N14) | O14: =IF('Registrar recibidas_gastos'!O14="","",'Registrar recibidas_gastos'!O14) | P14: =IF(OR(LEFT('Registrar recibidas_gastos'!P14,2)="01",'Registrar recibidas_gastos'!P14=""),"",VLOOKUP(CONCATENATE("TIPO NIF",'Registrar recibidas_gastos'!P14),'CODIGO-LITERAL'!$C:$D,2,FALSE)) | Q14: =IF('Registrar recibidas_gastos'!Q14="","",'Registrar recibidas_gastos'!Q14) | R14: =IF('Registrar recibidas_gastos'!R14="","",'Registrar recibidas_gastos'!R14) | S14: =IF('Registrar recibidas_gastos'!S14="","",'Registrar recibidas_gastos'!S14) | T14: =IF('Registrar recibidas_gastos'!T14="","",VLOOKUP(CONCATENATE("CLAVE OPERACION GASTO",'Registrar recibidas_gastos'!T14),'CODIGO-LITERAL'!$C:$D,2,FALSE)) | U14: =IF(T14="","",IF(OR(T14="02",T14="08"),"N",IF('Registrar recibidas_gastos'!U14="","N",'Registrar recibidas_gastos'!U14))) | V14: =IF(T14="","",IF(OR(T14="07",T14="08",T14="09",F14="F5",F14="LC"),"N",IF('Registrar recibidas_gastos'!V14="","N",'Registrar recibidas_gastos'!V14))) | W14: =IF(AND(X14="",Y14=""),"",IF(AND(RECIBIDAS_GASTOS!$X14<>"",RECIBIDAS_GASTOS!$Y14<>""),"S",IF('Registrar recibidas_gastos'!W14="","N",'Registrar recibidas_gastos'!W14))) | X14: =IF('Registrar recibidas_gastos'!X14="","",'Registrar recibidas_gastos'!X14) | Y14: =IF('Registrar recibidas_gastos'!Y14="","",'Registrar recibidas_gastos'!Y14) | Z14: =IF('Registrar recibidas_gastos'!Z14="","",IF(AND(F14="",T14=""),"",IF(OR(T14="03",T14="05",T14="09"),AA14,SUM(AA14,AC14,AF14)))) | AA14: =IF('Registrar recibidas_gastos'!AA14="","",ROUND('Registrar recibidas_gastos'!AA14,2)) | AB14: =IF('Registrar recibidas_gastos'!AB14="","",'Registrar recibidas_gastos'!AB14) | AC14: =IF(OR(T14="03",T14="05"),0,IF('Registrar recibidas_gastos'!AC14="","",ROUND(AA14*AB14/100,2))) | AD14: =IF('Registrar recibidas_gastos'!AD14="","",ROUND('Registrar recibidas_gastos'!AD14,2)) | AE14: =IF('Registrar recibidas_gastos'!AE14="","",'Registrar recibidas_gastos'!AE14) | AF14: =IF('Registrar recibidas_gastos'!AF14="","",ROUND(AA14*AE14/100,2)) | AG14: =IF('Registrar recibidas_gastos'!AG14="","",'Registrar recibidas_gastos'!AG14) | AH14: =IF('Registrar recibidas_gastos'!AH14="","",'Registrar recibidas_gastos'!AH14) | AI14: =IF('Registrar recibidas_gastos'!AI14="","",VLOOKUP(CONCATENATE("MEDIO UTILIZADO",'Registrar recibidas_gastos'!AI14),'CODIGO-LITERAL'!$C:$D,2,FALSE)) | AJ14: =IF('Registrar recibidas_gastos'!AJ14="","",'Registrar recibidas_gastos'!AJ14) | AM14: =IF('Registrar recibidas_gastos'!AM14="","",'Registrar recibidas_gastos'!AM14) | AN14: =IF('Registrar recibidas_gastos'!AN14="","",VLOOKUP(CONCATENATE("SITUACION",'Registrar recibidas_gastos'!AN14),'CODIGO-LITERAL'!$C:$D,2,FALSE)) | AO14: =IF('Registrar recibidas_gastos'!AO14="","",'Registrar recibidas_gastos'!AO14) | AP14: =IF('Registrar recibidas_gastos'!AP14="","",'Registrar recibidas_gastos'!AP14)
A15: =IF('Registrar recibidas_gastos'!A15="","",'Registrar recibidas_gastos'!A15) | B15: =IF('Registrar recibidas_gastos'!B15="","",'Registrar recibidas_gastos'!B15) | C15: =IF('Registrar recibidas_gastos'!C15="","",VLOOKUP(CONCATENATE("ACTIVIDAD",'Registrar recibidas_gastos'!C15),'CODIGO-LITERAL'!$C:$D,2,FALSE)) | D15: =IF(OR(C15="C",C15="D"),"",IF(ISERROR(VLOOKUP(CONCATENATE(C15,'Registrar recibidas_gastos'!D15),'CODIGO-LITERAL'!$C:$D,2,FALSE)),"",VLOOKUP(CONCATENATE(C15,'Registrar recibidas_gastos'!D15),'CODIGO-LITERAL'!$C:$D,2,FALSE))) | E15: =IF('Registrar recibidas_gastos'!E15="","",'Registrar recibidas_gastos'!E15) | F15: =IF('Registrar recibidas_gastos'!F15="","",VLOOKUP(CONCATENATE("TIPO FACTURA GASTO",'Registrar recibidas_gastos'!F15),'CODIGO-LITERAL'!$C:$D,2,FALSE)) | I15: =IF('Registrar recibidas_gastos'!I15="","",'Registrar recibidas_gastos'!I15) | J15: =IF('Registrar recibidas_gastos'!J15="","",'Registrar recibidas_gastos'!J15) | K15: =IF('Registrar recibidas_gastos'!K15="","",'Registrar recibidas_gastos'!K15) | L15: =IF('Registrar recibidas_gastos'!L15="","",'Registrar recibidas_gastos'!L15) | M15: =IF('Registrar recibidas_gastos'!M15="","",'Registrar recibidas_gastos'!M15) | N15: =IF('Registrar recibidas_gastos'!N15="","",'Registrar recibidas_gastos'!N15) | O15: =IF('Registrar recibidas_gastos'!O15="","",'Registrar recibidas_gastos'!O15) | P15: =IF(OR(LEFT('Registrar recibidas_gastos'!P15,2)="01",'Registrar recibidas_gastos'!P15=""),"",VLOOKUP(CONCATENATE("TIPO NIF",'Registrar recibidas_gastos'!P15),'CODIGO-LITERAL'!$C:$D,2,FALSE)) | Q15: =IF('Registrar recibidas_gastos'!Q15="","",'Registrar recibidas_gastos'!Q15) | R15: =IF('Registrar recibidas_gastos'!R15="","",'Registrar recibidas_gastos'!R15) | S15: =IF('Registrar recibidas_gastos'!S15="","",'Registrar recibidas_gastos'!S15) | T15: =IF('Registrar recibidas_gastos'!T15="","",VLOOKUP(CONCATENATE("CLAVE OPERACION GASTO",'Registrar recibidas_gastos'!T15),'CODIGO-LITERAL'!$C:$D,2,FALSE)) | U15: =IF(T15="","",IF(OR(T15="02",T15="08"),"N",IF('Registrar recibidas_gastos'!U15="","N",'Registrar recibidas_gastos'!U15))) | V15: =IF(T15="","",IF(OR(T15="07",T15="08",T15="09",F15="F5",F15="LC"),"N",IF('Registrar recibidas_gastos'!V15="","N",'Registrar recibidas_gastos'!V15))) | W15: =IF(AND(X15="",Y15=""),"",IF(AND(RECIBIDAS_GASTOS!$X15<>"",RECIBIDAS_GASTOS!$Y15<>""),"S",IF('Registrar recibidas_gastos'!W15="","N",'Registrar recibidas_gastos'!W15))) | X15: =IF('Registrar recibidas_gastos'!X15="","",'Registrar recibidas_gastos'!X15) | Y15: =IF('Registrar recibidas_gastos'!Y15="","",'Registrar recibidas_gastos'!Y15) | Z15: =IF('Registrar recibidas_gastos'!Z15="","",IF(AND(F15="",T15=""),"",IF(OR(T15="03",T15="05",T15="09"),AA15,SUM(AA15,AC15,AF15)))) | AA15: =IF('Registrar recibidas_gastos'!AA15="","",ROUND('Registrar recibidas_gastos'!AA15,2)) | AB15: =IF('Registrar recibidas_gastos'!AB15="","",'Registrar recibidas_gastos'!AB15) | AC15: =IF(OR(T15="03",T15="05"),0,IF('Registrar recibidas_gastos'!AC15="","",ROUND(AA15*AB15/100,2))) | AD15: =IF('Registrar recibidas_gastos'!AD15="","",ROUND('Registrar recibidas_gastos'!AD15,2)) | AE15: =IF('Registrar recibidas_gastos'!AE15="","",'Registrar recibidas_gastos'!AE15) | AF15: =IF('Registrar recibidas_gastos'!AF15="","",ROUND(AA15*AE15/100,2)) | AG15: =IF('Registrar recibidas_gastos'!AG15="","",'Registrar recibidas_gastos'!AG15) | AH15: =IF('Registrar recibidas_gastos'!AH15="","",'Registrar recibidas_gastos'!AH15) | AI15: =IF('Registrar recibidas_gastos'!AI15="","",VLOOKUP(CONCATENATE("MEDIO UTILIZADO",'Registrar recibidas_gastos'!AI15),'CODIGO-LITERAL'!$C:$D,2,FALSE)) | AJ15: =IF('Registrar recibidas_gastos'!AJ15="","",'Registrar recibidas_gastos'!AJ15) | AM15: =IF('Registrar recibidas_gastos'!AM15="","",'Registrar recibidas_gastos'!AM15) | AN15: =IF('Registrar recibidas_gastos'!AN15="","",VLOOKUP(CONCATENATE("SITUACION",'Registrar recibidas_gastos'!AN15),'CODIGO-LITERAL'!$C:$D,2,FALSE)) | AO15: =IF('Registrar recibidas_gastos'!AO15="","",'Registrar recibidas_gastos'!AO15) | AP15: =IF('Registrar recibidas_gastos'!AP15="","",'Registrar recibidas_gastos'!AP15)
... A103: =IF('Registrar recibidas_gastos'!A103="","",'Registrar recibidas_gastos'!A103) | B103: =IF('Registrar recibidas_gastos'!B103="","",'Registrar recibidas_gastos'!B103) | C103: =IF('Registrar recibidas_gastos'!C103="","",VLOOKUP(CONCATENATE("ACTIVIDAD",'Registrar recibidas_gastos'!C103),'CODIGO-LITERAL'!$C:$D,2,FALSE)) | D103: =IF(OR(C103="C",C103="D"),"",IF(ISERROR(VLOOKUP(CONCATENATE(C103,'Registrar recibidas_gastos'!D103),'CODIGO-LITERAL'!$C:$D,2,FALSE)),"",VLOOKUP(CONCATENATE(C103,'Registrar recibidas_gastos'!D103),'CODIGO-LITERAL'!$C:$D,2,FALSE))) | E103: =IF('Registrar recibidas_gastos'!E103="","",'Registrar recibidas_gastos'!E103) | F103: =IF('Registrar recibidas_gastos'!F103="","",VLOOKUP(CONCATENATE("TIPO FACTURA GASTO",'Registrar recibidas_gastos'!F103),'CODIGO-LITERAL'!$C:$D,2,FALSE)) | I103: =IF('Registrar recibidas_gastos'!I103="","",'Registrar recibidas_gastos'!I103) | J103: =IF('Registrar recibidas_gastos'!J103="","",'Registrar recibidas_gastos'!J103) | K103: =IF('Registrar recibidas_gastos'!K103="","",'Registrar recibidas_gastos'!K103) | L103: =IF('Registrar recibidas_gastos'!L103="","",'Registrar recibidas_gastos'!L103) | M103: =IF('Registrar recibidas_gastos'!M103="","",'Registrar recibidas_gastos'!M103) | N103: =IF('Registrar recibidas_gastos'!N103="","",'Registrar recibidas_gastos'!N103) | O103: =IF('Registrar recibidas_gastos'!O103="","",'Registrar recibidas_gastos'!O103) | P103: =IF(OR(LEFT('Registrar recibidas_gastos'!P103,2)="01",'Registrar recibidas_gastos'!P103=""),"",VLOOKUP(CONCATENATE("TIPO NIF",'Registrar recibidas_gastos'!P103),'CODIGO-LITERAL'!$C:$D,2,FALSE)) | Q103: =IF('Registrar recibidas_gastos'!Q103="","",'Registrar recibidas_gastos'!Q103) | R103: =IF('Registrar recibidas_gastos'!R103="","",'Registrar recibidas_gastos'!R103) | S103: =IF('Registrar recibidas_gastos'!S103="","",'Registrar recibidas_gastos'!S103) | T103: =IF('Registrar recibidas_gastos'!T103="","",VLOOKUP(CONCATENATE("CLAVE OPERACION GASTO",'Registrar recibidas_gastos'!T103),'CODIGO-LITERAL'!$C:$D,2,FALSE)) | U103: =IF(T103="","",IF(OR(T103="02",T103="08"),"N",IF('Registrar recibidas_gastos'!U103="","N",'Registrar recibidas_gastos'!U103))) | V103: =IF(T103="","",IF(OR(T103="07",T103="08",T103="09",F103="F5",F103="LC"),"N",IF('Registrar recibidas_gastos'!V103="","N",'Registrar recibidas_gastos'!V103))) | W103: =IF(AND(X103="",Y103=""),"",IF(AND(RECIBIDAS_GASTOS!$X103<>"",RECIBIDAS_GASTOS!$Y103<>""),"S",IF('Registrar recibidas_gastos'!W103="","N",'Registrar recibidas_gastos'!W103))) | X103: =IF('Registrar recibidas_gastos'!X103="","",'Registrar recibidas_gastos'!X103) | Y103: =IF('Registrar recibidas_gastos'!Y103="","",'Registrar recibidas_gastos'!Y103) | Z103: =IF('Registrar recibidas_gastos'!Z103="","",IF(AND(F103="",T103=""),"",IF(OR(T103="03",T103="05",T103="09"),AA103,SUM(AA103,AC103,AF103)))) | AA103: =IF('Registrar recibidas_gastos'!AA103="","",ROUND('Registrar recibidas_gastos'!AA103,2)) | AB103: =IF('Registrar recibidas_gastos'!AB103="","",'Registrar recibidas_gastos'!AB103) | AC103: =IF(OR(T103="03",T103="05"),0,IF('Registrar recibidas_gastos'!AC103="","",ROUND(AA103*AB103/100,2))) | AD103: =IF('Registrar recibidas_gastos'!AD103="","",ROUND('Registrar recibidas_gastos'!AD103,2)) | AE103: =IF('Registrar recibidas_gastos'!AE103="","",'Registrar recibidas_gastos'!AE103) | AF103: =IF('Registrar recibidas_gastos'!AF103="","",ROUND(AA103*AE103/100,2)) | AG103: =IF('Registrar recibidas_gastos'!AG103="","",'Registrar recibidas_gastos'!AG103) | AH103: =IF('Registrar recibidas_gastos'!AH103="","",'Registrar recibidas_gastos'!AH103) | AI103: =IF('Registrar recibidas_gastos'!AI103="","",VLOOKUP(CONCATENATE("MEDIO UTILIZADO",'Registrar recibidas_gastos'!AI103),'CODIGO-LITERAL'!$C:$D,2,FALSE)) | AJ103: =IF('Registrar recibidas_gastos'!AJ103="","",'Registrar recibidas_gastos'!AJ103) | AM103: =IF('Registrar recibidas_gastos'!AM103="","",'Registrar recibidas_gastos'!AM103) | AN103: =IF('Registrar recibidas_gastos'!AN103="","",VLOOKUP(CONCATENATE("SITUACION",'Registrar recibidas_gastos'!AN103),'CODIGO-LITERAL'!$C:$D,2,FALSE)) | AO103: =IF('Registrar recibidas_gastos'!AO103="","",'Registrar recibidas_gastos'!AO103) | AP103: =IF('Registrar recibidas_gastos'!AP103="","",'Registrar recibidas_gastos'!AP103)

Sheet BIENES-INVERSIÓN
A1: Autoliquidación | C1: Actividad | F1: Tipo de Bien | G1: Descripción del Bien | I1: Fecha Inicio Utilización | J1: Valor Adquisición | K1: Valor Amortizable | L1: Método de Amortización | M1: Porcentaje de Amortización | N1: Amortización | R1: Fecha Expedición | S1: Identificación Factura del Expedidor | U1: Número Recepción | V1: Número Recepción Final | W1: NIF Expedidor | Z1: Nombre Expedidor | AA1: Año de Inicio Utilización | AE1: Regularización Anual | AH1: Baja del Bien | AJ1: Identificación de la Factura de Transmisión del Bien | AM1: Registro Acuerdo Facturación | AN1: Inmueble | AP1: Refrencia Externa
A2: Ejercicio | B2: Periodo | C2: Código | D2: Tipo | E2: Grupo o Epígrafe del IAE | G2: Identificador | H2: Literal | N2: Acumulada al Inicio | O2: Cuota Resultante | P2: Acumulada al final | Q2: Pendiente | S2: (Serie-Número) | T2: Número-Final | W2: Tipo | X2: Código País | Y2: Identificación | AA2: Base Imponible | AB2: Tipo de IVA | AC2: Prorrata Definitiva | AD2: Cuota Deducible | AE2: Prorrata Definitiva | AF2: Cuota Deducible | AG2: Cuota a Regularizar | AH2: Fecha | AI2: Causa | AJ2: Serie | AK2: Número | AL2: Número-Final | AN2: Situación | AO2: Referencia Catastral
A3: Decimal (4,0) | B3: Alfanumérico (2) | C3: Alfanumérico (1) | D3: Alfanumérico (2) | E3: Alfanumérico (4) | F3: Alfanumérico (2) | G3: Alfanumérico (40) | H3: Alfanumérico (160) | I3: Fecha(dd/mm/yyyy) | J3: Decimal(12,2) | K3: Decimal(12,2) | L3: Alfanumérico (2) | M3: Decimal (4,2) | N3: Decimal(12,2) | O3: Decimal(12,2) | P3: Decimal(12,2) | Q3: Decimal(12,2) | R3: Fecha(dd/mm/yyyy) | S3: Alfanumérico (40) | T3: Alfanumérico (20) | U3: Alfanumérico (20) | V3: Alfanumérico (20) | W3: Alfanumérico (2) | X3: Alfanumérico (2) | Y3: Alfanumérico (20) | Z3: Alfanumérico (40) | AA3: Decimal(12,2) | AB3: Decimal(4,2) | AC3: Decimal(5,2) | AD3: Decimal(12,2) | AE3: Decimal(5,2) | AF3: Decimal(12,2) | AG3: Decimal(12,2) | AH3: Fecha(dd/mm/yyyy) | AI3: Alfanumérico (2) | AJ3: Alfanumérico (20) | AK3: Alfanumérico (20) | AL3: Alfanumérico (20) | AM3: Alfanumérico (15) | AN3: Alfanumérico (1) | AO3: Alfanumérico (20) | AP3: Alfanumérico (40)
A4: =IF('Registrar bienes de inversión'!A4="","",'Registrar bienes de inversión'!A4) | B4: =IF('Registrar bienes de inversión'!B4="","",'Registrar bienes de inversión'!B4) | C4: =IF('Registrar bienes de inversión'!C4="","",VLOOKUP(CONCATENATE("ACTIVIDAD",'Registrar bienes de inversión'!C4),'CODIGO-LITERAL'!$C:$D,2,FALSE)) | D4: =IF(OR(C4="C",C4="D"),"",IF(ISERROR(VLOOKUP(CONCATENATE(C4,'Registrar bienes de inversión'!D4),'CODIGO-LITERAL'!$C:$D,2,FALSE)),"",VLOOKUP(CONCATENATE(C4,'Registrar bienes de inversión'!D4),'CODIGO-LITERAL'!$C:$D,2,FALSE))) | E4: =IF('Registrar bienes de inversión'!E4="","",'Registrar bienes de inversión'!E4) | F4: =IF('Registrar bienes de inversión'!F4="","",VLOOKUP(CONCATENATE("TIPO BIEN",'Registrar bienes de inversión'!F4),'CODIGO-LITERAL'!$C:$D,2,FALSE)) | G4: =IF('Registrar bienes de inversión'!G4="","",'Registrar bienes de inversión'!G4) | H4: =IF('Registrar bienes de inversión'!H4="","",'Registrar bienes de inversión'!H4) | I4: =IF('Registrar bienes de inversión'!I4="","",'Registrar bienes de inversión'!I4) | J4: =IF('Registrar bienes de inversión'!J4="","",'Registrar bienes de inversión'!J4) | K4: =IF('Registrar bienes de inversión'!K4="","",'Registrar bienes de inversión'!K4) | L4: =IF('Registrar bienes de inversión'!L4="","",VLOOKUP(CONCATENATE("METODO AMORTIZACION",'Registrar bienes de inversión'!L4),'CODIGO-LITERAL'!$C:$D,2,FALSE)) | M4: =IF('Registrar bienes de inversión'!M4="","",'Registrar bienes de inversión'!M4) | N4: =IF('Registrar bienes de inversión'!N4="","",'Registrar bienes de inversión'!N4) | O4: =IF('Registrar bienes de inversión'!O4="","",'Registrar bienes de inversión'!O4) | P4: =IF('Registrar bienes de inversión'!P4="","",'Registrar bienes de inversión'!P4) | Q4: =IF('Registrar bienes de inversión'!Q4="","",'Registrar bienes de inversión'!Q4) | R4: =IF('Registrar bienes de inversión'!R4="","",'Registrar bienes de inversión'!R4) | S4: =IF('Registrar bienes de inversión'!S4="","",'Registrar bienes de inversión'!S4) | T4: =IF('Registrar bienes de inversión'!T4="","",'Registrar bienes de inversión'!T4) | ... V4: =IF('Registrar bienes de inversión'!V4="","",'Registrar bienes de inversión'!V4) | W4: =IF(OR('Registrar bienes de inversión'!W4="",LEFT('Registrar bienes de inversión'!W4,2)="01"),"",VLOOKUP(CONCATENATE("TIPO NIF",'Registrar bienes de inversión'!W4),'CODIGO-LITERAL'!$C:$D,2,FALSE)) | X4: =IF('Registrar bienes de inversión'!X4="","",'Registrar bienes de inversión'!X4) | Y4: =IF('Registrar bienes de inversión'!Y4="","",'Registrar bienes de inversión'!Y4) | Z4: =IF('Registrar bienes de inversión'!Z4="","",'Registrar bienes de inversión'!Z4) | AA4: =IF('Registrar bienes de inversión'!AA4="","",ROUND('Registrar bienes de inversión'!AA4,2)) | AB4: =IF('Registrar bienes de inversión'!AB4="","",'Registrar bienes de inversión'!AB4) | AC4: =IF('Registrar bienes de inversión'!AC4="","",ROUND('Registrar bienes de inversión'!AC4,2)) | AD4: =IF('Registrar bienes de inversión'!AD4="","",ROUND('Registrar bienes de inversión'!AD4,2)) | AE4: =IF('Registrar bienes de inversión'!AE4="","",ROUND('Registrar bienes de inversión'!AE4,2)) | AF4: =IF('Registrar bienes de inversión'!AF4="","",ROUND('Registrar bienes de inversión'!AF4,2)) | AG4: =IF('Registrar bienes de inversión'!AG4="","",ROUND('Registrar bienes de inversión'!AG4,2)) | AH4: =IF('Registrar bienes de inversión'!AH4="","",'Registrar bienes de inversión'!AH4) | AI4: =IF('Registrar bienes de inversión'!AI4="","",VLOOKUP(CONCATENATE("CAUSA BAJA BIEN",'Registrar bienes de inversión'!AI4),'CODIGO-LITERAL'!$C:$D,2,FALSE)) | AJ4: =IF('Registrar bienes de inversión'!AJ4="","",'Registrar bienes de inversión'!AJ4) | AK4: =IF('Registrar bienes de inversión'!AK4="","",'Registrar bienes de inversión'!AK4) | AL4: =IF('Registrar bienes de inversión'!AL4="","",'Registrar bienes de inversión'!AL4) | AM4: =IF('Registrar bienes de inversión'!AM4="","",'Registrar bienes de inversión'!AM4) | AN4: =IF('Registrar bienes de inversión'!AN4="","",VLOOKUP(CONCATENATE("SITUACION",'Registrar bienes de inversión'!AN4),'CODIGO-LITERAL'!$C:$D,2,FALSE)) | AO4: =IF('Registrar bienes de inversión'!AO4="","",'Registrar bienes de inversión'!AO4) | AP4: =IF('Registrar bienes de inversión'!AP4="","",'Registrar bienes de inversión'!AP4)
A5: =IF('Registrar bienes de inversión'!A5="","",'Registrar bienes de inversión'!A5) | B5: =IF('Registrar bienes de inversión'!B5="","",'Registrar bienes de inversión'!B5) | C5: =IF('Registrar bienes de inversión'!C5="","",VLOOKUP(CONCATENATE("ACTIVIDAD",'Registrar bienes de inversión'!C5),'CODIGO-LITERAL'!$C:$D,2,FALSE)) | D5: =IF(OR(C5="C",C5="D"),"",IF(ISERROR(VLOOKUP(CONCATENATE(C5,'Registrar bienes de inversión'!D5),'CODIGO-LITERAL'!$C:$D,2,FALSE)),"",VLOOKUP(CONCATENATE(C5,'Registrar bienes de inversión'!D5),'CODIGO-LITERAL'!$C:$D,2,FALSE))) | E5: =IF('Registrar bienes de inversión'!E5="","",'Registrar bienes de inversión'!E5) | F5: =IF('Registrar bienes de inversión'!F5="","",VLOOKUP(CONCATENATE("TIPO BIEN",'Registrar bienes de inversión'!F5),'CODIGO-LITERAL'!$C:$D,2,FALSE)) | G5: =IF('Registrar bienes de inversión'!G5="","",'Registrar bienes de inversión'!G5) | H5: =IF('Registrar bienes de inversión'!H5="","",'Registrar bienes de inversión'!H5) | I5: =IF('Registrar bienes de inversión'!I5="","",'Registrar bienes de inversión'!I5) | J5: =IF('Registrar bienes de inversión'!J5="","",'Registrar bienes de inversión'!J5) | K5: =IF('Registrar bienes de inversión'!K5="","",'Registrar bienes de inversión'!K5) | L5: =IF('Registrar bienes de inversión'!L5="","",VLOOKUP(CONCATENATE("METODO AMORTIZACION",'Registrar bienes de inversión'!L5),'CODIGO-LITERAL'!$C:$D,2,FALSE)) | M5: =IF('Registrar bienes de inversión'!M5="","",'Registrar bienes de inversión'!M5) | N5: =IF('Registrar bienes de inversión'!N5="","",'Registrar bienes de inversión'!N5) | O5: =IF('Registrar bienes de inversión'!O5="","",'Registrar bienes de inversión'!O5) | P5: =IF('Registrar bienes de inversión'!P5="","",'Registrar bienes de inversión'!P5) | Q5: =IF('Registrar bienes de inversión'!Q5="","",'Registrar bienes de inversión'!Q5) | R5: =IF('Registrar bienes de inversión'!R5="","",'Registrar bienes de inversión'!R5) | S5: =IF('Registrar bienes de inversión'!S5="","",'Registrar bienes de inversión'!S5) | T5: =IF('Registrar bienes de inversión'!T5="","",'Registrar bienes de inversión'!T5) | ... V5: =IF('Registrar bienes de inversión'!V5="","",'Registrar bienes de inversión'!V5) | W5: =IF(OR('Registrar bienes de inversión'!W5="",LEFT('Registrar bienes de inversión'!W5,2)="01"),"",VLOOKUP(CONCATENATE("TIPO NIF",'Registrar bienes de inversión'!W5),'CODIGO-LITERAL'!$C:$D,2,FALSE)) | X5: =IF('Registrar bienes de inversión'!X5="","",'Registrar bienes de inversión'!X5) | Y5: =IF('Registrar bienes de inversión'!Y5="","",'Registrar bienes de inversión'!Y5) | Z5: =IF('Registrar bienes de inversión'!Z5="","",'Registrar bienes de inversión'!Z5) | AA5: =IF('Registrar bienes de inversión'!AA5="","",ROUND('Registrar bienes de inversión'!AA5,2)) | AB5: =IF('Registrar bienes de inversión'!AB5="","",'Registrar bienes de inversión'!AB5) | AC5: =IF('Registrar bienes de inversión'!AC5="","",ROUND('Registrar bienes de inversión'!AC5,2)) | AD5: =IF('Registrar bienes de inversión'!AD5="","",ROUND('Registrar bienes de inversión'!AD5,2)) | AE5: =IF('Registrar bienes de inversión'!AE5="","",ROUND('Registrar bienes de inversión'!AE5,2)) | AF5: =IF('Registrar bienes de inversión'!AF5="","",ROUND('Registrar bienes de inversión'!AF5,2)) | AG5: =IF('Registrar bienes de inversión'!AG5="","",ROUND('Registrar bienes de inversión'!AG5,2)) | AH5: =IF('Registrar bienes de inversión'!AH5="","",'Registrar bienes de inversión'!AH5) | AI5: =IF('Registrar bienes de inversión'!AI5="","",VLOOKUP(CONCATENATE("CAUSA BAJA BIEN",'Registrar bienes de inversión'!AI5),'CODIGO-LITERAL'!$C:$D,2,FALSE)) | AJ5: =IF('Registrar bienes de inversión'!AJ5="","",'Registrar bienes de inversión'!AJ5) | AK5: =IF('Registrar bienes de inversión'!AK5="","",'Registrar bienes de inversión'!AK5) | AL5: =IF('Registrar bienes de inversión'!AL5="","",'Registrar bienes de inversión'!AL5) | AM5: =IF('Registrar bienes de inversión'!AM5="","",'Registrar bienes de inversión'!AM5) | AN5: =IF('Registrar bienes de inversión'!AN5="","",VLOOKUP(CONCATENATE("SITUACION",'Registrar bienes de inversión'!AN5),'CODIGO-LITERAL'!$C:$D,2,FALSE)) | AO5: =IF('Registrar bienes de inversión'!AO5="","",'Registrar bienes de inversión'!AO5) | AP5: =IF('Registrar bienes de inversión'!AP5="","",'Registrar bienes de inversión'!AP5)
A6: =IF('Registrar bienes de inversión'!A6="","",'Registrar bienes de inversión'!A6) | B6: =IF('Registrar bienes de inversión'!B6="","",'Registrar bienes de inversión'!B6) | C6: =IF('Registrar bienes de inversión'!C6="","",VLOOKUP(CONCATENATE("ACTIVIDAD",'Registrar bienes de inversión'!C6),'CODIGO-LITERAL'!$C:$D,2,FALSE)) | D6: =IF(OR(C6="C",C6="D"),"",IF(ISERROR(VLOOKUP(CONCATENATE(C6,'Registrar bienes de inversión'!D6),'CODIGO-LITERAL'!$C:$D,2,FALSE)),"",VLOOKUP(CONCATENATE(C6,'Registrar bienes de inversión'!D6),'CODIGO-LITERAL'!$C:$D,2,FALSE))) | E6: =IF('Registrar bienes de inversión'!E6="","",'Registrar bienes de inversión'!E6) | F6: =IF('Registrar bienes de inversión'!F6="","",VLOOKUP(CONCATENATE("TIPO BIEN",'Registrar bienes de inversión'!F6),'CODIGO-LITERAL'!$C:$D,2,FALSE)) | G6: =IF('Registrar bienes de inversión'!G6="","",'Registrar bienes de inversión'!G6) | H6: =IF('Registrar bienes de inversión'!H6="","",'Registrar bienes de inversión'!H6) | I6: =IF('Registrar bienes de inversión'!I6="","",'Registrar bienes de inversión'!I6) | J6: =IF('Registrar bienes de inversión'!J6="","",'Registrar bienes de inversión'!J6) | K6: =IF('Registrar bienes de inversión'!K6="","",'Registrar bienes de inversión'!K6) | L6: =IF('Registrar bienes de inversión'!L6="","",VLOOKUP(CONCATENATE("METODO AMORTIZACION",'Registrar bienes de inversión'!L6),'CODIGO-LITERAL'!$C:$D,2,FALSE)) | M6: =IF('Registrar bienes de inversión'!M6="","",'Registrar bienes de inversión'!M6) | N6: =IF('Registrar bienes de inversión'!N6="","",'Registrar bienes de inversión'!N6) | O6: =IF('Registrar bienes de inversión'!O6="","",'Registrar bienes de inversión'!O6) | P6: =IF('Registrar bienes de inversión'!P6="","",'Registrar bienes de inversión'!P6) | Q6: =IF('Registrar bienes de inversión'!Q6="","",'Registrar bienes de inversión'!Q6) | R6: =IF('Registrar bienes de inversión'!R6="","",'Registrar bienes de inversión'!R6) | S6: =IF('Registrar bienes de inversión'!S6="","",'Registrar bienes de inversión'!S6) | T6: =IF('Registrar bienes de inversión'!T6="","",'Registrar bienes de inversión'!T6) | ... V6: =IF('Registrar bienes de inversión'!V6="","",'Registrar bienes de inversión'!V6) | W6: =IF(OR('Registrar bienes de inversión'!W6="",LEFT('Registrar bienes de inversión'!W6,2)="01"),"",VLOOKUP(CONCATENATE("TIPO NIF",'Registrar bienes de inversión'!W6),'CODIGO-LITERAL'!$C:$D,2,FALSE)) | X6: =IF('Registrar bienes de inversión'!X6="","",'Registrar bienes de inversión'!X6) | Y6: =IF('Registrar bienes de inversión'!Y6="","",'Registrar bienes de inversión'!Y6) | Z6: =IF('Registrar bienes de inversión'!Z6="","",'Registrar bienes de inversión'!Z6) | AA6: =IF('Registrar bienes de inversión'!AA6="","",ROUND('Registrar bienes de inversión'!AA6,2)) | AB6: =IF('Registrar bienes de inversión'!AB6="","",'Registrar bienes de inversión'!AB6) | AC6: =IF('Registrar bienes de inversión'!AC6="","",ROUND('Registrar bienes de inversión'!AC6,2)) | AD6: =IF('Registrar bienes de inversión'!AD6="","",ROUND('Registrar bienes de inversión'!AD6,2)) | AE6: =IF('Registrar bienes de inversión'!AE6="","",ROUND('Registrar bienes de inversión'!AE6,2)) | AF6: =IF('Registrar bienes de inversión'!AF6="","",ROUND('Registrar bienes de inversión'!AF6,2)) | AG6: =IF('Registrar bienes de inversión'!AG6="","",ROUND('Registrar bienes de inversión'!AG6,2)) | AH6: =IF('Registrar bienes de inversión'!AH6="","",'Registrar bienes de inversión'!AH6) | AI6: =IF('Registrar bienes de inversión'!AI6="","",VLOOKUP(CONCATENATE("CAUSA BAJA BIEN",'Registrar bienes de inversión'!AI6),'CODIGO-LITERAL'!$C:$D,2,FALSE)) | AJ6: =IF('Registrar bienes de inversión'!AJ6="","",'Registrar bienes de inversión'!AJ6) | AK6: =IF('Registrar bienes de inversión'!AK6="","",'Registrar bienes de inversión'!AK6) | AL6: =IF('Registrar bienes de inversión'!AL6="","",'Registrar bienes de inversión'!AL6) | AM6: =IF('Registrar bienes de inversión'!AM6="","",'Registrar bienes de inversión'!AM6) | AN6: =IF('Registrar bienes de inversión'!AN6="","",VLOOKUP(CONCATENATE("SITUACION",'Registrar bienes de inversión'!AN6),'CODIGO-LITERAL'!$C:$D,2,FALSE)) | AO6: =IF('Registrar bienes de inversión'!AO6="","",'Registrar bienes de inversión'!AO6) | AP6: =IF('Registrar bienes de inversión'!AP6="","",'Registrar bienes de inversión'!AP6)
A7: =IF('Registrar bienes de inversión'!A7="","",'Registrar bienes de inversión'!A7) | B7: =IF('Registrar bienes de inversión'!B7="","",'Registrar bienes de inversión'!B7) | C7: =IF('Registrar bienes de inversión'!C7="","",VLOOKUP(CONCATENATE("ACTIVIDAD",'Registrar bienes de inversión'!C7),'CODIGO-LITERAL'!$C:$D,2,FALSE)) | D7: =IF(OR(C7="C",C7="D"),"",IF(ISERROR(VLOOKUP(CONCATENATE(C7,'Registrar bienes de inversión'!D7),'CODIGO-LITERAL'!$C:$D,2,FALSE)),"",VLOOKUP(CONCATENATE(C7,'Registrar bienes de inversión'!D7),'CODIGO-LITERAL'!$C:$D,2,FALSE))) | E7: =IF('Registrar bienes de inversión'!E7="","",'Registrar bienes de inversión'!E7) | F7: =IF('Registrar bienes de inversión'!F7="","",VLOOKUP(CONCATENATE("TIPO BIEN",'Registrar bienes de inversión'!F7),'CODIGO-LITERAL'!$C:$D,2,FALSE)) | G7: =IF('Registrar bienes de inversión'!G7="","",'Registrar bienes de inversión'!G7) | H7: =IF('Registrar bienes de inversión'!H7="","",'Registrar bienes de inversión'!H7) | I7: =IF('Registrar bienes de inversión'!I7="","",'Registrar bienes de inversión'!I7) | J7: =IF('Registrar bienes de inversión'!J7="","",'Registrar bienes de inversión'!J7) | K7: =IF('Registrar bienes de inversión'!K7="","",'Registrar bienes de inversión'!K7) | L7: =IF('Registrar bienes de inversión'!L7="","",VLOOKUP(CONCATENATE("METODO AMORTIZACION",'Registrar bienes de inversión'!L7),'CODIGO-LITERAL'!$C:$D,2,FALSE)) | M7: =IF('Registrar bienes de inversión'!M7="","",'Registrar bienes de inversión'!M7) | N7: =IF('Registrar bienes de inversión'!N7="","",'Registrar bienes de inversión'!N7) | O7: =IF('Registrar bienes de inversión'!O7="","",'Registrar bienes de inversión'!O7) | P7: =IF('Registrar bienes de inversión'!P7="","",'Registrar bienes de inversión'!P7) | Q7: =IF('Registrar bienes de inversión'!Q7="","",'Registrar bienes de inversión'!Q7) | R7: =IF('Registrar bienes de inversión'!R7="","",'Registrar bienes de inversión'!R7) | S7: =IF('Registrar bienes de inversión'!S7="","",'Registrar bienes de inversión'!S7) | T7: =IF('Registrar bienes de inversión'!T7="","",'Registrar bienes de inversión'!T7) | ... V7: =IF('Registrar bienes de inversión'!V7="","",'Registrar bienes de inversión'!V7) | W7: =IF(OR('Registrar bienes de inversión'!W7="",LEFT('Registrar bienes de inversión'!W7,2)="01"),"",VLOOKUP(CONCATENATE("TIPO NIF",'Registrar bienes de inversión'!W7),'CODIGO-LITERAL'!$C:$D,2,FALSE)) | X7: =IF('Registrar bienes de inversión'!X7="","",'Registrar bienes de inversión'!X7) | Y7: =IF('Registrar bienes de inversión'!Y7="","",'Registrar bienes de inversión'!Y7) | Z7: =IF('Registrar bienes de inversión'!Z7="","",'Registrar bienes de inversión'!Z7) | AA7: =IF('Registrar bienes de inversión'!AA7="","",ROUND('Registrar bienes de inversión'!AA7,2)) | AB7: =IF('Registrar bienes de inversión'!AB7="","",'Registrar bienes de inversión'!AB7) | AC7: =IF('Registrar bienes de inversión'!AC7="","",ROUND('Registrar bienes de inversión'!AC7,2)) | AD7: =IF('Registrar bienes de inversión'!AD7="","",ROUND('Registrar bienes de inversión'!AD7,2)) | AE7: =IF('Registrar bienes de inversión'!AE7="","",ROUND('Registrar bienes de inversión'!AE7,2)) | AF7: =IF('Registrar bienes de inversión'!AF7="","",ROUND('Registrar bienes de inversión'!AF7,2)) | AG7: =IF('Registrar bienes de inversión'!AG7="","",ROUND('Registrar bienes de inversión'!AG7,2)) | AH7: =IF('Registrar bienes de inversión'!AH7="","",'Registrar bienes de inversión'!AH7) | AI7: =IF('Registrar bienes de inversión'!AI7="","",VLOOKUP(CONCATENATE("CAUSA BAJA BIEN",'Registrar bienes de inversión'!AI7),'CODIGO-LITERAL'!$C:$D,2,FALSE)) | AJ7: =IF('Registrar bienes de inversión'!AJ7="","",'Registrar bienes de inversión'!AJ7) | AK7: =IF('Registrar bienes de inversión'!AK7="","",'Registrar bienes de inversión'!AK7) | AL7: =IF('Registrar bienes de inversión'!AL7="","",'Registrar bienes de inversión'!AL7) | AM7: =IF('Registrar bienes de inversión'!AM7="","",'Registrar bienes de inversión'!AM7) | AN7: =IF('Registrar bienes de inversión'!AN7="","",VLOOKUP(CONCATENATE("SITUACION",'Registrar bienes de inversión'!AN7),'CODIGO-LITERAL'!$C:$D,2,FALSE)) | AO7: =IF('Registrar bienes de inversión'!AO7="","",'Registrar bienes de inversión'!AO7) | AP7: =IF('Registrar bienes de inversión'!AP7="","",'Registrar bienes de inversión'!AP7)
A8: =IF('Registrar bienes de inversión'!A8="","",'Registrar bienes de inversión'!A8) | B8: =IF('Registrar bienes de inversión'!B8="","",'Registrar bienes de inversión'!B8) | C8: =IF('Registrar bienes de inversión'!C8="","",VLOOKUP(CONCATENATE("ACTIVIDAD",'Registrar bienes de inversión'!C8),'CODIGO-LITERAL'!$C:$D,2,FALSE)) | D8: =IF(OR(C8="C",C8="D"),"",IF(ISERROR(VLOOKUP(CONCATENATE(C8,'Registrar bienes de inversión'!D8),'CODIGO-LITERAL'!$C:$D,2,FALSE)),"",VLOOKUP(CONCATENATE(C8,'Registrar bienes de inversión'!D8),'CODIGO-LITERAL'!$C:$D,2,FALSE))) | E8: =IF('Registrar bienes de inversión'!E8="","",'Registrar bienes de inversión'!E8) | F8: =IF('Registrar bienes de inversión'!F8="","",VLOOKUP(CONCATENATE("TIPO BIEN",'Registrar bienes de inversión'!F8),'CODIGO-LITERAL'!$C:$D,2,FALSE)) | G8: =IF('Registrar bienes de inversión'!G8="","",'Registrar bienes de inversión'!G8) | H8: =IF('Registrar bienes de inversión'!H8="","",'Registrar bienes de inversión'!H8) | I8: =IF('Registrar bienes de inversión'!I8="","",'Registrar bienes de inversión'!I8) | J8: =IF('Registrar bienes de inversión'!J8="","",'Registrar bienes de inversión'!J8) | K8: =IF('Registrar bienes de inversión'!K8="","",'Registrar bienes de inversión'!K8) | L8: =IF('Registrar bienes de inversión'!L8="","",VLOOKUP(CONCATENATE("METODO AMORTIZACION",'Registrar bienes de inversión'!L8),'CODIGO-LITERAL'!$C:$D,2,FALSE)) | M8: =IF('Registrar bienes de inversión'!M8="","",'Registrar bienes de inversión'!M8) | N8: =IF('Registrar bienes de inversión'!N8="","",'Registrar bienes de inversión'!N8) | O8: =IF('Registrar bienes de inversión'!O8="","",'Registrar bienes de inversión'!O8) | P8: =IF('Registrar bienes de inversión'!P8="","",'Registrar bienes de inversión'!P8) | Q8: =IF('Registrar bienes de inversión'!Q8="","",'Registrar bienes de inversión'!Q8) | R8: =IF('Registrar bienes de inversión'!R8="","",'Registrar bienes de inversión'!R8) | S8: =IF('Registrar bienes de inversión'!S8="","",'Registrar bienes de inversión'!S8) | T8: =IF('Registrar bienes de inversión'!T8="","",'Registrar bienes de inversión'!T8) | ... V8: =IF('Registrar bienes de inversión'!V8="","",'Registrar bienes de inversión'!V8) | W8: =IF(OR('Registrar bienes de inversión'!W8="",LEFT('Registrar bienes de inversión'!W8,2)="01"),"",VLOOKUP(CONCATENATE("TIPO NIF",'Registrar bienes de inversión'!W8),'CODIGO-LITERAL'!$C:$D,2,FALSE)) | X8: =IF('Registrar bienes de inversión'!X8="","",'Registrar bienes de inversión'!X8) | Y8: =IF('Registrar bienes de inversión'!Y8="","",'Registrar bienes de inversión'!Y8) | Z8: =IF('Registrar bienes de inversión'!Z8="","",'Registrar bienes de inversión'!Z8) | AA8: =IF('Registrar bienes de inversión'!AA8="","",ROUND('Registrar bienes de inversión'!AA8,2)) | AB8: =IF('Registrar bienes de inversión'!AB8="","",'Registrar bienes de inversión'!AB8) | AC8: =IF('Registrar bienes de inversión'!AC8="","",ROUND('Registrar bienes de inversión'!AC8,2)) | AD8: =IF('Registrar bienes de inversión'!AD8="","",ROUND('Registrar bienes de inversión'!AD8,2)) | AE8: =IF('Registrar bienes de inversión'!AE8="","",ROUND('Registrar bienes de inversión'!AE8,2)) | AF8: =IF('Registrar bienes de inversión'!AF8="","",ROUND('Registrar bienes de inversión'!AF8,2)) | AG8: =IF('Registrar bienes de inversión'!AG8="","",ROUND('Registrar bienes de inversión'!AG8,2)) | AH8: =IF('Registrar bienes de inversión'!AH8="","",'Registrar bienes de inversión'!AH8) | AI8: =IF('Registrar bienes de inversión'!AI8="","",VLOOKUP(CONCATENATE("CAUSA BAJA BIEN",'Registrar bienes de inversión'!AI8),'CODIGO-LITERAL'!$C:$D,2,FALSE)) | AJ8: =IF('Registrar bienes de inversión'!AJ8="","",'Registrar bienes de inversión'!AJ8) | AK8: =IF('Registrar bienes de inversión'!AK8="","",'Registrar bienes de inversión'!AK8) | AL8: =IF('Registrar bienes de inversión'!AL8="","",'Registrar bienes de inversión'!AL8) | AM8: =IF('Registrar bienes de inversión'!AM8="","",'Registrar bienes de inversión'!AM8) | AN8: =IF('Registrar bienes de inversión'!AN8="","",VLOOKUP(CONCATENATE("SITUACION",'Registrar bienes de inversión'!AN8),'CODIGO-LITERAL'!$C:$D,2,FALSE)) | AO8: =IF('Registrar bienes de inversión'!AO8="","",'Registrar bienes de inversión'!AO8) | AP8: =IF('Registrar bienes de inversión'!AP8="","",'Registrar bienes de inversión'!AP8)
A9: =IF('Registrar bienes de inversión'!A9="","",'Registrar bienes de inversión'!A9) | B9: =IF('Registrar bienes de inversión'!B9="","",'Registrar bienes de inversión'!B9) | C9: =IF('Registrar bienes de inversión'!C9="","",VLOOKUP(CONCATENATE("ACTIVIDAD",'Registrar bienes de inversión'!C9),'CODIGO-LITERAL'!$C:$D,2,FALSE)) | D9: =IF(OR(C9="C",C9="D"),"",IF(ISERROR(VLOOKUP(CONCATENATE(C9,'Registrar bienes de inversión'!D9),'CODIGO-LITERAL'!$C:$D,2,FALSE)),"",VLOOKUP(CONCATENATE(C9,'Registrar bienes de inversión'!D9),'CODIGO-LITERAL'!$C:$D,2,FALSE))) | E9: =IF('Registrar bienes de inversión'!E9="","",'Registrar bienes de inversión'!E9) | F9: =IF('Registrar bienes de inversión'!F9="","",VLOOKUP(CONCATENATE("TIPO BIEN",'Registrar bienes de inversión'!F9),'CODIGO-LITERAL'!$C:$D,2,FALSE)) | G9: =IF('Registrar bienes de inversión'!G9="","",'Registrar bienes de inversión'!G9) | H9: =IF('Registrar bienes de inversión'!H9="","",'Registrar bienes de inversión'!H9) | I9: =IF('Registrar bienes de inversión'!I9="","",'Registrar bienes de inversión'!I9) | J9: =IF('Registrar bienes de inversión'!J9="","",'Registrar bienes de inversión'!J9) | K9: =IF('Registrar bienes de inversión'!K9="","",'Registrar bienes de inversión'!K9) | L9: =IF('Registrar bienes de inversión'!L9="","",VLOOKUP(CONCATENATE("METODO AMORTIZACION",'Registrar bienes de inversión'!L9),'CODIGO-LITERAL'!$C:$D,2,FALSE)) | M9: =IF('Registrar bienes de inversión'!M9="","",'Registrar bienes de inversión'!M9) | N9: =IF('Registrar bienes de inversión'!N9="","",'Registrar bienes de inversión'!N9) | O9: =IF('Registrar bienes de inversión'!O9="","",'Registrar bienes de inversión'!O9) | P9: =IF('Registrar bienes de inversión'!P9="","",'Registrar bienes de inversión'!P9) | Q9: =IF('Registrar bienes de inversión'!Q9="","",'Registrar bienes de inversión'!Q9) | R9: =IF('Registrar bienes de inversión'!R9="","",'Registrar bienes de inversión'!R9) | S9: =IF('Registrar bienes de inversión'!S9="","",'Registrar bienes de inversión'!S9) | T9: =IF('Registrar bienes de inversión'!T9="","",'Registrar bienes de inversión'!T9) | ... V9: =IF('Registrar bienes de inversión'!V9="","",'Registrar bienes de inversión'!V9) | W9: =IF(OR('Registrar bienes de inversión'!W9="",LEFT('Registrar bienes de inversión'!W9,2)="01"),"",VLOOKUP(CONCATENATE("TIPO NIF",'Registrar bienes de inversión'!W9),'CODIGO-LITERAL'!$C:$D,2,FALSE)) | X9: =IF('Registrar bienes de inversión'!X9="","",'Registrar bienes de inversión'!X9) | Y9: =IF('Registrar bienes de inversión'!Y9="","",'Registrar bienes de inversión'!Y9) | Z9: =IF('Registrar bienes de inversión'!Z9="","",'Registrar bienes de inversión'!Z9) | AA9: =IF('Registrar bienes de inversión'!AA9="","",ROUND('Registrar bienes de inversión'!AA9,2)) | AB9: =IF('Registrar bienes de inversión'!AB9="","",'Registrar bienes de inversión'!AB9) | AC9: =IF('Registrar bienes de inversión'!AC9="","",ROUND('Registrar bienes de inversión'!AC9,2)) | AD9: =IF('Registrar bienes de inversión'!AD9="","",ROUND('Registrar bienes de inversión'!AD9,2)) | AE9: =IF('Registrar bienes de inversión'!AE9="","",ROUND('Registrar bienes de inversión'!AE9,2)) | AF9: =IF('Registrar bienes de inversión'!AF9="","",ROUND('Registrar bienes de inversión'!AF9,2)) | AG9: =IF('Registrar bienes de inversión'!AG9="","",ROUND('Registrar bienes de inversión'!AG9,2)) | AH9: =IF('Registrar bienes de inversión'!AH9="","",'Registrar bienes de inversión'!AH9) | AI9: =IF('Registrar bienes de inversión'!AI9="","",VLOOKUP(CONCATENATE("CAUSA BAJA BIEN",'Registrar bienes de inversión'!AI9),'CODIGO-LITERAL'!$C:$D,2,FALSE)) | AJ9: =IF('Registrar bienes de inversión'!AJ9="","",'Registrar bienes de inversión'!AJ9) | AK9: =IF('Registrar bienes de inversión'!AK9="","",'Registrar bienes de inversión'!AK9) | AL9: =IF('Registrar bienes de inversión'!AL9="","",'Registrar bienes de inversión'!AL9) | AM9: =IF('Registrar bienes de inversión'!AM9="","",'Registrar bienes de inversión'!AM9) | AN9: =IF('Registrar bienes de inversión'!AN9="","",VLOOKUP(CONCATENATE("SITUACION",'Registrar bienes de inversión'!AN9),'CODIGO-LITERAL'!$C:$D,2,FALSE)) | AO9: =IF('Registrar bienes de inversión'!AO9="","",'Registrar bienes de inversión'!AO9) | AP9: =IF('Registrar bienes de inversión'!AP9="","",'Registrar bienes de inversión'!AP9)
A10: =IF('Registrar bienes de inversión'!A10="","",'Registrar bienes de inversión'!A10) | B10: =IF('Registrar bienes de inversión'!B10="","",'Registrar bienes de inversión'!B10) | C10: =IF('Registrar bienes de inversión'!C10="","",VLOOKUP(CONCATENATE("ACTIVIDAD",'Registrar bienes de inversión'!C10),'CODIGO-LITERAL'!$C:$D,2,FALSE)) | D10: =IF(OR(C10="C",C10="D"),"",IF(ISERROR(VLOOKUP(CONCATENATE(C10,'Registrar bienes de inversión'!D10),'CODIGO-LITERAL'!$C:$D,2,FALSE)),"",VLOOKUP(CONCATENATE(C10,'Registrar bienes de inversión'!D10),'CODIGO-LITERAL'!$C:$D,2,FALSE))) | E10: =IF('Registrar bienes de inversión'!E10="","",'Registrar bienes de inversión'!E10) | F10: =IF('Registrar bienes de inversión'!F10="","",VLOOKUP(CONCATENATE("TIPO BIEN",'Registrar bienes de inversión'!F10),'CODIGO-LITERAL'!$C:$D,2,FALSE)) | G10: =IF('Registrar bienes de inversión'!G10="","",'Registrar bienes de inversión'!G10) | H10: =IF('Registrar bienes de inversión'!H10="","",'Registrar bienes de inversión'!H10) | I10: =IF('Registrar bienes de inversión'!I10="","",'Registrar bienes de inversión'!I10) | J10: =IF('Registrar bienes de inversión'!J10="","",'Registrar bienes de inversión'!J10) | K10: =IF('Registrar bienes de inversión'!K10="","",'Registrar bienes de inversión'!K10) | L10: =IF('Registrar bienes de inversión'!L10="","",VLOOKUP(CONCATENATE("METODO AMORTIZACION",'Registrar bienes de inversión'!L10),'CODIGO-LITERAL'!$C:$D,2,FALSE)) | M10: =IF('Registrar bienes de inversión'!M10="","",'Registrar bienes de inversión'!M10) | N10: =IF('Registrar bienes de inversión'!N10="","",'Registrar bienes de inversión'!N10) | O10: =IF('Registrar bienes de inversión'!O10="","",'Registrar bienes de inversión'!O10) | P10: =IF('Registrar bienes de inversión'!P10="","",'Registrar bienes de inversión'!P10) | Q10: =IF('Registrar bienes de inversión'!Q10="","",'Registrar bienes de inversión'!Q10) | R10: =IF('Registrar bienes de inversión'!R10="","",'Registrar bienes de inversión'!R10) | S10: =IF('Registrar bienes de inversión'!S10="","",'Registrar bienes de inversión'!S10) | T10: =IF('Registrar bienes de inversión'!T10="","",'Registrar bienes de inversión'!T10) | ... V10: =IF('Registrar bienes de inversión'!V10="","",'Registrar bienes de inversión'!V10) | W10: =IF(OR('Registrar bienes de inversión'!W10="",LEFT('Registrar bienes de inversión'!W10,2)="01"),"",VLOOKUP(CONCATENATE("TIPO NIF",'Registrar bienes de inversión'!W10),'CODIGO-LITERAL'!$C:$D,2,FALSE)) | X10: =IF('Registrar bienes de inversión'!X10="","",'Registrar bienes de inversión'!X10) | Y10: =IF('Registrar bienes de inversión'!Y10="","",'Registrar bienes de inversión'!Y10) | Z10: =IF('Registrar bienes de inversión'!Z10="","",'Registrar bienes de inversión'!Z10) | AA10: =IF('Registrar bienes de inversión'!AA10="","",ROUND('Registrar bienes de inversión'!AA10,2)) | AB10: =IF('Registrar bienes de inversión'!AB10="","",'Registrar bienes de inversión'!AB10) | AC10: =IF('Registrar bienes de inversión'!AC10="","",ROUND('Registrar bienes de inversión'!AC10,2)) | AD10: =IF('Registrar bienes de inversión'!AD10="","",ROUND('Registrar bienes de inversión'!AD10,2)) | AE10: =IF('Registrar bienes de inversión'!AE10="","",ROUND('Registrar bienes de inversión'!AE10,2)) | AF10: =IF('Registrar bienes de inversión'!AF10="","",ROUND('Registrar bienes de inversión'!AF10,2)) | AG10: =IF('Registrar bienes de inversión'!AG10="","",ROUND('Registrar bienes de inversión'!AG10,2)) | AH10: =IF('Registrar bienes de inversión'!AH10="","",'Registrar bienes de inversión'!AH10) | AI10: =IF('Registrar bienes de inversión'!AI10="","",VLOOKUP(CONCATENATE("CAUSA BAJA BIEN",'Registrar bienes de inversión'!AI10),'CODIGO-LITERAL'!$C:$D,2,FALSE)) | AJ10: =IF('Registrar bienes de inversión'!AJ10="","",'Registrar bienes de inversión'!AJ10) | AK10: =IF('Registrar bienes de inversión'!AK10="","",'Registrar bienes de inversión'!AK10) | AL10: =IF('Registrar bienes de inversión'!AL10="","",'Registrar bienes de inversión'!AL10) | AM10: =IF('Registrar bienes de inversión'!AM10="","",'Registrar bienes de inversión'!AM10) | AN10: =IF('Registrar bienes de inversión'!AN10="","",VLOOKUP(CONCATENATE("SITUACION",'Registrar bienes de inversión'!AN10),'CODIGO-LITERAL'!$C:$D,2,FALSE)) | AO10: =IF('Registrar bienes de inversión'!AO10="","",'Registrar bienes de inversión'!AO10) | AP10: =IF('Registrar bienes de inversión'!AP10="","",'Registrar bienes de inversión'!AP10)
A11: =IF('Registrar bienes de inversión'!A11="","",'Registrar bienes de inversión'!A11) | B11: =IF('Registrar bienes de inversión'!B11="","",'Registrar bienes de inversión'!B11) | C11: =IF('Registrar bienes de inversión'!C11="","",VLOOKUP(CONCATENATE("ACTIVIDAD",'Registrar bienes de inversión'!C11),'CODIGO-LITERAL'!$C:$D,2,FALSE)) | D11: =IF(OR(C11="C",C11="D"),"",IF(ISERROR(VLOOKUP(CONCATENATE(C11,'Registrar bienes de inversión'!D11),'CODIGO-LITERAL'!$C:$D,2,FALSE)),"",VLOOKUP(CONCATENATE(C11,'Registrar bienes de inversión'!D11),'CODIGO-LITERAL'!$C:$D,2,FALSE))) | E11: =IF('Registrar bienes de inversión'!E11="","",'Registrar bienes de inversión'!E11) | F11: =IF('Registrar bienes de inversión'!F11="","",VLOOKUP(CONCATENATE("TIPO BIEN",'Registrar bienes de inversión'!F11),'CODIGO-LITERAL'!$C:$D,2,FALSE)) | G11: =IF('Registrar bienes de inversión'!G11="","",'Registrar bienes de inversión'!G11) | H11: =IF('Registrar bienes de inversión'!H11="","",'Registrar bienes de inversión'!H11) | I11: =IF('Registrar bienes de inversión'!I11="","",'Registrar bienes de inversión'!I11) | J11: =IF('Registrar bienes de inversión'!J11="","",'Registrar bienes de inversión'!J11) | K11: =IF('Registrar bienes de inversión'!K11="","",'Registrar bienes de inversión'!K11) | L11: =IF('Registrar bienes de inversión'!L11="","",VLOOKUP(CONCATENATE("METODO AMORTIZACION",'Registrar bienes de inversión'!L11),'CODIGO-LITERAL'!$C:$D,2,FALSE)) | M11: =IF('Registrar bienes de inversión'!M11="","",'Registrar bienes de inversión'!M11) | N11: =IF('Registrar bienes de inversión'!N11="","",'Registrar bienes de inversión'!N11) | O11: =IF('Registrar bienes de inversión'!O11="","",'Registrar bienes de inversión'!O11) | P11: =IF('Registrar bienes de inversión'!P11="","",'Registrar bienes de inversión'!P11) | Q11: =IF('Registrar bienes de inversión'!Q11="","",'Registrar bienes de inversión'!Q11) | R11: =IF('Registrar bienes de inversión'!R11="","",'Registrar bienes de inversión'!R11) | S11: =IF('Registrar bienes de inversión'!S11="","",'Registrar bienes de inversión'!S11) | T11: =IF('Registrar bienes de inversión'!T11="","",'Registrar bienes de inversión'!T11) | ... V11: =IF('Registrar bienes de inversión'!V11="","",'Registrar bienes de inversión'!V11) | W11: =IF(OR('Registrar bienes de inversión'!W11="",LEFT('Registrar bienes de inversión'!W11,2)="01"),"",VLOOKUP(CONCATENATE("TIPO NIF",'Registrar bienes de inversión'!W11),'CODIGO-LITERAL'!$C:$D,2,FALSE)) | X11: =IF('Registrar bienes de inversión'!X11="","",'Registrar bienes de inversión'!X11) | Y11: =IF('Registrar bienes de inversión'!Y11="","",'Registrar bienes de inversión'!Y11) | Z11: =IF('Registrar bienes de inversión'!Z11="","",'Registrar bienes de inversión'!Z11) | AA11: =IF('Registrar bienes de inversión'!AA11="","",ROUND('Registrar bienes de inversión'!AA11,2)) | AB11: =IF('Registrar bienes de inversión'!AB11="","",'Registrar bienes de inversión'!AB11) | AC11: =IF('Registrar bienes de inversión'!AC11="","",ROUND('Registrar bienes de inversión'!AC11,2)) | AD11: =IF('Registrar bienes de inversión'!AD11="","",ROUND('Registrar bienes de inversión'!AD11,2)) | AE11: =IF('Registrar bienes de inversión'!AE11="","",ROUND('Registrar bienes de inversión'!AE11,2)) | AF11: =IF('Registrar bienes de inversión'!AF11="","",ROUND('Registrar bienes de inversión'!AF11,2)) | AG11: =IF('Registrar bienes de inversión'!AG11="","",ROUND('Registrar bienes de inversión'!AG11,2)) | AH11: =IF('Registrar bienes de inversión'!AH11="","",'Registrar bienes de inversión'!AH11) | AI11: =IF('Registrar bienes de inversión'!AI11="","",VLOOKUP(CONCATENATE("CAUSA BAJA BIEN",'Registrar bienes de inversión'!AI11),'CODIGO-LITERAL'!$C:$D,2,FALSE)) | AJ11: =IF('Registrar bienes de inversión'!AJ11="","",'Registrar bienes de inversión'!AJ11) | AK11: =IF('Registrar bienes de inversión'!AK11="","",'Registrar bienes de inversión'!AK11) | AL11: =IF('Registrar bienes de inversión'!AL11="","",'Registrar bienes de inversión'!AL11) | AM11: =IF('Registrar bienes de inversión'!AM11="","",'Registrar bienes de inversión'!AM11) | AN11: =IF('Registrar bienes de inversión'!AN11="","",VLOOKUP(CONCATENATE("SITUACION",'Registrar bienes de inversión'!AN11),'CODIGO-LITERAL'!$C:$D,2,FALSE)) | AO11: =IF('Registrar bienes de inversión'!AO11="","",'Registrar bienes de inversión'!AO11) | AP11: =IF('Registrar bienes de inversión'!AP11="","",'Registrar bienes de inversión'!AP11)
A12: =IF('Registrar bienes de inversión'!A12="","",'Registrar bienes de inversión'!A12) | B12: =IF('Registrar bienes de inversión'!B12="","",'Registrar bienes de inversión'!B12) | C12: =IF('Registrar bienes de inversión'!C12="","",VLOOKUP(CONCATENATE("ACTIVIDAD",'Registrar bienes de inversión'!C12),'CODIGO-LITERAL'!$C:$D,2,FALSE)) | D12: =IF(OR(C12="C",C12="D"),"",IF(ISERROR(VLOOKUP(CONCATENATE(C12,'Registrar bienes de inversión'!D12),'CODIGO-LITERAL'!$C:$D,2,FALSE)),"",VLOOKUP(CONCATENATE(C12,'Registrar bienes de inversión'!D12),'CODIGO-LITERAL'!$C:$D,2,FALSE))) | E12: =IF('Registrar bienes de inversión'!E12="","",'Registrar bienes de inversión'!E12) | F12: =IF('Registrar bienes de inversión'!F12="","",VLOOKUP(CONCATENATE("TIPO BIEN",'Registrar bienes de inversión'!F12),'CODIGO-LITERAL'!$C:$D,2,FALSE)) | G12: =IF('Registrar bienes de inversión'!G12="","",'Registrar bienes de inversión'!G12) | H12: =IF('Registrar bienes de inversión'!H12="","",'Registrar bienes de inversión'!H12) | I12: =IF('Registrar bienes de inversión'!I12="","",'Registrar bienes de inversión'!I12) | J12: =IF('Registrar bienes de inversión'!J12="","",'Registrar bienes de inversión'!J12) | K12: =IF('Registrar bienes de inversión'!K12="","",'Registrar bienes de inversión'!K12) | L12: =IF('Registrar bienes de inversión'!L12="","",VLOOKUP(CONCATENATE("METODO AMORTIZACION",'Registrar bienes de inversión'!L12),'CODIGO-LITERAL'!$C:$D,2,FALSE)) | M12: =IF('Registrar bienes de inversión'!M12="","",'Registrar bienes de inversión'!M12) | N12: =IF('Registrar bienes de inversión'!N12="","",'Registrar bienes de inversión'!N12) | O12: =IF('Registrar bienes de inversión'!O12="","",'Registrar bienes de inversión'!O12) | P12: =IF('Registrar bienes de inversión'!P12="","",'Registrar bienes de inversión'!P12) | Q12: =IF('Registrar bienes de inversión'!Q12="","",'Registrar bienes de inversión'!Q12) | R12: =IF('Registrar bienes de inversión'!R12="","",'Registrar bienes de inversión'!R12) | S12: =IF('Registrar bienes de inversión'!S12="","",'Registrar bienes de inversión'!S12) | T12: =IF('Registrar bienes de inversión'!T12="","",'Registrar bienes de inversión'!T12) | ... V12: =IF('Registrar bienes de inversión'!V12="","",'Registrar bienes de inversión'!V12) | W12: =IF(OR('Registrar bienes de inversión'!W12="",LEFT('Registrar bienes de inversión'!W12,2)="01"),"",VLOOKUP(CONCATENATE("TIPO NIF",'Registrar bienes de inversión'!W12),'CODIGO-LITERAL'!$C:$D,2,FALSE)) | X12: =IF('Registrar bienes de inversión'!X12="","",'Registrar bienes de inversión'!X12) | Y12: =IF('Registrar bienes de inversión'!Y12="","",'Registrar bienes de inversión'!Y12) | Z12: =IF('Registrar bienes de inversión'!Z12="","",'Registrar bienes de inversión'!Z12) | AA12: =IF('Registrar bienes de inversión'!AA12="","",ROUND('Registrar bienes de inversión'!AA12,2)) | AB12: =IF('Registrar bienes de inversión'!AB12="","",'Registrar bienes de inversión'!AB12) | AC12: =IF('Registrar bienes de inversión'!AC12="","",ROUND('Registrar bienes de inversión'!AC12,2)) | AD12: =IF('Registrar bienes de inversión'!AD12="","",ROUND('Registrar bienes de inversión'!AD12,2)) | AE12: =IF('Registrar bienes de inversión'!AE12="","",ROUND('Registrar bienes de inversión'!AE12,2)) | AF12: =IF('Registrar bienes de inversión'!AF12="","",ROUND('Registrar bienes de inversión'!AF12,2)) | AG12: =IF('Registrar bienes de inversión'!AG12="","",ROUND('Registrar bienes de inversión'!AG12,2)) | AH12: =IF('Registrar bienes de inversión'!AH12="","",'Registrar bienes de inversión'!AH12) | AI12: =IF('Registrar bienes de inversión'!AI12="","",VLOOKUP(CONCATENATE("CAUSA BAJA BIEN",'Registrar bienes de inversión'!AI12),'CODIGO-LITERAL'!$C:$D,2,FALSE)) | AJ12: =IF('Registrar bienes de inversión'!AJ12="","",'Registrar bienes de inversión'!AJ12) | AK12: =IF('Registrar bienes de inversión'!AK12="","",'Registrar bienes de inversión'!AK12) | AL12: =IF('Registrar bienes de inversión'!AL12="","",'Registrar bienes de inversión'!AL12) | AM12: =IF('Registrar bienes de inversión'!AM12="","",'Registrar bienes de inversión'!AM12) | AN12: =IF('Registrar bienes de inversión'!AN12="","",VLOOKUP(CONCATENATE("SITUACION",'Registrar bienes de inversión'!AN12),'CODIGO-LITERAL'!$C:$D,2,FALSE)) | AO12: =IF('Registrar bienes de inversión'!AO12="","",'Registrar bienes de inversión'!AO12) | AP12: =IF('Registrar bienes de inversión'!AP12="","",'Registrar bienes de inversión'!AP12)
A13: =IF('Registrar bienes de inversión'!A13="","",'Registrar bienes de inversión'!A13) | B13: =IF('Registrar bienes de inversión'!B13="","",'Registrar bienes de inversión'!B13) | C13: =IF('Registrar bienes de inversión'!C13="","",VLOOKUP(CONCATENATE("ACTIVIDAD",'Registrar bienes de inversión'!C13),'CODIGO-LITERAL'!$C:$D,2,FALSE)) | D13: =IF(OR(C13="C",C13="D"),"",IF(ISERROR(VLOOKUP(CONCATENATE(C13,'Registrar bienes de inversión'!D13),'CODIGO-LITERAL'!$C:$D,2,FALSE)),"",VLOOKUP(CONCATENATE(C13,'Registrar bienes de inversión'!D13),'CODIGO-LITERAL'!$C:$D,2,FALSE))) | E13: =IF('Registrar bienes de inversión'!E13="","",'Registrar bienes de inversión'!E13) | F13: =IF('Registrar bienes de inversión'!F13="","",VLOOKUP(CONCATENATE("TIPO BIEN",'Registrar bienes de inversión'!F13),'CODIGO-LITERAL'!$C:$D,2,FALSE)) | G13: =IF('Registrar bienes de inversión'!G13="","",'Registrar bienes de inversión'!G13) | H13: =IF('Registrar bienes de inversión'!H13="","",'Registrar bienes de inversión'!H13) | I13: =IF('Registrar bienes de inversión'!I13="","",'Registrar bienes de inversión'!I13) | J13: =IF('Registrar bienes de inversión'!J13="","",'Registrar bienes de inversión'!J13) | K13: =IF('Registrar bienes de inversión'!K13="","",'Registrar bienes de inversión'!K13) | L13: =IF('Registrar bienes de inversión'!L13="","",VLOOKUP(CONCATENATE("METODO AMORTIZACION",'Registrar bienes de inversión'!L13),'CODIGO-LITERAL'!$C:$D,2,FALSE)) | M13: =IF('Registrar bienes de inversión'!M13="","",'Registrar bienes de inversión'!M13) | N13: =IF('Registrar bienes de inversión'!N13="","",'Registrar bienes de inversión'!N13) | O13: =IF('Registrar bienes de inversión'!O13="","",'Registrar bienes de inversión'!O13) | P13: =IF('Registrar bienes de inversión'!P13="","",'Registrar bienes de inversión'!P13) | Q13: =IF('Registrar bienes de inversión'!Q13="","",'Registrar bienes de inversión'!Q13) | R13: =IF('Registrar bienes de inversión'!R13="","",'Registrar bienes de inversión'!R13) | S13: =IF('Registrar bienes de inversión'!S13="","",'Registrar bienes de inversión'!S13) | T13: =IF('Registrar bienes de inversión'!T13="","",'Registrar bienes de inversión'!T13) | ... V13: =IF('Registrar bienes de inversión'!V13="","",'Registrar bienes de inversión'!V13) | W13: =IF(OR('Registrar bienes de inversión'!W13="",LEFT('Registrar bienes de inversión'!W13,2)="01"),"",VLOOKUP(CONCATENATE("TIPO NIF",'Registrar bienes de inversión'!W13),'CODIGO-LITERAL'!$C:$D,2,FALSE)) | X13: =IF('Registrar bienes de inversión'!X13="","",'Registrar bienes de inversión'!X13) | Y13: =IF('Registrar bienes de inversión'!Y13="","",'Registrar bienes de inversión'!Y13) | Z13: =IF('Registrar bienes de inversión'!Z13="","",'Registrar bienes de inversión'!Z13) | AA13: =IF('Registrar bienes de inversión'!AA13="","",ROUND('Registrar bienes de inversión'!AA13,2)) | AB13: =IF('Registrar bienes de inversión'!AB13="","",'Registrar bienes de inversión'!AB13) | AC13: =IF('Registrar bienes de inversión'!AC13="","",ROUND('Registrar bienes de inversión'!AC13,2)) | AD13: =IF('Registrar bienes de inversión'!AD13="","",ROUND('Registrar bienes de inversión'!AD13,2)) | AE13: =IF('Registrar bienes de inversión'!AE13="","",ROUND('Registrar bienes de inversión'!AE13,2)) | AF13: =IF('Registrar bienes de inversión'!AF13="","",ROUND('Registrar bienes de inversión'!AF13,2)) | AG13: =IF('Registrar bienes de inversión'!AG13="","",ROUND('Registrar bienes de inversión'!AG13,2)) | AH13: =IF('Registrar bienes de inversión'!AH13="","",'Registrar bienes de inversión'!AH13) | AI13: =IF('Registrar bienes de inversión'!AI13="","",VLOOKUP(CONCATENATE("CAUSA BAJA BIEN",'Registrar bienes de inversión'!AI13),'CODIGO-LITERAL'!$C:$D,2,FALSE)) | AJ13: =IF('Registrar bienes de inversión'!AJ13="","",'Registrar bienes de inversión'!AJ13) | AK13: =IF('Registrar bienes de inversión'!AK13="","",'Registrar bienes de inversión'!AK13) | AL13: =IF('Registrar bienes de inversión'!AL13="","",'Registrar bienes de inversión'!AL13) | AM13: =IF('Registrar bienes de inversión'!AM13="","",'Registrar bienes de inversión'!AM13) | AN13: =IF('Registrar bienes de inversión'!AN13="","",VLOOKUP(CONCATENATE("SITUACION",'Registrar bienes de inversión'!AN13),'CODIGO-LITERAL'!$C:$D,2,FALSE)) | AO13: =IF('Registrar bienes de inversión'!AO13="","",'Registrar bienes de inversión'!AO13) | AP13: =IF('Registrar bienes de inversión'!AP13="","",'Registrar bienes de inversión'!AP13)
A14: =IF('Registrar bienes de inversión'!A14="","",'Registrar bienes de inversión'!A14) | B14: =IF('Registrar bienes de inversión'!B14="","",'Registrar bienes de inversión'!B14) | C14: =IF('Registrar bienes de inversión'!C14="","",VLOOKUP(CONCATENATE("ACTIVIDAD",'Registrar bienes de inversión'!C14),'CODIGO-LITERAL'!$C:$D,2,FALSE)) | D14: =IF(OR(C14="C",C14="D"),"",IF(ISERROR(VLOOKUP(CONCATENATE(C14,'Registrar bienes de inversión'!D14),'CODIGO-LITERAL'!$C:$D,2,FALSE)),"",VLOOKUP(CONCATENATE(C14,'Registrar bienes de inversión'!D14),'CODIGO-LITERAL'!$C:$D,2,FALSE))) | E14: =IF('Registrar bienes de inversión'!E14="","",'Registrar bienes de inversión'!E14) | F14: =IF('Registrar bienes de inversión'!F14="","",VLOOKUP(CONCATENATE("TIPO BIEN",'Registrar bienes de inversión'!F14),'CODIGO-LITERAL'!$C:$D,2,FALSE)) | G14: =IF('Registrar bienes de inversión'!G14="","",'Registrar bienes de inversión'!G14) | H14: =IF('Registrar bienes de inversión'!H14="","",'Registrar bienes de inversión'!H14) | I14: =IF('Registrar bienes de inversión'!I14="","",'Registrar bienes de inversión'!I14) | J14: =IF('Registrar bienes de inversión'!J14="","",'Registrar bienes de inversión'!J14) | K14: =IF('Registrar bienes de inversión'!K14="","",'Registrar bienes de inversión'!K14) | L14: =IF('Registrar bienes de inversión'!L14="","",VLOOKUP(CONCATENATE("METODO AMORTIZACION",'Registrar bienes de inversión'!L14),'CODIGO-LITERAL'!$C:$D,2,FALSE)) | M14: =IF('Registrar bienes de inversión'!M14="","",'Registrar bienes de inversión'!M14) | N14: =IF('Registrar bienes de inversión'!N14="","",'Registrar bienes de inversión'!N14) | O14: =IF('Registrar bienes de inversión'!O14="","",'Registrar bienes de inversión'!O14) | P14: =IF('Registrar bienes de inversión'!P14="","",'Registrar bienes de inversión'!P14) | Q14: =IF('Registrar bienes de inversión'!Q14="","",'Registrar bienes de inversión'!Q14) | R14: =IF('Registrar bienes de inversión'!R14="","",'Registrar bienes de inversión'!R14) | S14: =IF('Registrar bienes de inversión'!S14="","",'Registrar bienes de inversión'!S14) | T14: =IF('Registrar bienes de inversión'!T14="","",'Registrar bienes de inversión'!T14) | ... V14: =IF('Registrar bienes de inversión'!V14="","",'Registrar bienes de inversión'!V14) | W14: =IF(OR('Registrar bienes de inversión'!W14="",LEFT('Registrar bienes de inversión'!W14,2)="01"),"",VLOOKUP(CONCATENATE("TIPO NIF",'Registrar bienes de inversión'!W14),'CODIGO-LITERAL'!$C:$D,2,FALSE)) | X14: =IF('Registrar bienes de inversión'!X14="","",'Registrar bienes de inversión'!X14) | Y14: =IF('Registrar bienes de inversión'!Y14="","",'Registrar bienes de inversión'!Y14) | Z14: =IF('Registrar bienes de inversión'!Z14="","",'Registrar bienes de inversión'!Z14) | AA14: =IF('Registrar bienes de inversión'!AA14="","",ROUND('Registrar bienes de inversión'!AA14,2)) | AB14: =IF('Registrar bienes de inversión'!AB14="","",'Registrar bienes de inversión'!AB14) | AC14: =IF('Registrar bienes de inversión'!AC14="","",ROUND('Registrar bienes de inversión'!AC14,2)) | AD14: =IF('Registrar bienes de inversión'!AD14="","",ROUND('Registrar bienes de inversión'!AD14,2)) | AE14: =IF('Registrar bienes de inversión'!AE14="","",ROUND('Registrar bienes de inversión'!AE14,2)) | AF14: =IF('Registrar bienes de inversión'!AF14="","",ROUND('Registrar bienes de inversión'!AF14,2)) | AG14: =IF('Registrar bienes de inversión'!AG14="","",ROUND('Registrar bienes de inversión'!AG14,2)) | AH14: =IF('Registrar bienes de inversión'!AH14="","",'Registrar bienes de inversión'!AH14) | AI14: =IF('Registrar bienes de inversión'!AI14="","",VLOOKUP(CONCATENATE("CAUSA BAJA BIEN",'Registrar bienes de inversión'!AI14),'CODIGO-LITERAL'!$C:$D,2,FALSE)) | AJ14: =IF('Registrar bienes de inversión'!AJ14="","",'Registrar bienes de inversión'!AJ14) | AK14: =IF('Registrar bienes de inversión'!AK14="","",'Registrar bienes de inversión'!AK14) | AL14: =IF('Registrar bienes de inversión'!AL14="","",'Registrar bienes de inversión'!AL14) | AM14: =IF('Registrar bienes de inversión'!AM14="","",'Registrar bienes de inversión'!AM14) | AN14: =IF('Registrar bienes de inversión'!AN14="","",VLOOKUP(CONCATENATE("SITUACION",'Registrar bienes de inversión'!AN14),'CODIGO-LITERAL'!$C:$D,2,FALSE)) | AO14: =IF('Registrar bienes de inversión'!AO14="","",'Registrar bienes de inversión'!AO14) | AP14: =IF('Registrar bienes de inversión'!AP14="","",'Registrar bienes de inversión'!AP14)
A15: =IF('Registrar bienes de inversión'!A15="","",'Registrar bienes de inversión'!A15) | B15: =IF('Registrar bienes de inversión'!B15="","",'Registrar bienes de inversión'!B15) | C15: =IF('Registrar bienes de inversión'!C15="","",VLOOKUP(CONCATENATE("ACTIVIDAD",'Registrar bienes de inversión'!C15),'CODIGO-LITERAL'!$C:$D,2,FALSE)) | D15: =IF(OR(C15="C",C15="D"),"",IF(ISERROR(VLOOKUP(CONCATENATE(C15,'Registrar bienes de inversión'!D15),'CODIGO-LITERAL'!$C:$D,2,FALSE)),"",VLOOKUP(CONCATENATE(C15,'Registrar bienes de inversión'!D15),'CODIGO-LITERAL'!$C:$D,2,FALSE))) | E15: =IF('Registrar bienes de inversión'!E15="","",'Registrar bienes de inversión'!E15) | F15: =IF('Registrar bienes de inversión'!F15="","",VLOOKUP(CONCATENATE("TIPO BIEN",'Registrar bienes de inversión'!F15),'CODIGO-LITERAL'!$C:$D,2,FALSE)) | G15: =IF('Registrar bienes de inversión'!G15="","",'Registrar bienes de inversión'!G15) | H15: =IF('Registrar bienes de inversión'!H15="","",'Registrar bienes de inversión'!H15) | I15: =IF('Registrar bienes de inversión'!I15="","",'Registrar bienes de inversión'!I15) | J15: =IF('Registrar bienes de inversión'!J15="","",'Registrar bienes de inversión'!J15) | K15: =IF('Registrar bienes de inversión'!K15="","",'Registrar bienes de inversión'!K15) | L15: =IF('Registrar bienes de inversión'!L15="","",VLOOKUP(CONCATENATE("METODO AMORTIZACION",'Registrar bienes de inversión'!L15),'CODIGO-LITERAL'!$C:$D,2,FALSE)) | M15: =IF('Registrar bienes de inversión'!M15="","",'Registrar bienes de inversión'!M15) | N15: =IF('Registrar bienes de inversión'!N15="","",'Registrar bienes de inversión'!N15) | O15: =IF('Registrar bienes de inversión'!O15="","",'Registrar bienes de inversión'!O15) | P15: =IF('Registrar bienes de inversión'!P15="","",'Registrar bienes de inversión'!P15) | Q15: =IF('Registrar bienes de inversión'!Q15="","",'Registrar bienes de inversión'!Q15) | R15: =IF('Registrar bienes de inversión'!R15="","",'Registrar bienes de inversión'!R15) | S15: =IF('Registrar bienes de inversión'!S15="","",'Registrar bienes de inversión'!S15) | T15: =IF('Registrar bienes de inversión'!T15="","",'Registrar bienes de inversión'!T15) | ... V15: =IF('Registrar bienes de inversión'!V15="","",'Registrar bienes de inversión'!V15) | W15: =IF(OR('Registrar bienes de inversión'!W15="",LEFT('Registrar bienes de inversión'!W15,2)="01"),"",VLOOKUP(CONCATENATE("TIPO NIF",'Registrar bienes de inversión'!W15),'CODIGO-LITERAL'!$C:$D,2,FALSE)) | X15: =IF('Registrar bienes de inversión'!X15="","",'Registrar bienes de inversión'!X15) | Y15: =IF('Registrar bienes de inversión'!Y15="","",'Registrar bienes de inversión'!Y15) | Z15: =IF('Registrar bienes de inversión'!Z15="","",'Registrar bienes de inversión'!Z15) | AA15: =IF('Registrar bienes de inversión'!AA15="","",ROUND('Registrar bienes de inversión'!AA15,2)) | AB15: =IF('Registrar bienes de inversión'!AB15="","",'Registrar bienes de inversión'!AB15) | AC15: =IF('Registrar bienes de inversión'!AC15="","",ROUND('Registrar bienes de inversión'!AC15,2)) | AD15: =IF('Registrar bienes de inversión'!AD15="","",ROUND('Registrar bienes de inversión'!AD15,2)) | AE15: =IF('Registrar bienes de inversión'!AE15="","",ROUND('Registrar bienes de inversión'!AE15,2)) | AF15: =IF('Registrar bienes de inversión'!AF15="","",ROUND('Registrar bienes de inversión'!AF15,2)) | AG15: =IF('Registrar bienes de inversión'!AG15="","",ROUND('Registrar bienes de inversión'!AG15,2)) | AH15: =IF('Registrar bienes de inversión'!AH15="","",'Registrar bienes de inversión'!AH15) | AI15: =IF('Registrar bienes de inversión'!AI15="","",VLOOKUP(CONCATENATE("CAUSA BAJA BIEN",'Registrar bienes de inversión'!AI15),'CODIGO-LITERAL'!$C:$D,2,FALSE)) | AJ15: =IF('Registrar bienes de inversión'!AJ15="","",'Registrar bienes de inversión'!AJ15) | AK15: =IF('Registrar bienes de inversión'!AK15="","",'Registrar bienes de inversión'!AK15) | AL15: =IF('Registrar bienes de inversión'!AL15="","",'Registrar bienes de inversión'!AL15) | AM15: =IF('Registrar bienes de inversión'!AM15="","",'Registrar bienes de inversión'!AM15) | AN15: =IF('Registrar bienes de inversión'!AN15="","",VLOOKUP(CONCATENATE("SITUACION",'Registrar bienes de inversión'!AN15),'CODIGO-LITERAL'!$C:$D,2,FALSE)) | AO15: =IF('Registrar bienes de inversión'!AO15="","",'Registrar bienes de inversión'!AO15) | AP15: =IF('Registrar bienes de inversión'!AP15="","",'Registrar bienes de inversión'!AP15)
... A103: =IF('Registrar bienes de inversión'!A103="","",'Registrar bienes de inversión'!A103) | B103: =IF('Registrar bienes de inversión'!B103="","",'Registrar bienes de inversión'!B103) | C103: =IF('Registrar bienes de inversión'!C103="","",VLOOKUP(CONCATENATE("ACTIVIDAD",'Registrar bienes de inversión'!C103),'CODIGO-LITERAL'!$C:$D,2,FALSE)) | D103: =IF(OR(C103="C",C103="D"),"",IF(ISERROR(VLOOKUP(CONCATENATE(C103,'Registrar bienes de inversión'!D103),'CODIGO-LITERAL'!$C:$D,2,FALSE)),"",VLOOKUP(CONCATENATE(C103,'Registrar bienes de inversión'!D103),'CODIGO-LITERAL'!$C:$D,2,FALSE))) | E103: =IF('Registrar bienes de inversión'!E103="","",'Registrar bienes de inversión'!E103) | F103: =IF('Registrar bienes de inversión'!F103="","",VLOOKUP(CONCATENATE("TIPO BIEN",'Registrar bienes de inversión'!F103),'CODIGO-LITERAL'!$C:$D,2,FALSE)) | G103: =IF('Registrar bienes de inversión'!G103="","",'Registrar bienes de inversión'!G103) | H103: =IF('Registrar bienes de inversión'!H103="","",'Registrar bienes de inversión'!H103) | I103: =IF('Registrar bienes de inversión'!I103="","",'Registrar bienes de inversión'!I103) | J103: =IF('Registrar bienes de inversión'!J103="","",'Registrar bienes de inversión'!J103) | K103: =IF('Registrar bienes de inversión'!K103="","",'Registrar bienes de inversión'!K103) | L103: =IF('Registrar bienes de inversión'!L103="","",VLOOKUP(CONCATENATE("METODO AMORTIZACION",'Registrar bienes de inversión'!L103),'CODIGO-LITERAL'!$C:$D,2,FALSE)) | M103: =IF('Registrar bienes de inversión'!M103="","",'Registrar bienes de inversión'!M103) | N103: =IF('Registrar bienes de inversión'!N103="","",'Registrar bienes de inversión'!N103) | O103: =IF('Registrar bienes de inversión'!O103="","",'Registrar bienes de inversión'!O103) | P103: =IF('Registrar bienes de inversión'!P103="","",'Registrar bienes de inversión'!P103) | Q103: =IF('Registrar bienes de inversión'!Q103="","",'Registrar bienes de inversión'!Q103) | R103: =IF('Registrar bienes de inversión'!R103="","",'Registrar bienes de inversión'!R103) | S103: =IF('Registrar bienes de inversión'!S103="","",'Registrar bienes de inversión'!S103) | T103: =IF('Registrar bienes de inversión'!T103="","",'Registrar bienes de inversión'!T103) | ... V103: =IF('Registrar bienes de inversión'!V103="","",'Registrar bienes de inversión'!V103) | W103: =IF(OR('Registrar bienes de inversión'!W103="",LEFT('Registrar bienes de inversión'!W103,2)="01"),"",VLOOKUP(CONCATENATE("TIPO NIF",'Registrar bienes de inversión'!W103),'CODIGO-LITERAL'!$C:$D,2,FALSE)) | X103: =IF('Registrar bienes de inversión'!X103="","",'Registrar bienes de inversión'!X103) | Y103: =IF('Registrar bienes de inversión'!Y103="","",'Registrar bienes de inversión'!Y103) | Z103: =IF('Registrar bienes de inversión'!Z103="","",'Registrar bienes de inversión'!Z103) | AA103: =IF('Registrar bienes de inversión'!AA103="","",ROUND('Registrar bienes de inversión'!AA103,2)) | AB103: =IF('Registrar bienes de inversión'!AB103="","",'Registrar bienes de inversión'!AB103) | AC103: =IF('Registrar bienes de inversión'!AC103="","",ROUND('Registrar bienes de inversión'!AC103,2)) | AD103: =IF('Registrar bienes de inversión'!AD103="","",ROUND('Registrar bienes de inversión'!AD103,2)) | AE103: =IF('Registrar bienes de inversión'!AE103="","",ROUND('Registrar bienes de inversión'!AE103,2)) | AF103: =IF('Registrar bienes de inversión'!AF103="","",ROUND('Registrar bienes de inversión'!AF103,2)) | AG103: =IF('Registrar bienes de inversión'!AG103="","",ROUND('Registrar bienes de inversión'!AG103,2)) | AH103: =IF('Registrar bienes de inversión'!AH103="","",'Registrar bienes de inversión'!AH103) | AI103: =IF('Registrar bienes de inversión'!AI103="","",VLOOKUP(CONCATENATE("CAUSA BAJA BIEN",'Registrar bienes de inversión'!AI103),'CODIGO-LITERAL'!$C:$D,2,FALSE)) | AJ103: =IF('Registrar bienes de inversión'!AJ103="","",'Registrar bienes de inversión'!AJ103) | AK103: =IF('Registrar bienes de inversión'!AK103="","",'Registrar bienes de inversión'!AK103) | AL103: =IF('Registrar bienes de inversión'!AL103="","",'Registrar bienes de inversión'!AL103) | AM103: =IF('Registrar bienes de inversión'!AM103="","",'Registrar bienes de inversión'!AM103) | AN103: =IF('Registrar bienes de inversión'!AN103="","",VLOOKUP(CONCATENATE("SITUACION",'Registrar bienes de inversión'!AN103),'CODIGO-LITERAL'!$C:$D,2,FALSE)) | AO103: =IF('Registrar bienes de inversión'!AO103="","",'Registrar bienes de inversión'!AO103) | AP103: =IF('Registrar bienes de inversión'!AP103="","",'Registrar bienes de inversión'!AP103)

Sheet CODIGO-LITERAL
A1: A | B1: 01-Arrendadores de bienes inmuebles | C1: =CONCATENATE(A1,B1) -> A01-Arrendadores de bienes inmuebles | D1: 01 | E1: =CONCATENATE(D1,"-",B1) -> 01-01-Arrendadores de bienes inmuebles
A2: A | B2: 02-Ganadería independiente | C2: =CONCATENATE(A2,B2) -> A02-Ganadería independiente | D2: 02 | E2: =CONCATENATE(D2,"-",B2) -> 02-02-Ganadería independiente
A3: A | B3: 03-Resto de actividades empresariales no incluidas en los dos subtipos anteriores | C3: =CONCATENATE(A3,B3) -> A03-Resto de actividades empresariales no incluidas en los dos subtipos anteriores | D3: 03 | E3: =CONCATENATE(D3,"-",B3) -> 03-03-Resto de actividades empresariales no incluidas en los dos subtipos anteriores
A4: A | B4: 04-Actividades profesionales de carácter artístico o deportivo | C4: =CONCATENATE(A4,B4) -> A04-Actividades profesionales de carácter artístico o deportivo | D4: 04 | E4: =CONCATENATE(D4,"-",B4) -> 04-04-Actividades profesionales de carácter artístico o deportivo
A5: A | B5: 05-Resto de actividades profesionales | C5: =CONCATENATE(A5,B5) -> A05-Resto de actividades profesionales | D5: 05 | E5: =CONCATENATE(D5,"-",B5) -> 05-05-Resto de actividades profesionales
A6: ACTIVIDAD | B6: A-Actividades incluidas en el I.A.E. | C6: =CONCATENATE(A6,B6) -> ACTIVIDADA-Actividades incluidas en el I.A.E. | D6: A | E6: =CONCATENATE(D6,"-",B6) -> A-A-Actividades incluidas en el I.A.E.
A7: ACTIVIDAD | B7: B-Actividades no incluidas en el I.A.E. | C7: =CONCATENATE(A7,B7) -> ACTIVIDADB-Actividades no incluidas en el I.A.E. | D7: B | E7: =CONCATENATE(D7,"-",B7) -> B-B-Actividades no incluidas en el I.A.E.
A8: ACTIVIDAD | B8: C-Actividades no iniciadas | C8: =CONCATENATE(A8,B8) -> ACTIVIDADC-Actividades no iniciadas | D8: C | E8: =CONCATENATE(D8,"-",B8) -> C-C-Actividades no iniciadas
A9: ACTIVIDAD | B9: D-Arrendadores de inmuebles no incluidos en los códigos anteriores | C9: =CONCATENATE(A9,B9) -> ACTIVIDADD-Arrendadores de inmuebles no incluidos en los códigos anteriores | D9: D | E9: =CONCATENATE(D9,"-",B9) -> D-D-Arrendadores de inmuebles no incluidos en los códigos anteriores
A10: B | B10: 01-Actividad agrícola | C10: =CONCATENATE(A10,B10) -> B01-Actividad agrícola | D10: 01 | E10: =CONCATENATE(D10,"-",B10) -> 01-01-Actividad agrícola
A11: B | B11: 02-Actividad ganadera dependiente | C11: =CONCATENATE(A11,B11) -> B02-Actividad ganadera dependiente | D11: 02 | E11: =CONCATENATE(D11,"-",B11) -> 02-02-Actividad ganadera dependiente
A12: B | B12: 03-Actividad forestal | C12: =CONCATENATE(A12,B12) -> B03-Actividad forestal | D12: 03 | E12: =CONCATENATE(D12,"-",B12) -> 03-03-Actividad forestal
... A161: TIPO FACTURA | B161: AJ-Asiento para realizar los ajustes periódicos que reflejen el correspondiente impuesto devengado incluido en la liquidación del impuesto | C161: =CONCATENATE(A161,B161) -> TIPO FACTURAAJ-Asiento para realizar los ajustes periódicos que reflejen el correspondiente impuesto devengado incluido en la liquidación del impuesto | D161: AJ | E161: =CONCATENATE(D161,"-",B161) -> AJ-AJ-Asiento para realizar los ajustes periódicos que reflejen el correspondiente impuesto devengado incluido en la liquidación del impuesto
A162: TIPO NIF | B162: 01-NIF/NIE | C162: =CONCATENATE(A162,B162) -> TIPO NIF01-NIF/NIE | E162: =CONCATENATE(D162,"-",B162) -> -01-NIF/NIE
A163: TIPO NIF | B163: 02-NIF-IVA intracomunitario | C163: =CONCATENATE(A163,B163) -> TIPO NIF02-NIF-IVA intracomunitario | D163: 02 | E163: =CONCATENATE(D163,"-",B163) -> 02-02-NIF-IVA intracomunitario
A164: TIPO NIF | B164: 03-Pasaporte | C164: =CONCATENATE(A164,B164) -> TIPO NIF03-Pasaporte | D164: 03 | E164: =CONCATENATE(D164,"-",B164) -> 03-03-Pasaporte
A165: TIPO NIF | B165: 04-Documento oficial de identificación expedido por el país o territorio de residencia. | C165: =CONCATENATE(A165,B165) -> TIPO NIF04-Documento oficial de identificación expedido por el país o territorio de residencia. | D165: 04 | E165: =CONCATENATE(D165,"-",B165) -> 04-04-Documento oficial de identificación expedido por el país o territorio de residencia.
A166: TIPO NIF | B166: 05-Certificado de Residencia. | C166: =CONCATENATE(A166,B166) -> TIPO NIF05-Certificado de Residencia. | D166: 05 | E166: =CONCATENATE(D166,"-",B166) -> 05-05-Certificado de Residencia.
A167: TIPO NIF | B167: 06-Otro documento probatorio. | C167: =CONCATENATE(A167,B167) -> TIPO NIF06-Otro documento probatorio. | D167: 06 | E167: =CONCATENATE(D167,"-",B167) -> 06-06-Otro documento probatorio.
A168: TRIMESTRE | B168: 1T | C168: =CONCATENATE(A168,B168) -> TRIMESTRE1T | D168: 1T | E168: =CONCATENATE(D168,"-",B168) -> 1T-1T
A169: TRIMESTRE | B169: 2T | C169: =CONCATENATE(A169,B169) -> TRIMESTRE2T | D169: 2T | E169: =CONCATENATE(D169,"-",B169) -> 2T-2T
A170: TRIMESTRE | B170: 3T | C170: =CONCATENATE(A170,B170) -> TRIMESTRE3T | D170: 3T | E170: =CONCATENATE(D170,"-",B170) -> 3T-3T
A171: TRIMESTRE | B171: 4T | C171: =CONCATENATE(A171,B171) -> TRIMESTRE4T | D171: 4T | E171: =CONCATENATE(D171,"-",B171) -> 4T-4T
A172: TIPO IVA | B172: 21 | C172: =CONCATENATE(A172,B172) -> TIPO IVA21 | D172: 21
A173: TIPO IVA | B173: 10 | C173: =CONCATENATE(A173,B173) -> TIPO IVA10 | D173: 10
A174: TIPO IVA | B174: 4 | C174: =CONCATENATE(A174,B174) -> TIPO IVA4 | D174: 4
A175: TIPO IVA | B175: 0 | C175: =CONCATENATE(A175,B175) -> TIPO IVA0 | D175: 0
A176: TIPO IVA | B176: 2 | C176: =CONCATENATE(A176,B176) -> TIPO IVA2 | D176: 2
A177: TIPO IVA | B177: 5 | C177: =CONCATENATE(A177,B177) -> TIPO IVA5 | D177: 5
A178: TIPO IVA | B178: 7.5 | C178: =CONCATENATE(A178,B178) -> TIPO IVA7,5 | D178: 7.5
A179: TIPO IVA | B179: 10.5 | C179: =CONCATENATE(A179,B179) -> TIPO IVA10,5 | D179: 10.5
A180: TIPO IVA | B180: 12 | C180: =CONCATENATE(A180,B180) -> TIPO IVA12 | D180: 12
A181: TIPO RECARGO EQUIVALENCIA | B181: 5.2 | C181: =CONCATENATE(A181,B181) -> TIPO RECARGO EQUIVALENCIA5,2 | D181: 5.2
A182: TIPO RECARGO EQUIVALENCIA | B182: 1.4 | C182: =CONCATENATE(A182,B182) -> TIPO RECARGO EQUIVALENCIA1,4 | D182: 1.4
A183: TIPO RECARGO EQUIVALENCIA | B183: 0.5 | C183: =CONCATENATE(A183,B183) -> TIPO RECARGO EQUIVALENCIA0,5 | D183: 0.5
... A186: TIPO RECARGO EQUIVALENCIA | B186: 0 | C186: =CONCATENATE(A186,B186) -> TIPO RECARGO EQUIVALENCIA0 | D186: 0
A191: TIPO FACTURA GASTO | B191: F1-Factura en la que se identifica al destinatario | C191: =CONCATENATE(A191,B191) -> TIPO FACTURA GASTOF1-Factura en la que se identifica al destinatario | D191: F1 | E191: =LEFT(C191,2) -> TI | F191: =RIGHT(C191,LEN(C191)-4) -> FACTURA GASTOF1-Factura en la que se identifica al destinatario
A192: TIPO FACTURA GASTO | B192: F2-Factura sin identificación del destinatario | C192: =CONCATENATE(A192,B192) -> TIPO FACTURA GASTOF2-Factura sin identificación del destinatario | D192: F2 | E192: =LEFT(C192,2) -> TI | F192: =RIGHT(C192,LEN(C192)-4) -> FACTURA GASTOF2-Factura sin identificación del destinatario
A193: TIPO FACTURA GASTO | B193: F3-Factura sustitutiva sin una anotación negativa que anule las facturas simplificadas a las que sustituye. Sólo utilizarán este tipo aquellos obligados que registren facturas en sustitución de facturas simplificadas. | C193: =CONCATENATE(A193,B193) -> TIPO FACTURA GASTOF3-Factura sustitutiva sin una anotación negativa que anule las facturas simplificadas a las que sustituye. Sólo utilizarán este tipo aquellos obligados que registren facturas en sustitución de facturas simplificadas. | D193: F3 | E193: =LEFT(C193,2) -> TI | F193: =RIGHT(C193,LEN(C193)-4) -> FACTURA GASTOF3-Factura sustitutiva sin una anotación negativa que anule las facturas simplificadas a las que sustituye. Sólo utilizarán este tipo aquellos obligados que registren facturas en sustitución de facturas simplificadas.
A194: TIPO FACTURA GASTO | B194: F4-Asiento resumen de facturas | C194: =CONCATENATE(A194,B194) -> TIPO FACTURA GASTOF4-Asiento resumen de facturas | D194: F4 | E194: =LEFT(C194,2) -> TI | F194: =RIGHT(C194,LEN(C194)-4) -> FACTURA GASTOF4-Asiento resumen de facturas
A195: TIPO FACTURA GASTO | B195: F5-Importaciones (DUA) | C195: =CONCATENATE(A195,B195) -> TIPO FACTURA GASTOF5-Importaciones (DUA) | D195: F5 | E195: =LEFT(C195,2) -> TI | F195: =RIGHT(C195,LEN(C195)-4) -> FACTURA GASTOF5-Importaciones (DUA)
A196: TIPO FACTURA GASTO | B196: F6-Justificantes contables | C196: =CONCATENATE(A196,B196) -> TIPO FACTURA GASTOF6-Justificantes contables | D196: F6 | E196: =LEFT(C196,2) -> TI | F196: =RIGHT(C196,LEN(C196)-4) -> FACTURA GASTOF6-Justificantes contables
A197: TIPO FACTURA GASTO | B197: R1-Factura Rectificativa (Error fundado en derecho y Art. 80 Uno Dos y Seis LIVA) | C197: =CONCATENATE(A197,B197) -> TIPO FACTURA GASTOR1-Factura Rectificativa (Error fundado en derecho y Art. 80 Uno Dos y Seis LIVA) | D197: R1 | E197: =LEFT(C197,2) -> TI | F197: =RIGHT(C197,LEN(C197)-4) -> FACTURA GASTOR1-Factura Rectificativa (Error fundado en derecho y Art. 80 Uno Dos y Seis LIVA)
A198: TIPO FACTURA GASTO | B198: R2-Factura Rectificativa (Art. 80.tres, por concurso de acreedores) | C198: =CONCATENATE(A198,B198) -> TIPO FACTURA GASTOR2-Factura Rectificativa (Art. 80.tres, por concurso de acreedores) | D198: R2 | E198: =LEFT(C198,2) -> TI | F198: =RIGHT(C198,LEN(C198)-4) -> FACTURA GASTOR2-Factura Rectificativa (Art. 80.tres, por concurso de acreedores)
A199: TIPO FACTURA GASTO | B199: R3-Factura Rectificativa (Art. 80.cuatro, por crédito incobrable) | C199: =CONCATENATE(A199,B199) -> TIPO FACTURA GASTOR3-Factura Rectificativa (Art. 80.cuatro, por crédito incobrable) | D199: R3 | E199: =LEFT(C199,2) -> TI | F199: =RIGHT(C199,LEN(C199)-4) -> FACTURA GASTOR3-Factura Rectificativa (Art. 80.cuatro, por crédito incobrable)
A200: TIPO FACTURA GASTO | B200: R4-Factura Rectificativa (Resto) | C200: =CONCATENATE(A200,B200) -> TIPO FACTURA GASTOR4-Factura Rectificativa (Resto) | D200: R4 | E200: =LEFT(C200,2) -> TI | F200: =RIGHT(C200,LEN(C200)-4) -> FACTURA GASTOR4-Factura Rectificativa (Resto)
A201: TIPO FACTURA GASTO | B201: R5-Factura Rectificativa en facturas simplificadas y facturas sin identificación del destinatario | C201: =CONCATENATE(A201,B201) -> TIPO FACTURA GASTOR5-Factura Rectificativa en facturas simplificadas y facturas sin identificación del destinatario | D201: R5 | E201: =LEFT(C201,2) -> TI | F201: =RIGHT(C201,LEN(C201)-4) -> FACTURA GASTOR5-Factura Rectificativa en facturas simplificadas y facturas sin identificación del destinatario
A202: TIPO FACTURA GASTO | B202: LC-Aduanas - Liquidación complementaria | C202: =CONCATENATE(A202,B202) -> TIPO FACTURA GASTOLC-Aduanas - Liquidación complementaria | D202: LC | E202: =LEFT(C202,2) -> TI | F202: =RIGHT(C202,LEN(C202)-4) -> FACTURA GASTOLC-Aduanas - Liquidación complementaria
A203: TIPO FACTURA GASTO | B203: SF-Asiento sin obligación de emitir factura. En caso del libro del IVA, este valor sólo se podrá utilizar para el asiento por ajuste de la prorrata y sólo lleva cuota. | C203: =CONCATENATE(A203,B203) -> TIPO FACTURA GASTOSF-Asiento sin obligación de emitir factura. En caso del libro del IVA, este valor sólo se podrá utilizar para el asiento por ajuste de la prorrata y sólo lleva cuota. | D203: SF | E203: =LEFT(C203,2) -> TI | F203: =RIGHT(C203,LEN(C203)-4) -> FACTURA GASTOSF-Asiento sin obligación de emitir factura. En caso del libro del IVA, este valor sólo se podrá utilizar para el asiento por ajuste de la prorrata y sólo lleva cuota.
A204: METODO AMORTIZACION | B204: 01-Sistema de amortización lineal según tablas. | C204: =CONCATENATE(A204,B204) -> METODO AMORTIZACION01-Sistema de amortización lineal según tablas. | D204: =LEFT(B204,2) -> 01
A205: METODO AMORTIZACION | B205: 02-Sistema de amortización según porcentaje constante sobre el importe pendiente de amortización | C205: =CONCATENATE(A205,B205) -> METODO AMORTIZACION02-Sistema de amortización según porcentaje constante sobre el importe pendiente de amortización | D205: =LEFT(B205,2) -> 02
A206: METODO AMORTIZACION | B206: 03-Sistema de amortización según número dígitos. | C206: =CONCATENATE(A206,B206) -> METODO AMORTIZACION03-Sistema de amortización según número dígitos. | D206: =LEFT(B206,2) -> 03
A207: METODO AMORTIZACION | B207: 04-Planes de amortización | C207: =CONCATENATE(A207,B207) -> METODO AMORTIZACION04-Planes de amortización | D207: =LEFT(B207,2) -> 04
A208: METODO AMORTIZACION | B208: 05-Depreciación efectiva probada fehacientemente | C208: =CONCATENATE(A208,B208) -> METODO AMORTIZACION05-Depreciación efectiva probada fehacientemente | D208: =LEFT(B208,2) -> 05
A209: METODO AMORTIZACION | B209: 06-Libertad de Amortización | C209: =CONCATENATE(A209,B209) -> METODO AMORTIZACION06-Libertad de Amortización | D209: =LEFT(B209,2) -> 06
A210: METODO AMORTIZACION | B210: 07-Amortización Acelerada | C210: =CONCATENATE(A210,B210) -> METODO AMORTIZACION07-Amortización Acelerada | D210: =LEFT(B210,2) -> 07
A211: METODO AMORTIZACION | B211: 08-Amortización de Elementos Adquiridos Usados | C211: =CONCATENATE(A211,B211) -> METODO AMORTIZACION08-Amortización de Elementos Adquiridos Usados | D211: =LEFT(B211,2) -> 08
